Workbook

Sheet Summary
A1: 500-Lead Acquisition Plan — Summary
A2: Date | B2: 2026-10-13
A3: Status of numbers | B3: ILLUSTRATIVE. CPLs are third-party vendor estimates; every rate is an assumption you can edit on "Inputs (assumptions)". Replace with results from a 2–3 week test campaign.
A5: Three different targets
A6: 500 raw leads | B6: Google ₹4.7 L–₹11.8 L; Meta ₹3 L–₹8.9 L (incl. 18% GST assumption)
A7: 500 valid contacts | B7: Google ₹5.2 L–₹14.6 L; Meta ₹3.5 L–₹14.1 L
A8: 500 qualified ₹1 Cr+ buyers | B8: Google ₹13.1 L–₹73.1 L (base ₹29.6 L); Meta ₹11.8 L–₹1.4 Cr (base ₹35.7 L)
A9: 500 call-ready (qualified + call consent) | B9: Google ₹15.4 L–₹1.2 Cr (base ₹39.5 L); Meta ₹14.7 L–₹2.8 Cr (base ₹54.9 L)
A11: Best low-cost option | B11: Meta Lead Ads — lowest CPL for raw volume, but lowest quality; use a higher-intent form, budget/BHK/timeline questions and an optional call-consent box.
A12: Best quality option | B12: Google Search ads on locality + BHK + "price" keywords to a Mappingg landing page with your own consent wording (and OTP).
A13: Fastest legitimate route | B13: Run Google Search + Meta in parallel from day 1 (after fixing consent capture). At ₹10,000/day, 500 RAW leads takes roughly 54 (Meta base) to 77 (Google base) days; 500 QUALIFIED takes far longer unless the daily budget rises — see Scenario Calculator.
A14: Portals | B14: Supplementary only: 99acres/Magicbricks/Housing volumes are not guaranteed and pricing is quote-only. Do not count on them for the 500.
A15: Pre-requisites | B15: 1) Fix website consent capture (separate approved code task). 2) MahaRERA agent registration number/QR on ads. 3) Privacy policy covering ad leads. 4) 140-series/registered telemarketing set-up and DND scrub before promotional calls (legal confirmation).

Sheet Inputs (assumptions)
A1: ILLUSTRATIVE ASSUMPTIONS — yellow cells are inputs. Replace with real numbers from a test campaign.
A3: Global inputs | B3: Value | E3: Basis
A4: Target count | B4: 500 | E4: Your goal
A5: GST on ad spend (confirm on invoice) | B5: 0.18 | E5: Assumption — Meta/Google India invoices typically add GST; confirm
A6: Daily ad budget (₹) | B6: 10000 | E6: Your choice — drives time to target
A8: Google Search → landing page / lead form | B8: Conservative | C8: Base | D8: Optimistic | E8: Basis
A9: CPL — cost per raw lead (₹, ex-GST) | B9: 2000 | C9: 1300 | D9: 800 | E9: Third-party range ₹300–2,500 (Sell.do) / ₹800–2,000 (OwlClaw); ₹1 Cr+ keywords assumed toward upper half
A10: Valid phone rate (format valid + reachable) | B10: 0.85 | C10: 0.9 | D10: 0.93 | E10: Assumption. Meta pre-fill → more wrong/unused numbers; Search users type their number
A11: Duplicate rate | B11: 0.05 | C11: 0.04 | D11: 0.03 | E11: Assumption (repeat submissions, overlap with CRM)
A12: Qualified rate among valid (Pune/MMR + ₹1 Cr+ + 1–3 BHK + timeline ≠ exploring) | B12: 0.2 | C12: 0.3 | D12: 0.4 | E12: Assumption. OwlClaw reports 15–25% (Meta) / 25–40% (Google) lead-to-call — used as a loose anchor only
A13: Call-consent opt-in rate among qualified (optional unticked box) | B13: 0.6 | C13: 0.75 | D13: 0.85 | E13: Assumption — unknown until tested
A15: Meta Lead Ads (higher-intent form + custom questions) | B15: Conservative | C15: Base | D15: Optimistic | E15: Basis
A16: CPL — cost per raw lead (₹, ex-GST) | B16: 1500 | C16: 900 | D16: 500 | E16: Third-party range ₹150–2,000 (Sell.do) / ₹500–1,500 (OwlClaw); higher-intent form raises CPL
A17: Valid phone rate (format valid + reachable) | B17: 0.7 | C17: 0.8 | D17: 0.88 | E17: Assumption. Meta pre-fill → more wrong/unused numbers; Search users type their number
A18: Duplicate rate | B18: 0.1 | C18: 0.07 | D18: 0.05 | E18: Assumption (repeat submissions, overlap with CRM)
A19: Qualified rate among valid (Pune/MMR + ₹1 Cr+ + 1–3 BHK + timeline ≠ exploring) | B19: 0.1 | C19: 0.2 | D19: 0.3 | E19: Assumption. OwlClaw reports 15–25% (Meta) / 25–40% (Google) lead-to-call — used as a loose anchor only
A20: Call-consent opt-in rate among qualified (optional unticked box) | B20: 0.5 | C20: 0.65 | D20: 0.8 | E20: Assumption — unknown until tested

Sheet Scenario Calculator
A1: Google Search → landing page / lead form | B1: Conservative | C1: Base | D1: Optimistic | E1: Formula
A2: Cost for 500 RAW leads (₹ incl. GST) | B2: ='Inputs (assumptions)'!$B$4*'Inputs (assumptions)'!B9*(1+'Inputs (assumptions)'!$B$5) -> 1180000 | C2: ='Inputs (assumptions)'!$B$4*'Inputs (assumptions)'!C9*(1+'Inputs (assumptions)'!$B$5) -> 767000 | D2: ='Inputs (assumptions)'!$B$4*'Inputs (assumptions)'!D9*(1+'Inputs (assumptions)'!$B$5) -> 472000 | E2: Target × CPL × (1+GST)
A3: Valid, unique contacts from 500 raw | B3: =ROUND('Inputs (assumptions)'!$B$4*'Inputs (assumptions)'!B10*(1-'Inputs (assumptions)'!B11),0) -> 404 | C3: =ROUND('Inputs (assumptions)'!$B$4*'Inputs (assumptions)'!C10*(1-'Inputs (assumptions)'!C11),0) -> 432 | D3: =ROUND('Inputs (assumptions)'!$B$4*'Inputs (assumptions)'!D10*(1-'Inputs (assumptions)'!D11),0) -> 451 | E3: Target × valid × (1−dup)
A4: Raw leads needed for 500 VALID contacts | B4: =ROUNDUP('Inputs (assumptions)'!$B$4/('Inputs (assumptions)'!B10*(1-'Inputs (assumptions)'!B11)),0) -> 620 | C4: =ROUNDUP('Inputs (assumptions)'!$B$4/('Inputs (assumptions)'!C10*(1-'Inputs (assumptions)'!C11)),0) -> 579 | D4: =ROUNDUP('Inputs (assumptions)'!$B$4/('Inputs (assumptions)'!D10*(1-'Inputs (assumptions)'!D11)),0) -> 555 | E4: Target ÷ (valid × (1−dup))
A5: Cost for 500 VALID contacts (₹ incl. GST) | B5: =ROUNDUP('Inputs (assumptions)'!$B$4/('Inputs (assumptions)'!B10*(1-'Inputs (assumptions)'!B11)),0)*'Inputs (assumptions)'!B9*(1+'Inputs (assumptions)'!$B$5) -> 1463200 | C5: =ROUNDUP('Inputs (assumptions)'!$B$4/('Inputs (assumptions)'!C10*(1-'Inputs (assumptions)'!C11)),0)*'Inputs (assumptions)'!C9*(1+'Inputs (assumptions)'!$B$5) -> 888186 | D5: =ROUNDUP('Inputs (assumptions)'!$B$4/('Inputs (assumptions)'!D10*(1-'Inputs (assumptions)'!D11)),0)*'Inputs (assumptions)'!D9*(1+'Inputs (assumptions)'!$B$5) -> 523920 | E5: Raw needed × CPL × (1+GST)
A6: Qualified ₹1 Cr+ buyers from 500 raw | B6: =ROUND('Inputs (assumptions)'!$B$4*'Inputs (assumptions)'!B10*(1-'Inputs (assumptions)'!B11)*'Inputs (assumptions)'!B12,0) -> 81 | C6: =ROUND('Inputs (assumptions)'!$B$4*'Inputs (assumptions)'!C10*(1-'Inputs (assumptions)'!C11)*'Inputs (assumptions)'!C12,0) -> 130 | D6: =ROUND('Inputs (assumptions)'!$B$4*'Inputs (assumptions)'!D10*(1-'Inputs (assumptions)'!D11)*'Inputs (assumptions)'!D12,0) -> 180 | E6: Target × valid × (1−dup) × qualified
A7: Raw leads needed for 500 QUALIFIED buyers | B7: =ROUNDUP('Inputs (assumptions)'!$B$4/('Inputs (assumptions)'!B10*(1-'Inputs (assumptions)'!B11)*'Inputs (assumptions)'!B12),0) -> 3096 | C7: =ROUNDUP('Inputs (assumptions)'!$B$4/('Inputs (assumptions)'!C10*(1-'Inputs (assumptions)'!C11)*'Inputs (assumptions)'!C12),0) -> 1930 | D7: =ROUNDUP('Inputs (assumptions)'!$B$4/('Inputs (assumptions)'!D10*(1-'Inputs (assumptions)'!D11)*'Inputs (assumptions)'!D12),0) -> 1386 | E7: Target ÷ (valid × (1−dup) × qualified)
A8: Cost for 500 QUALIFIED buyers (₹ incl. GST) | B8: =ROUNDUP('Inputs (assumptions)'!$B$4/('Inputs (assumptions)'!B10*(1-'Inputs (assumptions)'!B11)*'Inputs (assumptions)'!B12),0)*'Inputs (assumptions)'!B9*(1+'Inputs (assumptions)'!$B$5) -> 7306560 | C8: =ROUNDUP('Inputs (assumptions)'!$B$4/('Inputs (assumptions)'!C10*(1-'Inputs (assumptions)'!C11)*'Inputs (assumptions)'!C12),0)*'Inputs (assumptions)'!C9*(1+'Inputs (assumptions)'!$B$5) -> 2960620 | D8: =ROUNDUP('Inputs (assumptions)'!$B$4/('Inputs (assumptions)'!D10*(1-'Inputs (assumptions)'!D11)*'Inputs (assumptions)'!D12),0)*'Inputs (assumptions)'!D9*(1+'Inputs (assumptions)'!$B$5) -> 1308384 | E8: Raw needed × CPL × (1+GST)
A9: Raw leads needed for 500 CALL-READY (qualified + call consent) | B9: =ROUNDUP('Inputs (assumptions)'!$B$4/('Inputs (assumptions)'!B10*(1-'Inputs (assumptions)'!B11)*'Inputs (assumptions)'!B12*'Inputs (assumptions)'!B13),0) -> 5160 | C9: =ROUNDUP('Inputs (assumptions)'!$B$4/('Inputs (assumptions)'!C10*(1-'Inputs (assumptions)'!C11)*'Inputs (assumptions)'!C12*'Inputs (assumptions)'!C13),0) -> 2573 | D9: =ROUNDUP('Inputs (assumptions)'!$B$4/('Inputs (assumptions)'!D10*(1-'Inputs (assumptions)'!D11)*'Inputs (assumptions)'!D12*'Inputs (assumptions)'!D13),0) -> 1631 | E9: … × call-consent rate
A10: Cost for 500 CALL-READY buyers (₹ incl. GST) | B10: =ROUNDUP('Inputs (assumptions)'!$B$4/('Inputs (assumptions)'!B10*(1-'Inputs (assumptions)'!B11)*'Inputs (assumptions)'!B12*'Inputs (assumptions)'!B13),0)*'Inputs (assumptions)'!B9*(1+'Inputs (assumptions)'!$B$5) -> 12177600 | C10: =ROUNDUP('Inputs (assumptions)'!$B$4/('Inputs (assumptions)'!C10*(1-'Inputs (assumptions)'!C11)*'Inputs (assumptions)'!C12*'Inputs (assumptions)'!C13),0)*'Inputs (assumptions)'!C9*(1+'Inputs (assumptions)'!$B$5) -> 3946982 | D10: =ROUNDUP('Inputs (assumptions)'!$B$4/('Inputs (assumptions)'!D10*(1-'Inputs (assumptions)'!D11)*'Inputs (assumptions)'!D12*'Inputs (assumptions)'!D13),0)*'Inputs (assumptions)'!D9*(1+'Inputs (assumptions)'!$B$5) -> 1539664 | E10: Raw needed × CPL × (1+GST)
A11: Days to 500 RAW at daily budget | B11: =ROUNDUP('Inputs (assumptions)'!$B$4*'Inputs (assumptions)'!B9*(1+'Inputs (assumptions)'!$B$5)/'Inputs (assumptions)'!$B$6,0) -> 118 | C11: =ROUNDUP('Inputs (assumptions)'!$B$4*'Inputs (assumptions)'!C9*(1+'Inputs (assumptions)'!$B$5)/'Inputs (assumptions)'!$B$6,0) -> 77 | D11: =ROUNDUP('Inputs (assumptions)'!$B$4*'Inputs (assumptions)'!D9*(1+'Inputs (assumptions)'!$B$5)/'Inputs (assumptions)'!$B$6,0) -> 48 | E11: Cost ÷ daily budget
A12: Days to 500 QUALIFIED at daily budget | B12: =ROUNDUP(ROUNDUP('Inputs (assumptions)'!$B$4/('Inputs (assumptions)'!B10*(1-'Inputs (assumptions)'!B11)*'Inputs (assumptions)'!B12),0)*'Inputs (assumptions)'!B9*(1+'Inputs (assumptions)'!$B$5)/'Inputs (assumptions)'!$B$6,0) -> 731 | C12: =ROUNDUP(ROUNDUP('Inputs (assumptions)'!$B$4/('Inputs (assumptions)'!C10*(1-'Inputs (assumptions)'!C11)*'Inputs (assumptions)'!C12),0)*'Inputs (assumptions)'!C9*(1+'Inputs (assumptions)'!$B$5)/'Inputs (assumptions)'!$B$6,0) -> 297 | D12: =ROUNDUP(ROUNDUP('Inputs (assumptions)'!$B$4/('Inputs (assumptions)'!D10*(1-'Inputs (assumptions)'!D11)*'Inputs (assumptions)'!D12),0)*'Inputs (assumptions)'!D9*(1+'Inputs (assumptions)'!$B$5)/'Inputs (assumptions)'!$B$6,0) -> 131 | E12: Cost ÷ daily budget
A14: Meta Lead Ads (higher-intent form + custom questions) | B14: Conservative | C14: Base | D14: Optimistic | E14: Formula
A15: Cost for 500 RAW leads (₹ incl. GST) | B15: ='Inputs (assumptions)'!$B$4*'Inputs (assumptions)'!B16*(1+'Inputs (assumptions)'!$B$5) -> 885000 | C15: ='Inputs (assumptions)'!$B$4*'Inputs (assumptions)'!C16*(1+'Inputs (assumptions)'!$B$5) -> 531000 | D15: ='Inputs (assumptions)'!$B$4*'Inputs (assumptions)'!D16*(1+'Inputs (assumptions)'!$B$5) -> 295000 | E15: Target × CPL × (1+GST)
A16: Valid, unique contacts from 500 raw | B16: =ROUND('Inputs (assumptions)'!$B$4*'Inputs (assumptions)'!B17*(1-'Inputs (assumptions)'!B18),0) -> 315 | C16: =ROUND('Inputs (assumptions)'!$B$4*'Inputs (assumptions)'!C17*(1-'Inputs (assumptions)'!C18),0) -> 372 | D16: =ROUND('Inputs (assumptions)'!$B$4*'Inputs (assumptions)'!D17*(1-'Inputs (assumptions)'!D18),0) -> 418 | E16: Target × valid × (1−dup)
A17: Raw leads needed for 500 VALID contacts | B17: =ROUNDUP('Inputs (assumptions)'!$B$4/('Inputs (assumptions)'!B17*(1-'Inputs (assumptions)'!B18)),0) -> 794 | C17: =ROUNDUP('Inputs (assumptions)'!$B$4/('Inputs (assumptions)'!C17*(1-'Inputs (assumptions)'!C18)),0) -> 673 | D17: =ROUNDUP('Inputs (assumptions)'!$B$4/('Inputs (assumptions)'!D17*(1-'Inputs (assumptions)'!D18)),0) -> 599 | E17: Target ÷ (valid × (1−dup))
A18: Cost for 500 VALID contacts (₹ incl. GST) | B18: =ROUNDUP('Inputs (assumptions)'!$B$4/('Inputs (assumptions)'!B17*(1-'Inputs (assumptions)'!B18)),0)*'Inputs (assumptions)'!B16*(1+'Inputs (assumptions)'!$B$5) -> 1405380 | C18: =ROUNDUP('Inputs (assumptions)'!$B$4/('Inputs (assumptions)'!C17*(1-'Inputs (assumptions)'!C18)),0)*'Inputs (assumptions)'!C16*(1+'Inputs (assumptions)'!$B$5) -> 714726 | D18: =ROUNDUP('Inputs (assumptions)'!$B$4/('Inputs (assumptions)'!D17*(1-'Inputs (assumptions)'!D18)),0)*'Inputs (assumptions)'!D16*(1+'Inputs (assumptions)'!$B$5) -> 353410 | E18: Raw needed × CPL × (1+GST)
A19: Qualified ₹1 Cr+ buyers from 500 raw | B19: =ROUND('Inputs (assumptions)'!$B$4*'Inputs (assumptions)'!B17*(1-'Inputs (assumptions)'!B18)*'Inputs (assumptions)'!B19,0) -> 32 | C19: =ROUND('Inputs (assumptions)'!$B$4*'Inputs (assumptions)'!C17*(1-'Inputs (assumptions)'!C18)*'Inputs (assumptions)'!C19,0) -> 74 | D19: =ROUND('Inputs (assumptions)'!$B$4*'Inputs (assumptions)'!D17*(1-'Inputs (assumptions)'!D18)*'Inputs (assumptions)'!D19,0) -> 125 | E19: Target × valid × (1−dup) × qualified
A20: Raw leads needed for 500 QUALIFIED buyers | B20: =ROUNDUP('Inputs (assumptions)'!$B$4/('Inputs (assumptions)'!B17*(1-'Inputs (assumptions)'!B18)*'Inputs (assumptions)'!B19),0) -> 7937 | C20: =ROUNDUP('Inputs (assumptions)'!$B$4/('Inputs (assumptions)'!C17*(1-'Inputs (assumptions)'!C18)*'Inputs (assumptions)'!C19),0) -> 3361 | D20: =ROUNDUP('Inputs (assumptions)'!$B$4/('Inputs (assumptions)'!D17*(1-'Inputs (assumptions)'!D18)*'Inputs (assumptions)'!D19),0) -> 1994 | E20: Target ÷ (valid × (1−dup) × qualified)
A21: Cost for 500 QUALIFIED buyers (₹ incl. GST) | B21: =ROUNDUP('Inputs (assumptions)'!$B$4/('Inputs (assumptions)'!B17*(1-'Inputs (assumptions)'!B18)*'Inputs (assumptions)'!B19),0)*'Inputs (assumptions)'!B16*(1+'Inputs (assumptions)'!$B$5) -> 14048490 | C21: =ROUNDUP('Inputs (assumptions)'!$B$4/('Inputs (assumptions)'!C17*(1-'Inputs (assumptions)'!C18)*'Inputs (assumptions)'!C19),0)*'Inputs (assumptions)'!C16*(1+'Inputs (assumptions)'!$B$5) -> 3569382 | D21: =ROUNDUP('Inputs (assumptions)'!$B$4/('Inputs (assumptions)'!D17*(1-'Inputs (assumptions)'!D18)*'Inputs (assumptions)'!D19),0)*'Inputs (assumptions)'!D16*(1+'Inputs (assumptions)'!$B$5) -> 1176460 | E21: Raw needed × CPL × (1+GST)
A22: Raw leads needed for 500 CALL-READY (qualified + call consent) | B22: =ROUNDUP('Inputs (assumptions)'!$B$4/('Inputs (assumptions)'!B17*(1-'Inputs (assumptions)'!B18)*'Inputs (assumptions)'!B19*'Inputs (assumptions)'!B20),0) -> 15874 | C22: =ROUNDUP('Inputs (assumptions)'!$B$4/('Inputs (assumptions)'!C17*(1-'Inputs (assumptions)'!C18)*'Inputs (assumptions)'!C19*'Inputs (assumptions)'!C20),0) -> 5170 | D22: =ROUNDUP('Inputs (assumptions)'!$B$4/('Inputs (assumptions)'!D17*(1-'Inputs (assumptions)'!D18)*'Inputs (assumptions)'!D19*'Inputs (assumptions)'!D20),0) -> 2493 | E22: … × call-consent rate
A23: Cost for 500 CALL-READY buyers (₹ incl. GST) | B23: =ROUNDUP('Inputs (assumptions)'!$B$4/('Inputs (assumptions)'!B17*(1-'Inputs (assumptions)'!B18)*'Inputs (assumptions)'!B19*'Inputs (assumptions)'!B20),0)*'Inputs (assumptions)'!B16*(1+'Inputs (assumptions)'!$B$5) -> 28096980 | C23: =ROUNDUP('Inputs (assumptions)'!$B$4/('Inputs (assumptions)'!C17*(1-'Inputs (assumptions)'!C18)*'Inputs (assumptions)'!C19*'Inputs (assumptions)'!C20),0)*'Inputs (assumptions)'!C16*(1+'Inputs (assumptions)'!$B$5) -> 5490540 | D23: =ROUNDUP('Inputs (assumptions)'!$B$4/('Inputs (assumptions)'!D17*(1-'Inputs (assumptions)'!D18)*'Inputs (assumptions)'!D19*'Inputs (assumptions)'!D20),0)*'Inputs (assumptions)'!D16*(1+'Inputs (assumptions)'!$B$5) -> 1470870 | E23: Raw needed × CPL × (1+GST)
A24: Days to 500 RAW at daily budget | B24: =ROUNDUP('Inputs (assumptions)'!$B$4*'Inputs (assumptions)'!B16*(1+'Inputs (assumptions)'!$B$5)/'Inputs (assumptions)'!$B$6,0) -> 89 | C24: =ROUNDUP('Inputs (assumptions)'!$B$4*'Inputs (assumptions)'!C16*(1+'Inputs (assumptions)'!$B$5)/'Inputs (assumptions)'!$B$6,0) -> 54 | D24: =ROUNDUP('Inputs (assumptions)'!$B$4*'Inputs (assumptions)'!D16*(1+'Inputs (assumptions)'!$B$5)/'Inputs (assumptions)'!$B$6,0) -> 30 | E24: Cost ÷ daily budget
A25: Days to 500 QUALIFIED at daily budget | B25: =ROUNDUP(ROUNDUP('Inputs (assumptions)'!$B$4/('Inputs (assumptions)'!B17*(1-'Inputs (assumptions)'!B18)*'Inputs (assumptions)'!B19),0)*'Inputs (assumptions)'!B16*(1+'Inputs (assumptions)'!$B$5)/'Inputs (assumptions)'!$B$6,0) -> 1405 | C25: =ROUNDUP(ROUNDUP('Inputs (assumptions)'!$B$4/('Inputs (assumptions)'!C17*(1-'Inputs (assumptions)'!C18)*'Inputs (assumptions)'!C19),0)*'Inputs (assumptions)'!C16*(1+'Inputs (assumptions)'!$B$5)/'Inputs (assumptions)'!$B$6,0) -> 357 | D25: =ROUNDUP(ROUNDUP('Inputs (assumptions)'!$B$4/('Inputs (assumptions)'!D17*(1-'Inputs (assumptions)'!D18)*'Inputs (assumptions)'!D19),0)*'Inputs (assumptions)'!D16*(1+'Inputs (assumptions)'!$B$5)/'Inputs (assumptions)'!$B$6,0) -> 118 | E25: Cost ÷ daily budget
A27: All figures are ILLUSTRATIVE, computed from the yellow assumption cells — not market statistics.

Sheet Phased Plan
A1: Phase | B1: Weeks | C1: Actions | D1: Spend (₹) | E1: Exit criteria
A2: 0 — Compliance prep | B2: 1–2 | C2: Approve & ship consent fixes on site; write consent wording (separate unticked call / WhatsApp boxes, business name, purpose); landing pages per locality; privacy policy update; confirm MahaRERA ad details; legal review of TRAI/DPDP points. | D2: 0 (internal) | E2: Forms store consent text, version, timestamp; legal sign-off
A3: 1 — Test | B3: 2–3 | C3: Google Search (Pune: Wakad, Hinjewadi, Kharadi, Mundhwa, Baner, Balewadi; MMR: Thane, Navi Mumbai, Andheri, Powai) + Meta higher-intent form. Equal split. | D3: Your choice, e.g. 14 days × ₹5,000/day ≈ ₹70,000 + GST (illustrative) | E3: Measured CPL, valid %, qualified %, consent % per channel — paste into Inputs sheet
A4: 1b — Portal quotes | B4: 2–3 | C4: Request written quotes from 99acres, Magicbricks, Housing.com using the Pre-Payment Checklist. Do not pay until answers received. | D4: 0 | E4: Written answers on volume, exclusivity, consent, refunds
A5: 2 — Scale | B5: 4–12 | C5: Move budget to the channel with the lowest cost per QUALIFIED (not per raw) lead. Weekly import via the import specification. | D5: Per Scenario Calculator | E5: 500 qualified / call-ready reached or budget cap
A6: 3 — Hygiene | B6: Ongoing | C6: Dedupe, suppression list, opt-out handling, weekly data-quality report. | D6: — | E6: —

Sheet Risks & Assumptions
A1: Risk / assumption | B1: Effect | C1: Mitigation
A2: CPLs are vendor benchmarks | B2: Budget could be 2–3× off | C2: Small test first; plan on cost per qualified lead
A3: Meta pre-filled forms | B3: Many low-intent / wrong numbers | C3: Higher-intent form, custom questions, OTP on landing page
A4: ₹1 Cr+ is self-declared | B4: Over-statement of budget | C4: Qualify on call; show price in ad ("from ₹1.2 Cr") to deter low budgets
A5: Optional call-consent box lowers opt-in | B5: Fewer call-ready leads | C5: Offer WhatsApp-first follow-up, ask for call permission there
A6: Portal leads may be shared | B6: Competing brokers call same buyer | C6: Ask exclusivity in writing; price accordingly
A7: Regulatory change (DPDP tranches, TRAI) | B7: Process must change | C7: Legal review before scaling calls
A8: Duplicates across channels | B8: Inflated counts | C8: Phone-based dedupe on import
A9: Ad policy / MahaRERA non-compliance | B9: Ads rejected, penalties | C9: Registration no./QR on all creatives

Sheet Pre-Payment Checklist
A1: # | B1: Ask the provider (get answers in writing) | C1: Why
A2: 1 | B2: Exact package price, GST, validity, auto-renewal, cancellation terms | C2: Avoid hidden charges
A3: 2 | B3: Guaranteed number of buyer enquiries (not views/clicks) in Pune/MMR at ₹1 Cr+ | C3: Most portals do not guarantee volume
A4: 3 | B4: Are leads exclusive to me or shared with other advertisers? How many? | C4: Shared leads convert worse
A5: 4 | B5: Lead fields supplied: name, phone, email, locality, budget, BHK, timeline, enquiry time | C5: Qualification needs these
A6: 5 | B6: Exact consent wording the buyer agreed to; does it cover calls/WhatsApp from me about OTHER projects? | C6: DPDP/TRAI — purpose-specific consent
A7: 6 | B7: Proof of consent per lead (timestamp, form, IP/OTP) | C7: Evidence if challenged
A8: 7 | B8: Are numbers OTP-verified? Invalid/duplicate/wrong-number replacement or refund policy and time limit | C8: Protects spend
A9: 8 | B9: Lead age at delivery (real-time vs historical) and delivery method (CSV/API/CRM) | C9: Fresh leads convert
A10: 9 | B10: Eligibility: do I need MahaRERA agent registration, developer authorisation for listings? | C10: Avoid account blocks
A11: 10 | B11: Data retention/deletion obligations and permitted uses after contract ends | C11: Compliance
