Workbook

Sheet Research Summary
A1: Pune & Mumbai MMR - MahaRERA Developers and Projects Database
A2: PARTIAL DATASET - NOT A COMPLETE LIST OF PUNE AND MUMBAI/MMR PROJECTS | C2: Only part of the official registered-project listing could be collected within MahaRERA's rate limits. See "Coverage & Missing Pages".
A3: Workbook generated | B3: 2026-10-11 06:39:08 UTC
A4: Data collection date(s) | B4: 2026-10-11 | C4: Dates the official pages were retrieved
A5: Source | B5: MahaRERA | C5: Maharashtra Real Estate Regulatory Authority, https://maharera.maharashtra.gov.in - reproduced under its copyright policy
A7: Collected records
A8: Unique MahaRERA project registrations collected | B8: =COUNTA('Registered Projects'!B2:B1571) -> 1570 | C8: Deduplicated on registration number
A9: Unique developers / promoters (from collected projects) | B9: =COUNTA('Developer Directory'!A2:A1189) -> 1188 | C9: Exact promoter name after case/whitespace/punctuation normalisation; no fuzzy merging
A10: Pune projects | B10: =COUNTIF('Registered Projects'!J2:J1571,"Pune") -> 260 | C10: District = Pune. Portal total: 12996
A11: Mumbai MMR projects | B11: =COUNTIF('Registered Projects'!J2:J1571,"Mumbai MMR") -> 1310 | C11: Mumbai City, Mumbai Suburban, Thane, Raigad, Palghar
A12: of which Mumbai City | B12: =COUNTIF('Registered Projects'!I2:I1571,"Mumbai City") -> 640 | C12: Portal total: 1299; collected 64/130 pages
A13: of which Mumbai Suburban | B13: =COUNTIF('Registered Projects'!I2:I1571,"Mumbai Suburban") -> 190 | C13: Portal total: 6324; collected 19/633 pages
A14: of which Thane | B14: =COUNTIF('Registered Projects'!I2:I1571,"Thane") -> 470 | C14: Portal total: 6988; collected 47/699 pages
A15: of which Raigad (shown as "Raigarh" by MahaRERA) | B15: =COUNTIF('Registered Projects'!I2:I1571,"Raigarh") -> 10 | C15: Portal total: 5416; collected 1/542 pages
A16: of which Palghar | B16: =COUNTIF('Registered Projects'!I2:I1571,"Palghar") -> 0 | C16: Portal total: 2706; collected 0/271 pages
A18: Record verification (Registered Projects)
A19: Verified (official listing) | B19: =COUNTIF('Registered Projects'!Y2:Y1571,"Verified (official listing)") -> 1544 | C19: All listing fields present and consistent
A20: Partially verified | B20: =COUNTIF('Registered Projects'!Y2:Y1571,"Partially verified") -> 26 | C20: Some listing field blank or inconsistent
A21: Unverified records included | B21: 0 | C21: None. Records from throttled/ambiguous pages were not created; those pages are listed as missing.
A22: Pages throttled / unverified (not collected) | B22: =SUM('Coverage & Missing Pages'!F2:F9)-'Coverage & Missing Pages'!F9 -> 4 | C22: Across all search categories
A23: Note | C23: All records lack project address, registration date and original completion date (detail pages not collected). Status for every record is cross-checked against official lists, but the Revoked search itself is only partly collected.
A25: Status (Registered Projects sheet - one status per project)
A26: Registered - no adverse list match | B26: =COUNTIF('Registered Projects'!Q2:Q1571,"Registered - no adverse list match") -> 1557
A27: Revoked | B27: =COUNTIF('Registered Projects'!Q2:Q1571,"Revoked") -> 0
A28: Deregistered | B28: =COUNTIF('Registered Projects'!Q2:Q1571,"Deregistered") -> 6
A29: Abeyance - lapse of completion date | B29: =COUNTIF('Registered Projects'!Q2:Q1571,"Abeyance - lapse of completion date") -> 1
A30: Abeyance - QPR non-compliance | B30: =COUNTIF('Registered Projects'!Q2:Q1571,"Abeyance - QPR non-compliance") -> 5
A31: Abeyance - common bank account | B31: =COUNTIF('Registered Projects'!Q2:Q1571,"Abeyance - common bank account") -> 1
A32: Extension certificate shown | B32: =COUNTIF('Registered Projects'!R2:R1571,"Yes") -> 696 | C32: Extension Certificate link present on listing card
A34: Status lists (Revoked Dereg Lapsed Projects sheet - all in-scope districts, one row per project)
A35: Projects on any status list | B35: =COUNTA('Revoked Dereg Lapsed Projects'!A2:A4378) -> 4377 | C35: Official lists were downloaded in full, so this covers all 6 districts
A36: Revoked = Yes | B36: =COUNTIF('Revoked Dereg Lapsed Projects'!G2:G4378,"Yes") -> 40 | C36: Under-reported: Revoked search only partly collected
A37: Deregistered = Yes | B37: =COUNTIF('Revoked Dereg Lapsed Projects'!H2:H4378,"Yes") -> 355 | C37: Separate column per list; a project on two lists is counted once in the total above
A38: Abeyance - Lapse of Completion Date = Yes | B38: =COUNTIF('Revoked Dereg Lapsed Projects'!I2:I4378,"Yes") -> 2773 | C38: Separate column per list; a project on two lists is counted once in the total above
A39: Abeyance - QPR Non-compliance = Yes | B39: =COUNTIF('Revoked Dereg Lapsed Projects'!J2:J4378,"Yes") -> 874 | C39: Separate column per list; a project on two lists is counted once in the total above
A40: Abeyance - Common Bank Account = Yes | B40: =COUNTIF('Revoked Dereg Lapsed Projects'!K2:K4378,"Yes") -> 133 | C40: Separate column per list; a project on two lists is counted once in the total above
A41: NCLT Listed = Yes | B41: =COUNTIF('Revoked Dereg Lapsed Projects'!L2:L4378,"Yes") -> 316 | C41: Separate column per list; a project on two lists is counted once in the total above
A42: Not present in collected registered pages | B42: =COUNTIF('Revoked Dereg Lapsed Projects'!O2:O4378,"No") -> 4351 | C42: Mostly because those districts are only partly collected
A44: Missing fields (Registered Projects)
A45: Project Address blank | B45: =COUNTBLANK('Registered Projects'!F2:F1571) -> 1570 | C45: Left blank - not verified
A46: Registration Date blank | B46: =COUNTBLANK('Registered Projects'!N2:N1571) -> 1570 | C46: Left blank - not verified
A47: Original Completion Date blank | B47: =COUNTBLANK('Registered Projects'!O2:O1571) -> 1570 | C47: Left blank - not verified
A48: Revised / Proposed Completion Date blank | B48: =COUNTBLANK('Registered Projects'!P2:P1571) -> 1557 | C48: Left blank - not verified
A49: Locality / Taluka (as displayed) blank | B49: =COUNTBLANK('Registered Projects'!G2:G1571) -> 26 | C49: Left blank - not verified
A50: Pincode blank | B50: =COUNTBLANK('Registered Projects'!H2:H1571) -> 0 | C50: Left blank - not verified
A51: Developer website / address / contact blank | B51: =COUNTBLANK('Developer Directory'!F2:F1189) -> 1188 | C51: Not on MahaRERA listing; not researched per developer
A53: Coverage by district (registered search)
A54: District | B54: Records collected / portal total | C54: Pages collected / total; throttled-unverified; not attempted
A55: Thane | B55: 470 / 6988 | C55: 47 / 699 pages (6.7%); 0 throttled/unverified; 652 not attempted
A56: Mumbai Suburban | B56: 190 / 6324 | C56: 19 / 633 pages (3.0%); 0 throttled/unverified; 614 not attempted
A57: Mumbai City | B57: 640 / 1299 | C57: 64 / 130 pages (49.2%); 1 throttled/unverified; 65 not attempted
A58: Raigarh | B58: 10 / 5416 | C58: 1 / 542 pages (0.2%); 0 throttled/unverified; 541 not attempted
A59: Pune | B59: 260 / 12996 | C59: 26 / 1300 pages (2.0%); 0 throttled/unverified; 1274 not attempted
A60: Palghar | B60: 0 / 2706 | C60: 0 / 271 pages (0.0%); 0 throttled/unverified; 271 not attempted
A61: All (filtered) - Revoked search | B61: 40 / 83 | C61: 4 / 9 pages (44.4%); 3 throttled/unverified; 2 not attempted
A63: Status definitions
A64: Registered - no adverse list match | C64: Listed in MahaRERA Registered Projects search and not found on any adverse list on the check date. Does NOT confirm the project is on schedule or that registration is unexpired.
A65: Revoked | C65: Listed in MahaRERA Revoked Projects search (registration revoked / ab initio void).
A66: Deregistered | C66: Listed on MahaRERA "List of Projects Deregistered".
A67: Abeyance - lapse of completion date | C67: MahaRERA's lapse list: completion date lapsed; bank account frozen and sale agreements prohibited until compliance. This is the "Lapsed" status in this workbook.
A68: Abeyance - QPR non-compliance | C68: On MahaRERA abeyance list for non-submission of quarterly progress reports.
A69: Abeyance - common bank account | C69: On MahaRERA abeyance list for sharing a bank account with another project.
A70: NCLT (flag only) | C70: On MahaRERA NCLT projects list; status shown is as on 31-01-2025. Not used to set primary status.
A71: Priority | C71: When several lists match, primary status = first of: Revoked > Deregistered > Abeyance-lapse > Abeyance-QPR > Abeyance-common account. Each list also has its own Yes/No column; each project is counted once.
A72: Verified (official listing) | C72: All listing fields present on the official MahaRERA search card (reg no, project, promoter, district, taluka, pincode, last modified, detail URL) and district consistent.
A73: Partially verified | C73: Record from official listing but one or more listing fields blank or inconsistent.
A74: Unverified / Not collected | C74: Pages that were throttled or returned ambiguous responses ("No Records Found" / "Unable to find records"). No records were taken from such pages; they are listed in Coverage & Missing Pages.
A76: Limitations
A77: PARTIAL: the MahaRERA portal throttles automated paging (returns "No Records Found" for valid pages). One request stream with long delays was used; no throttling was bypassed and collection stopped.
A78: Palghar has 0 collected records; Raigad, Pune, Mumbai Suburban and Thane are mostly uncollected. Do not use counts here as market totals.
A79: Registration date, original completion date, project address and promoter office address are only on project detail pages (JavaScript app) and were NOT collected - left blank.
A80: Status is derived by matching registration numbers against official lists. "Registered - no adverse list match" does not mean active or on schedule.
A81: Abeyance "As per Authority order" lists and de-registration notices are PDF-only and were not parsed.
A82: Developer websites, addresses and contacts were not collected; no third-party sources were used.
A83: Developer IDs group identical promoter names only; see Duplicate Review for possible duplicates (not merged).
A84: Navi Mumbai, Mira-Bhayandar and Vasai-Virar are not separate MahaRERA districts; identify them via Taluka / Pincode. Raigad and Palghar include talukas outside the MMR.
A85: Excel sheet names cannot contain "/", so the requested "Revoked / Deregistered / Lapsed Projects" sheet is named "Revoked Dereg Lapsed Projects".

Sheet Developer Directory
A1: Developer ID | B1: Developer / Promoter Legal Name (as displayed on MahaRERA) | C1: Name Variants Seen | D1: Brand / Trading Name | E1: Company Type | F1: Official Website | G1: Public Business Address | H1: Districts of Registered Projects | I1: Official Business Contact | J1: Registered Projects Collected (count) | K1: Pune Projects (count) | L1: Mumbai MMR Projects (count) | M1: Projects with Adverse Flag (count) | N1: MahaRERA Registration Nos. (collected) | O1: Source URL | P1: Retrieved Date | Q1: Verification Status
A2: D00001 | B2: A G SUPERSTRUCTURES PVT LTD | E2: Private Limited Company (from name suffix) | H2: Thane | J2: 1 | K2: 0 | L2: 1 | M2: 0 | N2: P51700001636 | O2: https://www.maharera.maharashtra.gov.in/projects-search-result?project_state=27&project_district=517&page=1 | P2: 2026-10-11 | Q2: Partially verified: legal name and registration nos. verified on MahaRERA listing. Brand, website, address, contact NOT collected. Company type derived from name suffix only. Project count reflects collected pages only.
A3: D00002 | B3: A. P. BHANDARI DEVELOPERS | H3: Pune | J3: 1 | K3: 1 | L3: 0 | M3: 0 | N3: P52100001730 | O3: https://www.maharera.maharashtra.gov.in/projects-search-result?project_state=27&project_district=521&page=4 | P3: 2026-10-11 | Q3: Partially verified: legal name and registration nos. verified on MahaRERA listing. Brand, website, address, contact NOT collected. Company type derived from name suffix only. Project count reflects collected pages only.
A4: D00003 | B4: A.PATNI REALTY PRIVATE LIMITED | E4: Private Limited Company (from name suffix) | H4: Mumbai City | J4: 1 | K4: 0 | L4: 1 | M4: 0 | N4: P51900010462 | O4: https://www.maharera.maharashtra.gov.in/projects-search-result?project_state=27&project_district=519&page=43 | P4: 2026-10-11 | Q4: Partially verified: legal name and registration nos. verified on MahaRERA listing. Brand, website, address, contact NOT collected. Company type derived from name suffix only. Project count reflects collected pages only.
A5: D00004 | B5: A PLUS REALTY | H5: Thane | J5: 1 | K5: 0 | L5: 1 | M5: 0 | N5: P51700002661 | O5: https://www.maharera.maharashtra.gov.in/projects-search-result?project_state=27&project_district=517&page=15 | P5: 2026-10-11 | Q5: Partially verified: legal name and registration nos. verified on MahaRERA listing. Brand, website, address, contact NOT collected. Company type derived from name suffix only. Project count reflects collected pages only.
A6: D00005 | B6: A.R ASSOCIATES | H6: Mumbai City | J6: 1 | K6: 0 | L6: 1 | M6: 0 | N6: P51900007503 | O6: https://www.maharera.maharashtra.gov.in/projects-search-result?project_state=27&project_district=519&page=25 | P6: 2026-10-11 | Q6: Partially verified: legal name and registration nos. verified on MahaRERA listing. Brand, website, address, contact NOT collected. Company type derived from name suffix only. Project count reflects collected pages only.
A7: D00006 | B7: A R Constructions | H7: Mumbai City | J7: 1 | K7: 0 | L7: 1 | M7: 0 | N7: P51900000604 | O7: https://www.maharera.maharashtra.gov.in/projects-search-result?project_state=27&project_district=519&page=5 | P7: 2026-10-11 | Q7: Partially verified: legal name and registration nos. verified on MahaRERA listing. Brand, website, address, contact NOT collected. Company type derived from name suffix only. Project count reflects collected pages only.
A8: D00007 | B8: A V ASSOCIATES | H8: Thane | J8: 1 | K8: 0 | L8: 1 | M8: 0 | N8: P51700001018 | O8: https://www.maharera.maharashtra.gov.in/projects-search-result?project_state=27&project_district=517&page=8 | P8: 2026-10-11 | Q8: Partially verified: legal name and registration nos. verified on MahaRERA listing. Brand, website, address, contact NOT collected. Company type derived from name suffix only. Project count reflects collected pages only.
A9: D00008 | B9: AADI DEVELOPERS | H9: Thane | J9: 1 | K9: 0 | L9: 1 | M9: 0 | N9: P51700003336 | O9: https://www.maharera.maharashtra.gov.in/projects-search-result?project_state=27&project_district=517&page=16 | P9: 2026-10-11 | Q9: Partially verified: legal name and registration nos. verified on MahaRERA listing. Brand, website, address, contact NOT collected. Company type derived from name suffix only. Project count reflects collected pages only.
A10: D00009 | B10: Aadinath builders & developers | H10: Thane | J10: 1 | K10: 0 | L10: 1 | M10: 0 | N10: P51700005002 | O10: https://www.maharera.maharashtra.gov.in/projects-search-result?project_state=27&project_district=517&page=31 | P10: 2026-10-11 | Q10: Partially verified: legal name and registration nos. verified on MahaRERA listing. Brand, website, address, contact NOT collected. Company type derived from name suffix only. Project count reflects collected pages only.
A11: D00010 | B11: Aakaar Tanishq Nirmaan J. V. | H11: Mumbai City | J11: 1 | K11: 0 | L11: 1 | M11: 0 | N11: P51900006567 | O11: https://www.maharera.maharashtra.gov.in/projects-search-result?project_state=27&project_district=519&page=34 | P11: 2026-10-11 | Q11: Partially verified: legal name and registration nos. verified on MahaRERA listing. Brand, website, address, contact NOT collected. Company type derived from name suffix only. Project count reflects collected pages only.
A12: D00011 | B12: AAKASH ASSOCIATES INFRASTRUCTURE | H12: Mumbai City | J12: 1 | K12: 0 | L12: 1 | M12: 1 | N12: P51900012769 | O12: https://www.maharera.maharashtra.gov.in/projects-search-result?project_state=27&project_district=519&page=52 | P12: 2026-10-11 | Q12: Partially verified: legal name and registration nos. verified on MahaRERA listing. Brand, website, address, contact NOT collected. Company type derived from name suffix only. Project count reflects collected pages only.
A13: D00012 | B13: AAKASH BUILDERS & DEVELOPERS | H13: Thane | J13: 1 | K13: 0 | L13: 1 | M13: 0 | N13: P51700011846 | O13: https://www.maharera.maharashtra.gov.in/projects-search-result?project_state=27&project_district=517&page=29 | P13: 2026-10-11 | Q13: Partially verified: legal name and registration nos. verified on MahaRERA listing. Brand, website, address, contact NOT collected. Company type derived from name suffix only. Project count reflects collected pages only.
A14: D00013 | B14: AALAY DEVELOPERS | H14: Mumbai City | J14: 1 | K14: 0 | L14: 1 | M14: 0 | N14: P51900004114 | O14: https://www.maharera.maharashtra.gov.in/projects-search-result?project_state=27&project_district=519&page=13 | P14: 2026-10-11 | Q14: Partially verified: legal name and registration nos. verified on MahaRERA listing. Brand, website, address, contact NOT collected. Company type derived from name suffix only. Project count reflects collected pages only.
A15: D00014 | B15: AAMANTRAN DEVELOPERS | H15: Thane | J15: 1 | K15: 0 | L15: 1 | M15: 0 | N15: P51700003251 | O15: https://www.maharera.maharashtra.gov.in/projects-search-result?project_state=27&project_district=517&page=35 | P15: 2026-10-11 | Q15: Partially verified: legal name and registration nos. verified on MahaRERA listing. Brand, website, address, contact NOT collected. Company type derived from name suffix only. Project count reflects collected pages only.
A16: D00015 | B16: AANANDVARDHAN REALTORS | H16: Mumbai City | J16: 1 | K16: 0 | L16: 1 | M16: 0 | N16: P51900011546 | O16: https://www.maharera.maharashtra.gov.in/projects-search-result?project_state=27&project_district=519&page=48 | P16: 2026-10-11 | Q16: Partially verified: legal name and registration nos. verified on MahaRERA listing. Brand, website, address, contact NOT collected. Company type derived from name suffix only. Project count reflects collected pages only.
... A24: D00023 | B24: Abhimanyu Group | H24: Pune | J24: 1 | K24: 1 | L24: 0 | M24: 0 | N24: P52100010222 | O24: https://www.maharera.maharashtra.gov.in/projects-search-result?project_state=27&project_district=521&page=23 | P24: 2026-10-11 | Q24: Partially verified: legal name and registration nos. verified on MahaRERA listing. Brand, website, address, contact NOT collected. Company type derived from name suffix only. Project count reflects collected pages only.
A25: D00024 | B25: ACCORD ESTATES PVT LTD | E25: Private Limited Company (from name suffix) | H25: Mumbai City | J25: 1 | K25: 0 | L25: 1 | M25: 0 | N25: P51900006752 | O25: https://www.maharera.maharashtra.gov.in/projects-search-result?project_state=27&project_district=519&page=33 | P25: 2026-10-11 | Q25: Partially verified: legal name and registration nos. verified on MahaRERA listing. Brand, website, address, contact NOT collected. Company type derived from name suffix only. Project count reflects collected pages only.
A26: D00025 | B26: ACE AURUM | H26: Pune | J26: 1 | K26: 1 | L26: 0 | M26: 0 | N26: P52100000090 | O26: https://www.maharera.maharashtra.gov.in/projects-search-result?project_state=27&project_district=521&page=4 | P26: 2026-10-11 | Q26: Partially verified: legal name and registration nos. verified on MahaRERA listing. Brand, website, address, contact NOT collected. Company type derived from name suffix only. Project count reflects collected pages only.
A27: D00026 | B27: ACEAUGUSTA | H27: Pune | J27: 1 | K27: 1 | L27: 0 | M27: 0 | N27: P52100000080 | O27: https://www.maharera.maharashtra.gov.in/projects-search-result?project_state=27&project_district=521&page=6 | P27: 2026-10-11 | Q27: Partially verified: legal name and registration nos. verified on MahaRERA listing. Brand, website, address, contact NOT collected. Company type derived from name suffix only. Project count reflects collected pages only.
A28: D00027 | B28: Acme Housing India Private Limited | E28: Private Limited Company (from name suffix) | H28: Thane | J28: 4 | K28: 0 | L28: 4 | M28: 0 | N28: P51700000778, P51700001032, P51700001033, P51700001038 | O28: https://www.maharera.maharashtra.gov.in/projects-search-result?project_state=27&project_district=517&page=23 | P28: 2026-10-11 | Q28: Partially verified: legal name and registration nos. verified on MahaRERA listing. Brand, website, address, contact NOT collected. Company type derived from name suffix only. Project count reflects collected pages only.
A29: D00028 | B29: ACME SAWANT VENTURES | H29: Pune | J29: 1 | K29: 1 | L29: 0 | M29: 0 | N29: P52100004621 | O29: https://www.maharera.maharashtra.gov.in/projects-search-result?project_state=27&project_district=521&page=23 | P29: 2026-10-11 | Q29: Partially verified: legal name and registration nos. verified on MahaRERA listing. Brand, website, address, contact NOT collected. Company type derived from name suffix only. Project count reflects collected pages only.
A30: D00029 | B30: ADANI DEVELOPERS PRIVATE LIMITED | E30: Private Limited Company (from name suffix) | H30: Mumbai City | J30: 2 | K30: 0 | L30: 2 | M30: 0 | N30: P51900006101, P51900008813 | O30: https://www.maharera.maharashtra.gov.in/projects-search-result?project_state=27&project_district=519&page=24 | P30: 2026-10-11 | Q30: Partially verified: legal name and registration nos. verified on MahaRERA listing. Brand, website, address, contact NOT collected. Company type derived from name suffix only. Project count reflects collected pages only.
A31: D00030 | B31: ADCON INFRAPROJECTS PVT.LTD. | E31: Private Limited Company (from name suffix) | H31: Mumbai Suburban | J31: 1 | K31: 0 | L31: 1 | M31: 0 | N31: P51800012207 | O31: https://www.maharera.maharashtra.gov.in/projects-search-result?project_state=27&project_district=518&page=10 | P31: 2026-10-11 | Q31: Partially verified: legal name and registration nos. verified on MahaRERA listing. Brand, website, address, contact NOT collected. Company type derived from name suffix only. Project count reflects collected pages only.
A32: D00031 | B32: ADHYA PROPERTIES | H32: Pune | J32: 2 | K32: 2 | L32: 0 | M32: 0 | N32: P52100001122, P52100001891 | O32: https://www.maharera.maharashtra.gov.in/projects-search-result?project_state=27&project_district=521&page=19 | P32: 2026-10-11 | Q32: Partially verified: legal name and registration nos. verified on MahaRERA listing. Brand, website, address, contact NOT collected. Company type derived from name suffix only. Project count reflects collected pages only.
A33: D00032 | B33: ADINATH ENTERPRISE | H33: Mumbai Suburban | J33: 1 | K33: 0 | L33: 1 | M33: 0 | N33: P51800000010 | O33: https://www.maharera.maharashtra.gov.in/projects-search-result?project_state=27&project_district=518&page=2 | P33: 2026-10-11 | Q33: Partially verified: legal name and registration nos. verified on MahaRERA listing. Brand, website, address, contact NOT collected. Company type derived from name suffix only. Project count reflects collected pages only.
A34: D00033 | B34: Aditdev Builders LLP | E34: LLP (from name suffix) | H34: Mumbai City | J34: 1 | K34: 0 | L34: 1 | M34: 0 | N34: P51900007964 | O34: https://www.maharera.maharashtra.gov.in/projects-search-result?project_state=27&project_district=519&page=33 | P34: 2026-10-11 | Q34: Partially verified: legal name and registration nos. verified on MahaRERA listing. Brand, website, address, contact NOT collected. Company type derived from name suffix only. Project count reflects collected pages only.
A35: D00034 | B35: Aditi Construction | H35: Thane | J35: 1 | K35: 0 | L35: 1 | M35: 0 | N35: P51700000782 | O35: https://www.maharera.maharashtra.gov.in/projects-search-result?project_state=27&project_district=517&page=4 | P35: 2026-10-11 | Q35: Partially verified: legal name and registration nos. verified on MahaRERA listing. Brand, website, address, contact NOT collected. Company type derived from name suffix only. Project count reflects collected pages only.
A36: D00035 | B36: Aditya Associates | H36: Thane | J36: 1 | K36: 0 | L36: 1 | M36: 0 | N36: P51700002433 | O36: https://www.maharera.maharashtra.gov.in/projects-search-result?project_state=27&project_district=517&page=12 | P36: 2026-10-11 | Q36: Partially verified: legal name and registration nos. verified on MahaRERA listing. Brand, website, address, contact NOT collected. Company type derived from name suffix only. Project count reflects collected pages only.
A37: D00036 | B37: ADITYA SHAGUN DEVELOPERS | H37: Pune | J37: 1 | K37: 1 | L37: 0 | M37: 0 | N37: P52100002025 | O37: https://www.maharera.maharashtra.gov.in/projects-search-result?project_state=27&project_district=521&page=22 | P37: 2026-10-11 | Q37: Partially verified: legal name and registration nos. verified on MahaRERA listing. Brand, website, address, contact NOT collected. Company type derived from name suffix only. Project count reflects collected pages only.
A38: D00037 | B38: ADVENT DEVELOPERS PRIVATE LIMITED | E38: Private Limited Company (from name suffix) | H38: Mumbai Suburban | J38: 1 | K38: 0 | L38: 1 | M38: 0 | N38: P51800002649 | O38: https://www.maharera.maharashtra.gov.in/projects-search-result?project_state=27&project_district=518&page=14 | P38: 2026-10-11 | Q38: Partially verified: legal name and registration nos. verified on MahaRERA listing. Brand, website, address, contact NOT collected. Company type derived from name suffix only. Project count reflects collected pages only.
A39: D00038 | B39: Agile Real Estate Pvt. Ltd. | E39: Private Limited Company (from name suffix) | H39: Thane | J39: 13 | K39: 0 | L39: 13 | M39: 0 | N39: P51700000625, P51700000635, P51700000640, P51700000732, P51700000922, P51700000924, P51700000925, P51700000927, P51700001039, P51700001040, P51700001083, P51700001278, P51700001310 | O39: https://www.maharera.maharashtra.gov.in/projects-search-result?project_state=27&project_district=517&page=25 | P39: 2026-10-11 | Q39: Partially verified: legal name and registration nos. verified on MahaRERA listing. Brand, website, address, contact NOT collected. Company type derived from name suffix only. Project count reflects collected pages only.
A40: D00039 | B40: AIKYA REALTY PVT LTD | E40: Private Limited Company (from name suffix) | H40: Mumbai City | J40: 1 | K40: 0 | L40: 1 | M40: 0 | N40: P51900002496 | O40: https://www.maharera.maharashtra.gov.in/projects-search-result?project_state=27&project_district=519&page=6 | P40: 2026-10-11 | Q40: Partially verified: legal name and registration nos. verified on MahaRERA listing. Brand, website, address, contact NOT collected. Company type derived from name suffix only. Project count reflects collected pages only.
A41: D00040 | B41: AJAY MADHUKAR THANEKAR | H41: Thane | J41: 2 | K41: 0 | L41: 2 | M41: 0 | N41: P51700000644, P51700001024 | O41: https://www.maharera.maharashtra.gov.in/projects-search-result?project_state=27&project_district=517&page=1 | P41: 2026-10-11 | Q41: Partially verified: legal name and registration nos. verified on MahaRERA listing. Brand, website, address, contact NOT collected. Company type derived from name suffix only. Project count reflects collected pages only.
A42: D00041 | B42: AJIT ANANT BARVE | H42: Mumbai City | J42: 1 | K42: 0 | L42: 1 | M42: 0 | N42: P51900012656 | O42: https://www.maharera.maharashtra.gov.in/projects-search-result?project_state=27&project_district=519&page=37 | P42: 2026-10-11 | Q42: Partially verified: legal name and registration nos. verified on MahaRERA listing. Brand, website, address, contact NOT collected. Company type derived from name suffix only. Project count reflects collected pages only.
A43: D00042 | B43: AJIT KRISHNAN RATNAM | H43: Thane | J43: 1 | K43: 0 | L43: 1 | M43: 0 | N43: P51700003326 | O43: https://www.maharera.maharashtra.gov.in/projects-search-result?project_state=27&project_district=517&page=16 | P43: 2026-10-11 | Q43: Partially verified: legal name and registration nos. verified on MahaRERA listing. Brand, website, address, contact NOT collected. Company type derived from name suffix only. Project count reflects collected pages only.
A44: D00043 | B44: Akbar Mohamadali Kazi | H44: Mumbai City | J44: 1 | K44: 0 | L44: 1 | M44: 0 | N44: P51900006052 | O44: https://www.maharera.maharashtra.gov.in/projects-search-result?project_state=27&project_district=519&page=3 | P44: 2026-10-11 | Q44: Partially verified: legal name and registration nos. verified on MahaRERA listing. Brand, website, address, contact NOT collected. Company type derived from name suffix only. Project count reflects collected pages only.
A45: D00044 | B45: Akshay Enterprises | H45: Thane | J45: 1 | K45: 0 | L45: 1 | M45: 0 | N45: P51700002757 | O45: https://www.maharera.maharashtra.gov.in/projects-search-result?project_state=27&project_district=517&page=5 | P45: 2026-10-11 | Q45: Partially verified: legal name and registration nos. verified on MahaRERA listing. Brand, website, address, contact NOT collected. Company type derived from name suffix only. Project count reflects collected pages only.
A46: D00045 | B46: AKSHAY GRUHPRAVESH LLP | E46: LLP (from name suffix) | H46: Mumbai Suburban | J46: 1 | K46: 0 | L46: 1 | M46: 0 | N46: P51800000487 | O46: https://www.maharera.maharashtra.gov.in/projects-search-result?project_state=27&project_district=518&page=8 | P46: 2026-10-11 | Q46: Partially verified: legal name and registration nos. verified on MahaRERA listing. Brand, website, address, contact NOT collected. Company type derived from name suffix only. Project count reflects collected pages only.
A47: D00046 | B47: AL HAADI DEVELOPERS | H47: Mumbai City | J47: 1 | K47: 0 | L47: 1 | M47: 0 | N47: P51900011681 | O47: https://www.maharera.maharashtra.gov.in/projects-search-result?project_state=27&project_district=519&page=40 | P47: 2026-10-11 | Q47: Partially verified: legal name and registration nos. verified on MahaRERA listing. Brand, website, address, contact NOT collected. Company type derived from name suffix only. Project count reflects collected pages only.
A48: D00047 | B48: AL-SAAD CONSTRUCTIONS | H48: Thane | J48: 1 | K48: 0 | L48: 1 | M48: 0 | N48: P51700005670 | O48: https://www.maharera.maharashtra.gov.in/projects-search-result?project_state=27&project_district=517&page=28 | P48: 2026-10-11 | Q48: Partially verified: legal name and registration nos. verified on MahaRERA listing. Brand, website, address, contact NOT collected. Company type derived from name suffix only. Project count reflects collected pages only.
A49: D00048 | B49: ALF DEVELOPERS | H49: Mumbai City | J49: 2 | K49: 0 | L49: 2 | M49: 0 | N49: P51900010150, P51900011198 | O49: https://www.maharera.maharashtra.gov.in/projects-search-result?project_state=27&project_district=519&page=53 | P49: 2026-10-11 | Q49: Partially verified: legal name and registration nos. verified on MahaRERA listing. Brand, website, address, contact NOT collected. Company type derived from name suffix only. Project count reflects collected pages only.
A50: D00049 | B50: ALFA MANA REALTORS PVT LTD | E50: Private Limited Company (from name suffix) | H50: Mumbai City | J50: 1 | K50: 0 | L50: 1 | M50: 0 | N50: P51900000070 | O50: https://www.maharera.maharashtra.gov.in/projects-search-result?project_state=27&project_district=519&page=1 | P50: 2026-10-11 | Q50: Partially verified: legal name and registration nos. verified on MahaRERA listing. Brand, website, address, contact NOT collected. Company type derived from name suffix only. Project count reflects collected pages only.
A51: D00050 | B51: ALLIANCE INFRACORP DEVELOPERS | H51: Mumbai City | J51: 1 | K51: 0 | L51: 1 | M51: 0 | N51: P51900018299 | O51: https://www.maharera.maharashtra.gov.in/projects-search-result?project_state=27&project_district=519&page=62 | P51: 2026-10-11 | Q51: Partially verified: legal name and registration nos. verified on MahaRERA listing. Brand, website, address, contact NOT collected. Company type derived from name suffix only. Project count reflects collected pages only.
A52: D00051 | B52: Aloka Commercial Private Limited | E52: Private Limited Company (from name suffix) | H52: Mumbai City | J52: 1 | K52: 0 | L52: 1 | M52: 0 | N52: P51900013712 | O52: https://www.maharera.maharashtra.gov.in/projects-search-result?project_state=27&project_district=519&page=15 | P52: 2026-10-11 | Q52: Partially verified: legal name and registration nos. verified on MahaRERA listing. Brand, website, address, contact NOT collected. Company type derived from name suffix only. Project count reflects collected pages only.
A53: D00052 | B53: AMA Properties | H53: Pune | J53: 1 | K53: 1 | L53: 0 | M53: 0 | N53: P52100000632 | O53: https://www.maharera.maharashtra.gov.in/projects-search-result?project_state=27&project_district=521&page=17 | P53: 2026-10-11 | Q53: Partially verified: legal name and registration nos. verified on MahaRERA listing. Brand, website, address, contact NOT collected. Company type derived from name suffix only. Project count reflects collected pages only.
A54: D00053 | B54: AMAR CONSTRUCTION | H54: Thane | J54: 1 | K54: 0 | L54: 1 | M54: 0 | N54: P51700005351 | O54: https://www.maharera.maharashtra.gov.in/projects-search-result?project_state=27&project_district=517&page=37 | P54: 2026-10-11 | Q54: Partially verified: legal name and registration nos. verified on MahaRERA listing. Brand, website, address, contact NOT collected. Company type derived from name suffix only. Project count reflects collected pages only.
A55: D00054 | B55: AMAR REALTY | H55: Thane | J55: 1 | K55: 0 | L55: 1 | M55: 0 | N55: P51700002411 | O55: https://www.maharera.maharashtra.gov.in/projects-search-result?project_state=27&project_district=517&page=30 | P55: 2026-10-11 | Q55: Partially verified: legal name and registration nos. verified on MahaRERA listing. Brand, website, address, contact NOT collected. Company type derived from name suffix only. Project count reflects collected pages only.
A56: D00055 | B56: AMBE DEEP ENTERPRISES | H56: Thane | J56: 1 | K56: 0 | L56: 1 | M56: 0 | N56: P51700002104 | O56: https://www.maharera.maharashtra.gov.in/projects-search-result?project_state=27&project_district=517&page=47 | P56: 2026-10-11 | Q56: Partially verified: legal name and registration nos. verified on MahaRERA listing. Brand, website, address, contact NOT collected. Company type derived from name suffix only. Project count reflects collected pages only.
A57: D00056 | B57: Ambrosial Developers Pvt. Ltd. | E57: Private Limited Company (from name suffix) | H57: Mumbai Suburban | J57: 1 | K57: 0 | L57: 1 | M57: 0 | N57: P51800001181 | O57: https://www.maharera.maharashtra.gov.in/projects-search-result?project_state=27&project_district=518&page=12 | P57: 2026-10-11 | Q57: Partially verified: legal name and registration nos. verified on MahaRERA listing. Brand, website, address, contact NOT collected. Company type derived from name suffix only. Project count reflects collected pages only.
A58: D00057 | B58: AMEX DEVELOPERS PVT. LTD., | E58: Private Limited Company (from name suffix) | H58: Mumbai City | J58: 1 | K58: 0 | L58: 1 | M58: 1 | N58: P51900009319 | O58: https://www.maharera.maharashtra.gov.in/projects-search-result?project_state=27&project_district=519&page=49 | P58: 2026-10-11 | Q58: Partially verified: legal name and registration nos. verified on MahaRERA listing. Brand, website, address, contact NOT collected. Company type derived from name suffix only. Project count reflects collected pages only.
A59: D00058 | B59: AMIT C THAKUR | H59: Pune | J59: 1 | K59: 1 | L59: 0 | M59: 0 | N59: P52100012200 | O59: https://www.maharera.maharashtra.gov.in/projects-search-result?project_state=27&project_district=521&page=1 | P59: 2026-10-11 | Q59: Partially verified: legal name and registration nos. verified on MahaRERA listing. Brand, website, address, contact NOT collected. Company type derived from name suffix only. Project count reflects collected pages only.
A60: D00059 | B60: AMIT JUGALKISHOR RATHI | H60: Pune | J60: 1 | K60: 1 | L60: 0 | M60: 0 | N60: P52100000198 | O60: https://www.maharera.maharashtra.gov.in/projects-search-result?project_state=27&project_district=521&page=9 | P60: 2026-10-11 | Q60: Partially verified: legal name and registration nos. verified on MahaRERA listing. Brand, website, address, contact NOT collected. Company type derived from name suffix only. Project count reflects collected pages only.
A61: D00060 | B61: AMN Enterprises | H61: Mumbai Suburban | J61: 1 | K61: 0 | L61: 1 | M61: 0 | N61: P51800003042 | O61: https://www.maharera.maharashtra.gov.in/projects-search-result?project_state=27&project_district=518&page=3 | P61: 2026-10-11 | Q61: Partially verified: legal name and registration nos. verified on MahaRERA listing. Brand, website, address, contact NOT collected. Company type derived from name suffix only. Project count reflects collected pages only.
A62: D00061 | B62: Amol Padmakar Tarmale | H62: Thane | J62: 1 | K62: 0 | L62: 1 | M62: 0 | N62: P51700011204 | O62: https://www.maharera.maharashtra.gov.in/projects-search-result?project_state=27&project_district=517&page=24 | P62: 2026-10-11 | Q62: Partially verified: legal name and registration nos. verified on MahaRERA listing. Brand, website, address, contact NOT collected. Company type derived from name suffix only. Project count reflects collected pages only.
A63: D00062 | B63: ANAHITA RUSI MEHTA | H63: Mumbai City | J63: 1 | K63: 0 | L63: 1 | M63: 0 | N63: P51900007228 | O63: https://www.maharera.maharashtra.gov.in/projects-search-result?project_state=27&project_district=519&page=38 | P63: 2026-10-11 | Q63: Partially verified: legal name and registration nos. verified on MahaRERA listing. Brand, website, address, contact NOT collected. Company type derived from name suffix only. Project count reflects collected pages only.
A64: D00063 | B64: ANAND DEVELOPERS | H64: Pune | J64: 1 | K64: 1 | L64: 0 | M64: 0 | N64: P52100001408 | O64: https://www.maharera.maharashtra.gov.in/projects-search-result?project_state=27&project_district=521&page=5 | P64: 2026-10-11 | Q64: Partially verified: legal name and registration nos. verified on MahaRERA listing. Brand, website, address, contact NOT collected. Company type derived from name suffix only. Project count reflects collected pages only.
A65: D00064 | B65: Anand Properties | H65: Pune | J65: 1 | K65: 1 | L65: 0 | M65: 0 | N65: P52100000045 | O65: https://www.maharera.maharashtra.gov.in/projects-search-result?project_state=27&project_district=521&page=5 | P65: 2026-10-11 | Q65: Partially verified: legal name and registration nos. verified on MahaRERA listing. Brand, website, address, contact NOT collected. Company type derived from name suffix only. Project count reflects collected pages only.
A66: D00065 | B66: ANANT SQUARE | H66: Thane | J66: 1 | K66: 0 | L66: 1 | M66: 0 | N66: P51700003827 | O66: https://www.maharera.maharashtra.gov.in/projects-search-result?project_state=27&project_district=517&page=31 | P66: 2026-10-11 | Q66: Partially verified: legal name and registration nos. verified on MahaRERA listing. Brand, website, address, contact NOT collected. Company type derived from name suffix only. Project count reflects collected pages only.
A67: D00066 | B67: ANANTNATH DEVELOPERS | H67: Thane | J67: 1 | K67: 0 | L67: 1 | M67: 0 | N67: P51700002966 | O67: https://www.maharera.maharashtra.gov.in/projects-search-result?project_state=27&project_district=517&page=14 | P67: 2026-10-11 | Q67: Partially verified: legal name and registration nos. verified on MahaRERA listing. Brand, website, address, contact NOT collected. Company type derived from name suffix only. Project count reflects collected pages only.
A68: D00067 | B68: Anchor Daewoo Industries Ltd. | E68: Limited Company (from name suffix) | H68: Mumbai City | J68: 1 | K68: 0 | L68: 1 | M68: 0 | N68: P51900011067 | O68: https://www.maharera.maharashtra.gov.in/projects-search-result?project_state=27&project_district=519&page=38 | P68: 2026-10-11 | Q68: Partially verified: legal name and registration nos. verified on MahaRERA listing. Brand, website, address, contact NOT collected. Company type derived from name suffix only. Project count reflects collected pages only.
A69: D00068 | B69: ANIL HARDASMAL THARWANI | H69: Thane | J69: 7 | K69: 0 | L69: 7 | M69: 0 | N69: P51700004565, P51700005135, P51700005630, P51700006127, P51700006728, P51700007310, P51700007834 | O69: https://www.maharera.maharashtra.gov.in/projects-search-result?project_state=27&project_district=517&page=41 | P69: 2026-10-11 | Q69: Partially verified: legal name and registration nos. verified on MahaRERA listing. Brand, website, address, contact NOT collected. Company type derived from name suffix only. Project count reflects collected pages only.
A70: D00069 | B70: ANIL MURARILAL AGARWAL | H70: Mumbai City | J70: 1 | K70: 0 | L70: 1 | M70: 0 | N70: P51900004866 | O70: https://www.maharera.maharashtra.gov.in/projects-search-result?project_state=27&project_district=519&page=32 | P70: 2026-10-11 | Q70: Partially verified: legal name and registration nos. verified on MahaRERA listing. Brand, website, address, contact NOT collected. Company type derived from name suffix only. Project count reflects collected pages only.
A71: D00070 | B71: ANIL SHILPAYATAN PRIVATE LIMITED | E71: Private Limited Company (from name suffix) | H71: Thane | J71: 1 | K71: 0 | L71: 1 | M71: 0 | N71: P51700001875 | O71: https://www.maharera.maharashtra.gov.in/projects-search-result?project_state=27&project_district=517&page=12 | P71: 2026-10-11 | Q71: Partially verified: legal name and registration nos. verified on MahaRERA listing. Brand, website, address, contact NOT collected. Company type derived from name suffix only. Project count reflects collected pages only.
A72: D00071 | B72: Anishka Developers Pvt. Ltd. | E72: Private Limited Company (from name suffix) | H72: Pune | J72: 1 | K72: 1 | L72: 0 | M72: 0 | N72: P52100000501 | O72: https://www.maharera.maharashtra.gov.in/projects-search-result?project_state=27&project_district=521&page=20 | P72: 2026-10-11 | Q72: Partially verified: legal name and registration nos. verified on MahaRERA listing. Brand, website, address, contact NOT collected. Company type derived from name suffix only. Project count reflects collected pages only.
A73: D00072 | B73: Ankur Premises Developers LLP | E73: LLP (from name suffix) | H73: Mumbai Suburban | J73: 2 | K73: 0 | L73: 2 | M73: 0 | N73: P51800004056, P51800007115 | O73: https://www.maharera.maharashtra.gov.in/projects-search-result?project_state=27&project_district=518&page=2 | P73: 2026-10-11 | Q73: Partially verified: legal name and registration nos. verified on MahaRERA listing. Brand, website, address, contact NOT collected. Company type derived from name suffix only. Project count reflects collected pages only.
A74: D00073 | B74: ANMOL LAND DEVELOPERS | H74: Mumbai City | J74: 2 | K74: 0 | L74: 2 | M74: 0 | N74: P51900006333, P51900007311 | O74: https://www.maharera.maharashtra.gov.in/projects-search-result?project_state=27&project_district=519&page=19 | P74: 2026-10-11 | Q74: Partially verified: legal name and registration nos. verified on MahaRERA listing. Brand, website, address, contact NOT collected. Company type derived from name suffix only. Project count reflects collected pages only.
A75: D00074 | B75: ANNAPURNA ASSOCIATES | H75: Thane | J75: 1 | K75: 0 | L75: 1 | M75: 0 | N75: P51700000957 | O75: https://www.maharera.maharashtra.gov.in/projects-search-result?project_state=27&project_district=517&page=29 | P75: 2026-10-11 | Q75: Partially verified: legal name and registration nos. verified on MahaRERA listing. Brand, website, address, contact NOT collected. Company type derived from name suffix only. Project count reflects collected pages only.
A76: D00075 | B76: ANNAPURNA BUILDCON INFRA PRIVATE LIMITED | E76: Private Limited Company (from name suffix) | H76: Thane | J76: 1 | K76: 0 | L76: 1 | M76: 0 | N76: P51800000876 | O76: https://www.maharera.maharashtra.gov.in/projects-search-result?project_state=27&project_district=517&page=36 | P76: 2026-10-11 | Q76: Partially verified: legal name and registration nos. verified on MahaRERA listing. Brand, website, address, contact NOT collected. Company type derived from name suffix only. Project count reflects collected pages only.
A77: D00076 | B77: ANNAPURNA CREATORS | H77: Thane | J77: 1 | K77: 0 | L77: 1 | M77: 0 | N77: P51700000893 | O77: https://www.maharera.maharashtra.gov.in/projects-search-result?project_state=27&project_district=517&page=18 | P77: 2026-10-11 | Q77: Partially verified: legal name and registration nos. verified on MahaRERA listing. Brand, website, address, contact NOT collected. Company type derived from name suffix only. Project count reflects collected pages only.
A78: D00077 | B78: Annapurna Properties | H78: Thane | J78: 1 | K78: 0 | L78: 1 | M78: 0 | N78: P51800002185 | O78: https://www.maharera.maharashtra.gov.in/projects-search-result?project_state=27&project_district=517&page=43 | P78: 2026-10-11 | Q78: Partially verified: legal name and registration nos. verified on MahaRERA listing. Brand, website, address, contact NOT collected. Company type derived from name suffix only. Project count reflects collected pages only.
A79: D00078 | B79: Anupam Properties | H79: Mumbai City | J79: 1 | K79: 0 | L79: 1 | M79: 0 | N79: P51900019688 | O79: https://www.maharera.maharashtra.gov.in/projects-search-result?project_state=27&project_district=519&page=64 | P79: 2026-10-11 | Q79: Partially verified: legal name and registration nos. verified on MahaRERA listing. Brand, website, address, contact NOT collected. Company type derived from name suffix only. Project count reflects collected pages only.
A80: D00079 | B80: AP Properties | H80: Pune | J80: 1 | K80: 1 | L80: 0 | M80: 0 | N80: P52100006578 | O80: https://www.maharera.maharashtra.gov.in/projects-search-result?project_state=27&project_district=521&page=22 | P80: 2026-10-11 | Q80: Partially verified: legal name and registration nos. verified on MahaRERA listing. Brand, website, address, contact NOT collected. Company type derived from name suffix only. Project count reflects collected pages only.
A81: D00080 | B81: Apex Builders | H81: Pune | J81: 1 | K81: 1 | L81: 0 | M81: 0 | N81: P52100000905 | O81: https://www.maharera.maharashtra.gov.in/projects-search-result?project_state=27&project_district=521&page=6 | P81: 2026-10-11 | Q81: Partially verified: legal name and registration nos. verified on MahaRERA listing. Brand, website, address, contact NOT collected. Company type derived from name suffix only. Project count reflects collected pages only.
A82: D00081 | B82: APRAULIC CONSTRUCTION INVESTMENT AND FINANCE PRIVATE LIMITED | E82: Private Limited Company (from name suffix) | H82: Mumbai Suburban | J82: 1 | K82: 0 | L82: 1 | M82: 0 | N82: P51800002160 | O82: https://www.maharera.maharashtra.gov.in/projects-search-result?project_state=27&project_district=518&page=11 | P82: 2026-10-11 | Q82: Partially verified: legal name and registration nos. verified on MahaRERA listing. Brand, website, address, contact NOT collected. Company type derived from name suffix only. Project count reflects collected pages only.
A83: D00082 | B83: AQURA BUILDER & DEVELOPER PRIVATE LIMITED | E83: Private Limited Company (from name suffix) | H83: Pune | J83: 1 | K83: 1 | L83: 0 | M83: 0 | N83: P52100000498 | O83: https://www.maharera.maharashtra.gov.in/projects-search-result?project_state=27&project_district=521&page=10 | P83: 2026-10-11 | Q83: Partially verified: legal name and registration nos. verified on MahaRERA listing. Brand, website, address, contact NOT collected. Company type derived from name suffix only. Project count reflects collected pages only.
A84: D00083 | B84: ARB DEVELOPERS | H84: Mumbai City | J84: 1 | K84: 0 | L84: 1 | M84: 0 | N84: P51900006633 | O84: https://www.maharera.maharashtra.gov.in/projects-search-result?project_state=27&project_district=519&page=42 | P84: 2026-10-11 | Q84: Partially verified: legal name and registration nos. verified on MahaRERA listing. Brand, website, address, contact NOT collected. Company type derived from name suffix only. Project count reflects collected pages only.
A85: D00084 | B85: ARC PUKHRAJ DEVELOPERS LLP | E85: LLP (from name suffix) | H85: Pune | J85: 1 | K85: 1 | L85: 0 | M85: 0 | N85: P52100005584 | O85: https://www.maharera.maharashtra.gov.in/projects-search-result?project_state=27&project_district=521&page=4 | P85: 2026-10-11 | Q85: Partially verified: legal name and registration nos. verified on MahaRERA listing. Brand, website, address, contact NOT collected. Company type derived from name suffix only. Project count reflects collected pages only.
A86: D00085 | B86: ARDENT PROPERTIES PRIVATE LIMITED | E86: Private Limited Company (from name suffix) | H86: Thane | J86: 1 | K86: 0 | L86: 1 | M86: 0 | N86: P51700000295 | O86: https://www.maharera.maharashtra.gov.in/projects-search-result?project_state=27&project_district=517&page=13 | P86: 2026-10-11 | Q86: Partially verified: legal name and registration nos. verified on MahaRERA listing. Brand, website, address, contact NOT collected. Company type derived from name suffix only. Project count reflects collected pages only.
A87: D00086 | B87: ARIHANT DEVLOPERS | H87: Mumbai City | J87: 1 | K87: 0 | L87: 1 | M87: 0 | N87: P51900015921 | O87: https://www.maharera.maharashtra.gov.in/projects-search-result?project_state=27&project_district=519&page=59 | P87: 2026-10-11 | Q87: Partially verified: legal name and registration nos. verified on MahaRERA listing. Brand, website, address, contact NOT collected. Company type derived from name suffix only. Project count reflects collected pages only.
A88: D00087 | B88: Aristocrat Marketing Ltd | E88: Limited Company (from name suffix) | H88: Mumbai Suburban | J88: 1 | K88: 0 | L88: 1 | M88: 0 | N88: P51800002492 | O88: https://www.maharera.maharashtra.gov.in/projects-search-result?project_state=27&project_district=518&page=2 | P88: 2026-10-11 | Q88: Partially verified: legal name and registration nos. verified on MahaRERA listing. Brand, website, address, contact NOT collected. Company type derived from name suffix only. Project count reflects collected pages only.
A89: D00088 | B89: Arkade Paradigm | H89: Mumbai City | J89: 1 | K89: 0 | L89: 1 | M89: 0 | N89: P51900015795 | O89: https://www.maharera.maharashtra.gov.in/projects-search-result?project_state=27&project_district=519&page=58 | P89: 2026-10-11 | Q89: Partially verified: legal name and registration nos. verified on MahaRERA listing. Brand, website, address, contact NOT collected. Company type derived from name suffix only. Project count reflects collected pages only.
A90: D00089 | B90: ARTH REALTECH SPACES PRIVATE LIMITED | E90: Private Limited Company (from name suffix) | H90: Mumbai City | J90: 1 | K90: 0 | L90: 1 | M90: 0 | N90: P51900020051 | O90: https://www.maharera.maharashtra.gov.in/projects-search-result?project_state=27&project_district=519&page=64 | P90: 2026-10-11 | Q90: Partially verified: legal name and registration nos. verified on MahaRERA listing. Brand, website, address, contact NOT collected. Company type derived from name suffix only. Project count reflects collected pages only.
A91: D00090 | B91: ARTH REALTECH SPACES PVT LTD | E91: Private Limited Company (from name suffix) | H91: Mumbai City | J91: 1 | K91: 0 | L91: 1 | M91: 0 | N91: P51900004688 | O91: https://www.maharera.maharashtra.gov.in/projects-search-result?project_state=27&project_district=519&page=50 | P91: 2026-10-11 | Q91: Partially verified: legal name and registration nos. verified on MahaRERA listing. Brand, website, address, contact NOT collected. Company type derived from name suffix only. Project count reflects collected pages only.
A92: D00091 | B92: AS DEVELOPER | H92: Mumbai City | J92: 1 | K92: 0 | L92: 1 | M92: 0 | N92: P51900011927 | O92: https://www.maharera.maharashtra.gov.in/projects-search-result?project_state=27&project_district=519&page=52 | P92: 2026-10-11 | Q92: Partially verified: legal name and registration nos. verified on MahaRERA listing. Brand, website, address, contact NOT collected. Company type derived from name suffix only. Project count reflects collected pages only.
A93: D00092 | B93: ASHA DEVELOPERS | H93: Thane, Mumbai Suburban | J93: 2 | K93: 0 | L93: 2 | M93: 0 | N93: P51700000624, P51800000004 | O93: https://www.maharera.maharashtra.gov.in/projects-search-result?project_state=27&project_district=517&page=2 | P93: 2026-10-11 | Q93: Partially verified: legal name and registration nos. verified on MahaRERA listing. Brand, website, address, contact NOT collected. Company type derived from name suffix only. Project count reflects collected pages only.
A94: D00093 | B94: ASHA ENTERPRISES | H94: Thane | J94: 1 | K94: 0 | L94: 1 | M94: 0 | N94: P51700001968 | O94: https://www.maharera.maharashtra.gov.in/projects-search-result?project_state=27&project_district=517&page=9 | P94: 2026-10-11 | Q94: Partially verified: legal name and registration nos. verified on MahaRERA listing. Brand, website, address, contact NOT collected. Company type derived from name suffix only. Project count reflects collected pages only.
A95: D00094 | B95: ASHIRWAD DEVELOPERS | H95: Thane | J95: 1 | K95: 0 | L95: 1 | M95: 0 | N95: P51700001476 | O95: https://www.maharera.maharashtra.gov.in/projects-search-result?project_state=27&project_district=517&page=40 | P95: 2026-10-11 | Q95: Partially verified: legal name and registration nos. verified on MahaRERA listing. Brand, website, address, contact NOT collected. Company type derived from name suffix only. Project count reflects collected pages only.
A96: D00095 | B96: Ashok Kumar Narayanlal Sahlot | H96: Thane | J96: 1 | K96: 0 | L96: 1 | M96: 0 | N96: P51700005077 | O96: https://www.maharera.maharashtra.gov.in/projects-search-result?project_state=27&project_district=517&page=23 | P96: 2026-10-11 | Q96: Partially verified: legal name and registration nos. verified on MahaRERA listing. Brand, website, address, contact NOT collected. Company type derived from name suffix only. Project count reflects collected pages only.
A97: D00096 | B97: ASHOK MURARI PATIL | H97: Mumbai City | J97: 1 | K97: 0 | L97: 1 | M97: 0 | N97: P51900017760 | O97: https://www.maharera.maharashtra.gov.in/projects-search-result?project_state=27&project_district=519&page=58 | P97: 2026-10-11 | Q97: Partially verified: legal name and registration nos. verified on MahaRERA listing. Brand, website, address, contact NOT collected. Company type derived from name suffix only. Project count reflects collected pages only.
A98: D00097 | B98: Ashok Rajaram Gupta | H98: Mumbai City | J98: 1 | K98: 0 | L98: 1 | M98: 0 | N98: P51900014574 | O98: https://www.maharera.maharashtra.gov.in/projects-search-result?project_state=27&project_district=519&page=48 | P98: 2026-10-11 | Q98: Partially verified: legal name and registration nos. verified on MahaRERA listing. Brand, website, address, contact NOT collected. Company type derived from name suffix only. Project count reflects collected pages only.
A99: D00098 | B99: ASHRAF VALI MOHAMMAD QURESH | H99: Mumbai City | J99: 1 | K99: 0 | L99: 1 | M99: 0 | N99: P51900017724 | O99: https://www.maharera.maharashtra.gov.in/projects-search-result?project_state=27&project_district=519&page=60 | P99: 2026-10-11 | Q99: Partially verified: legal name and registration nos. verified on MahaRERA listing. Brand, website, address, contact NOT collected. Company type derived from name suffix only. Project count reflects collected pages only.
A100: D00099 | B100: Ashta Siddhi Constructions Private Limited | E100: Private Limited Company (from name suffix) | H100: Thane | J100: 1 | K100: 0 | L100: 1 | M100: 0 | N100: P51800000861 | O100: https://www.maharera.maharashtra.gov.in/projects-search-result?project_state=27&project_district=517&page=31 | P100: 2026-10-11 | Q100: Partially verified: legal name and registration nos. verified on MahaRERA listing. Brand, website, address, contact NOT collected. Company type derived from name suffix only. Project count reflects collected pages only.
A101: D00100 | B101: ASHWAMEDH BUILDERS AND DEVELOPERS | H101: Thane | J101: 1 | K101: 0 | L101: 1 | M101: 0 | N101: P51700001143 | O101: https://www.maharera.maharashtra.gov.in/projects-search-result?project_state=27&project_district=517&page=41 | P101: 2026-10-11 | Q101: Partially verified: legal name and registration nos. verified on MahaRERA listing. Brand, website, address, contact NOT collected. Company type derived from name suffix only. Project count reflects collected pages only.
A102: D00101 | B102: ASHWAMEDH CONSTRUCTION | H102: Thane | J102: 1 | K102: 0 | L102: 1 | M102: 0 | N102: P51700002512 | O102: https://www.maharera.maharashtra.gov.in/projects-search-result?project_state=27&project_district=517&page=22 | P102: 2026-10-11 | Q102: Partially verified: legal name and registration nos. verified on MahaRERA listing. Brand, website, address, contact NOT collected. Company type derived from name suffix only. Project count reflects collected pages only.
A103: D00102 | B103: ASIAN VENTURES | H103: Pune | J103: 1 | K103: 1 | L103: 0 | M103: 0 | N103: P52100004157 | O103: https://www.maharera.maharashtra.gov.in/projects-search-result?project_state=27&project_district=521&page=7 | P103: 2026-10-11 | Q103: Partially verified: legal name and registration nos. verified on MahaRERA listing. Brand, website, address, contact NOT collected. Company type derived from name suffix only. Project count reflects collected pages only.
A104: D00103 | B104: ASR Promoters and Developers LLP | E104: LLP (from name suffix) | H104: Pune | J104: 1 | K104: 1 | L104: 0 | M104: 0 | N104: P52100000994 | O104: https://www.maharera.maharashtra.gov.in/projects-search-result?project_state=27&project_district=521&page=11 | P104: 2026-10-11 | Q104: Partially verified: legal name and registration nos. verified on MahaRERA listing. Brand, website, address, contact NOT collected. Company type derived from name suffix only. Project count reflects collected pages only.
A105: D00104 | B105: ASSETS REALITY | H105: Thane | J105: 1 | K105: 0 | L105: 1 | M105: 0 | N105: P51700008568 | O105: https://www.maharera.maharashtra.gov.in/projects-search-result?project_state=27&project_district=517&page=5 | P105: 2026-10-11 | Q105: Partially verified: legal name and registration nos. verified on MahaRERA listing. Brand, website, address, contact NOT collected. Company type derived from name suffix only. Project count reflects collected pages only.
A106: D00105 | B106: ATLANTIC WINDS INFRASTRUCTURE PVT.LTD. | E106: Private Limited Company (from name suffix) | H106: Thane | J106: 1 | K106: 0 | L106: 1 | M106: 0 | N106: P51700005954 | O106: https://www.maharera.maharashtra.gov.in/projects-search-result?project_state=27&project_district=517&page=34 | P106: 2026-10-11 | Q106: Partially verified: legal name and registration nos. verified on MahaRERA listing. Brand, website, address, contact NOT collected. Company type derived from name suffix only. Project count reflects collected pages only.
A107: D00106 | B107: Atlas Infratech Pvt.Ltd | E107: Private Limited Company (from name suffix) | H107: Mumbai City | J107: 2 | K107: 0 | L107: 2 | M107: 0 | N107: P51900013134, P51900015871 | O107: https://www.maharera.maharashtra.gov.in/projects-search-result?project_state=27&project_district=519&page=53 | P107: 2026-10-11 | Q107: Partially verified: legal name and registration nos. verified on MahaRERA listing. Brand, website, address, contact NOT collected. Company type derived from name suffix only. Project count reflects collected pages only.
...

Sheet Registered Projects
A1: Record ID | B1: MahaRERA Registration No. | C1: Project Name | D1: Promoter / Developer Name (as displayed) | E1: Developer ID | F1: Project Address | G1: Locality / Taluka (as displayed) | H1: Pincode | I1: District | J1: Region Group | K1: Sub-region | L1: Latitude | M1: Longitude | N1: Registration Date | O1: Original Completion Date | P1: Revised / Proposed Completion Date | Q1: Current Status (derived from official lists) | R1: Extension Certificate Shown | S1: Revocation / Lapse / Deregistration / Abeyance Indicated | T1: Status Flags Detail | U1: MahaRERA Last Modified | V1: Official Project Detail URL | W1: Source Listing URL | X1: Retrieved Date | Y1: Record Verification | Z1: Verified Fields | AA1: Missing / Unverified Fields | AB1: Status Verification | AC1: Notes
A2: R000001 | B2: P51700000001 | C2: MAYFAIR VISHWARAJA | D2: MAYFAIR HOUSING PRIVATE LIMITED | E2: D00568 | G2: Kalyan | H2: 421605 | I2: Thane | J2: Mumbai MMR | K2: Thane district (incl. Thane, Navi Mumbai-Thane side, Mira-Bhayandar, Kalyan-Dombivli, Bhiwandi, Ulhasnagar, Ambernath) | L2: 19.300941738924593 | M2: 73.21858197033089 | Q2: Registered - no adverse list match | R2: No | S2: No | U2: 2017-05-09 | V2: https://maharerait.maharashtra.gov.in/public/project/view/4 | W2: https://www.maharera.maharashtra.gov.in/projects-search-result?project_state=27&project_district=517&page=1 | X2: 2026-10-11 | Y2: Verified (official listing) | Z2: reg no, project name, promoter, district, taluka, pincode, last modified, detail URL | AA2: project address, registration date, original completion date, revised completion date | AB2: Cross-checked against 5 fully downloaded official lists (deregistered, 3 abeyance lists, NCLT) and the Revoked search (4/9 pages collected - revoked status may be under-reported)
A3: R000002 | B3: P51700000002 | C3: UNNATHI WOODS PHASE VII A | D3: UNNATHI ESTATES | E3: D01097 | G3: Thane | H3: 400615 | I3: Thane | J3: Mumbai MMR | K3: Thane district (incl. Thane, Navi Mumbai-Thane side, Mira-Bhayandar, Kalyan-Dombivli, Bhiwandi, Ulhasnagar, Ambernath) | L3: 19.268511 | M3: 72.97367 | Q3: Registered - no adverse list match | R3: No | S3: No | U3: 2018-04-12 | V3: https://maharerait.maharashtra.gov.in/public/project/view/3 | W3: https://www.maharera.maharashtra.gov.in/projects-search-result?project_state=27&project_district=517&page=1 | X3: 2026-10-11 | Y3: Verified (official listing) | Z3: reg no, project name, promoter, district, taluka, pincode, last modified, detail URL | AA3: project address, registration date, original completion date, revised completion date | AB3: Cross-checked against 5 fully downloaded official lists (deregistered, 3 abeyance lists, NCLT) and the Revoked search (4/9 pages collected - revoked status may be under-reported)
A4: R000003 | B4: P51700000006 | C4: THE PALMS | D4: METRO DEVELOPMENT | E4: D00576 | G4: Thane | H4: 400706 | I4: Thane | J4: Mumbai MMR | K4: Thane district (incl. Thane, Navi Mumbai-Thane side, Mira-Bhayandar, Kalyan-Dombivli, Bhiwandi, Ulhasnagar, Ambernath) | L4: 19.00971 | M4: 73.01719 | Q4: Registered - no adverse list match | R4: No | S4: No | U4: 2017-05-23 | V4: https://maharerait.maharashtra.gov.in/public/project/view/256 | W4: https://www.maharera.maharashtra.gov.in/projects-search-result?project_state=27&project_district=517&page=2 | X4: 2026-10-11 | Y4: Verified (official listing) | Z4: reg no, project name, promoter, district, taluka, pincode, last modified, detail URL | AA4: project address, registration date, original completion date, revised completion date | AB4: Cross-checked against 5 fully downloaded official lists (deregistered, 3 abeyance lists, NCLT) and the Revoked search (4/9 pages collected - revoked status may be under-reported)
A5: R000004 | B5: P51700000009 | C5: N G Silver Spring | D5: RNA Builders (NG) | E5: D00806 | G5: Thane | H5: 401107 | I5: Thane | J5: Mumbai MMR | K5: Thane district (incl. Thane, Navi Mumbai-Thane side, Mira-Bhayandar, Kalyan-Dombivli, Bhiwandi, Ulhasnagar, Ambernath) | L5: 19.2855196 | M5: 72.8692967 | Q5: Registered - no adverse list match | R5: No | S5: No | U5: 2017-05-23 | V5: https://maharerait.maharashtra.gov.in/public/project/view/825 | W5: https://www.maharera.maharashtra.gov.in/projects-search-result?project_state=27&project_district=517&page=2 | X5: 2026-10-11 | Y5: Verified (official listing) | Z5: reg no, project name, promoter, district, taluka, pincode, last modified, detail URL | AA5: project address, registration date, original completion date, revised completion date | AB5: Cross-checked against 5 fully downloaded official lists (deregistered, 3 abeyance lists, NCLT) and the Revoked search (4/9 pages collected - revoked status may be under-reported)
A6: R000005 | B6: P51700000038 | C6: THE WHITE VILLAS | D6: St. Angelo's VNCT Ventures Pvt. Ltd. | E6: D01024 | G6: Shahapur | H6: 420601 | I6: Thane | J6: Mumbai MMR | K6: Thane district (incl. Thane, Navi Mumbai-Thane side, Mira-Bhayandar, Kalyan-Dombivli, Bhiwandi, Ulhasnagar, Ambernath) | L6: 19.4559236 | M6: 73.3296037 | Q6: Registered - no adverse list match | R6: Yes | S6: No | U6: 2026-09-26 | V6: https://maharerait.maharashtra.gov.in/public/project/view/2491 | W6: https://www.maharera.maharashtra.gov.in/projects-search-result?project_state=27&project_district=517&page=4 | X6: 2026-10-11 | Y6: Verified (official listing) | Z6: reg no, project name, promoter, district, taluka, pincode, last modified, detail URL | AA6: project address, registration date, original completion date, revised completion date | AB6: Cross-checked against 5 fully downloaded official lists (deregistered, 3 abeyance lists, NCLT) and the Revoked search (4/9 pages collected - revoked status may be under-reported)
A7: R000006 | B7: P51700000053 | C7: GOLDSTAR DECENT HOMES | D7: GOLDSTAR SANKALP CONSTRUCTION | E7: D00305 | G7: Thane | H7: 401107 | I7: Thane | J7: Mumbai MMR | K7: Thane district (incl. Thane, Navi Mumbai-Thane side, Mira-Bhayandar, Kalyan-Dombivli, Bhiwandi, Ulhasnagar, Ambernath) | L7: 19.281762 | M7: 72.881768 | Q7: Registered - no adverse list match | R7: Yes | S7: No | U7: 2019-01-09 | V7: https://maharerait.maharashtra.gov.in/public/project/view/166 | W7: https://www.maharera.maharashtra.gov.in/projects-search-result?project_state=27&project_district=517&page=1 | X7: 2026-10-11 | Y7: Verified (official listing) | Z7: reg no, project name, promoter, district, taluka, pincode, last modified, detail URL | AA7: project address, registration date, original completion date, revised completion date | AB7: Cross-checked against 5 fully downloaded official lists (deregistered, 3 abeyance lists, NCLT) and the Revoked search (4/9 pages collected - revoked status may be under-reported)
A8: R000007 | B8: P51700000064 | C8: TULSI AAHAN | D8: RAJ GROUP | E8: D00777 | G8: Ambarnath | H8: 421503 | I8: Thane | J8: Mumbai MMR | K8: Thane district (incl. Thane, Navi Mumbai-Thane side, Mira-Bhayandar, Kalyan-Dombivli, Bhiwandi, Ulhasnagar, Ambernath) | L8: 19.1667854 | M8: 73.2367896 | Q8: Registered - no adverse list match | R8: No | S8: No | U8: 2017-06-22 | V8: https://maharerait.maharashtra.gov.in/public/project/view/1283 | W8: https://www.maharera.maharashtra.gov.in/projects-search-result?project_state=27&project_district=517&page=2 | X8: 2026-10-11 | Y8: Verified (official listing) | Z8: reg no, project name, promoter, district, taluka, pincode, last modified, detail URL | AA8: project address, registration date, original completion date, revised completion date | AB8: Cross-checked against 5 fully downloaded official lists (deregistered, 3 abeyance lists, NCLT) and the Revoked search (4/9 pages collected - revoked status may be under-reported)
A9: R000008 | B9: P51700000068 | C9: NG GRAND PLAZA PHASE I | D9: OM NAMAH SHIVAY DEVELOPERS PRIVATE LIMITED | E9: D00679 | G9: Thane | H9: 400701 | I9: Thane | J9: Mumbai MMR | K9: Thane district (incl. Thane, Navi Mumbai-Thane side, Mira-Bhayandar, Kalyan-Dombivli, Bhiwandi, Ulhasnagar, Ambernath) | L9: 19.118673 | M9: 72.992341 | Q9: Registered - no adverse list match | R9: No | S9: No | U9: 2017-06-22 | V9: https://maharerait.maharashtra.gov.in/public/project/view/2943 | W9: https://www.maharera.maharashtra.gov.in/projects-search-result?project_state=27&project_district=517&page=5 | X9: 2026-10-11 | Y9: Verified (official listing) | Z9: reg no, project name, promoter, district, taluka, pincode, last modified, detail URL | AA9: project address, registration date, original completion date, revised completion date | AB9: Cross-checked against 5 fully downloaded official lists (deregistered, 3 abeyance lists, NCLT) and the Revoked search (4/9 pages collected - revoked status may be under-reported)
A10: R000009 | B10: P51700000074 | C10: Juhi Serenity | D10: Vijaykumar Baldev Bajaj | E10: D01139 | G10: Thane | H10: 400701 | I10: Thane | J10: Mumbai MMR | K10: Thane district (incl. Thane, Navi Mumbai-Thane side, Mira-Bhayandar, Kalyan-Dombivli, Bhiwandi, Ulhasnagar, Ambernath) | L10: 19.118294 | M10: 72.996908 | Q10: Registered - no adverse list match | R10: No | S10: No | U10: 2017-06-28 | V10: https://maharerait.maharashtra.gov.in/public/project/view/3212 | W10: https://www.maharera.maharashtra.gov.in/projects-search-result?project_state=27&project_district=517&page=8 | X10: 2026-10-11 | Y10: Verified (official listing) | Z10: reg no, project name, promoter, district, taluka, pincode, last modified, detail URL | AA10: project address, registration date, original completion date, revised completion date | AB10: Cross-checked against 5 fully downloaded official lists (deregistered, 3 abeyance lists, NCLT) and the Revoked search (4/9 pages collected - revoked status may be under-reported)
A11: R000010 | B11: P51700000089 | C11: Eagleton | D11: ROMA BUILDERS PRIVATE LIMITED | E11: D00811 | G11: Thane | H11: 400607 | I11: Thane | J11: Mumbai MMR | K11: Thane district (incl. Thane, Navi Mumbai-Thane side, Mira-Bhayandar, Kalyan-Dombivli, Bhiwandi, Ulhasnagar, Ambernath) | L11: 19.24360352 | M11: 72.97722982 | Q11: Registered - no adverse list match | R11: No | S11: No | U11: 2017-06-29 | V11: https://maharerait.maharashtra.gov.in/public/project/view/3090 | W11: https://www.maharera.maharashtra.gov.in/projects-search-result?project_state=27&project_district=517&page=7 | X11: 2026-10-11 | Y11: Verified (official listing) | Z11: reg no, project name, promoter, district, taluka, pincode, last modified, detail URL | AA11: project address, registration date, original completion date, revised completion date | AB11: Cross-checked against 5 fully downloaded official lists (deregistered, 3 abeyance lists, NCLT) and the Revoked search (4/9 pages collected - revoked status may be under-reported)
A12: R000011 | B12: P51700000091 | C12: Hampton | D12: ROMA BUILDERS PRIVATE LIMITED | E12: D00811 | G12: Thane | H12: 400607 | I12: Thane | J12: Mumbai MMR | K12: Thane district (incl. Thane, Navi Mumbai-Thane side, Mira-Bhayandar, Kalyan-Dombivli, Bhiwandi, Ulhasnagar, Ambernath) | L12: 19.24360352 | M12: 72.97722982 | Q12: Registered - no adverse list match | R12: No | S12: No | U12: 2017-06-30 | V12: https://maharerait.maharashtra.gov.in/public/project/view/3293 | W12: https://www.maharera.maharashtra.gov.in/projects-search-result?project_state=27&project_district=517&page=8 | X12: 2026-10-11 | Y12: Verified (official listing) | Z12: reg no, project name, promoter, district, taluka, pincode, last modified, detail URL | AA12: project address, registration date, original completion date, revised completion date | AB12: Cross-checked against 5 fully downloaded official lists (deregistered, 3 abeyance lists, NCLT) and the Revoked search (4/9 pages collected - revoked status may be under-reported)
A13: R000012 | B13: P51700000095 | C13: Evergreen Heights | D13: Vijay Vasudev Wadhwa | E13: D01138 | G13: Thane | H13: 400605 | I13: Thane | J13: Mumbai MMR | K13: Thane district (incl. Thane, Navi Mumbai-Thane side, Mira-Bhayandar, Kalyan-Dombivli, Bhiwandi, Ulhasnagar, Ambernath) | L13: 19.206852 | M13: 73.014004 | Q13: Registered - no adverse list match | R13: No | S13: No | U13: 2017-06-30 | V13: https://maharerait.maharashtra.gov.in/public/project/view/228 | W13: https://www.maharera.maharashtra.gov.in/projects-search-result?project_state=27&project_district=517&page=1 | X13: 2026-10-11 | Y13: Verified (official listing) | Z13: reg no, project name, promoter, district, taluka, pincode, last modified, detail URL | AA13: project address, registration date, original completion date, revised completion date | AB13: Cross-checked against 5 fully downloaded official lists (deregistered, 3 abeyance lists, NCLT) and the Revoked search (4/9 pages collected - revoked status may be under-reported)
... A95: R000094 | B95: P51700000656 | C95: Panvelkar Homes - Phase II | D95: Om Sai Constructions | E95: D00681 | G95: Ambarnath | H95: 421501 | I95: Thane | J95: Mumbai MMR | K95: Thane district (incl. Thane, Navi Mumbai-Thane side, Mira-Bhayandar, Kalyan-Dombivli, Bhiwandi, Ulhasnagar, Ambernath) | L95: 19.208057 | M95: 73.205729 | Q95: Registered - no adverse list match | R95: No | S95: No | U95: 2019-03-05 | V95: https://maharerait.maharashtra.gov.in/public/project/view/5656 | W95: https://www.maharera.maharashtra.gov.in/projects-search-result?project_state=27&project_district=517&page=29 | X95: 2026-10-11 | Y95: Verified (official listing) | Z95: reg no, project name, promoter, district, taluka, pincode, last modified, detail URL | AA95: project address, registration date, original completion date, revised completion date | AB95: Cross-checked against 5 fully downloaded official lists (deregistered, 3 abeyance lists, NCLT) and the Revoked search (4/9 pages collected - revoked status may be under-reported)
A96: R000095 | B96: P51700000659 | C96: LODHA SPLENDORA - PLATINO - D | D96: MACROTECH DEVELOPERS LIMITED | E96: D00539 | G96: Thane | H96: 400607 | I96: Thane | J96: Mumbai MMR | K96: Thane district (incl. Thane, Navi Mumbai-Thane side, Mira-Bhayandar, Kalyan-Dombivli, Bhiwandi, Ulhasnagar, Ambernath) | L96: 19.2392834 | M96: 72.9873924 | Q96: Deregistered | R96: No | S96: Yes | T96: Deregistered: Planning authority: TMC | U96: 2018-04-06 | V96: https://maharerait.maharashtra.gov.in/public/project/view/2096 | W96: https://www.maharera.maharashtra.gov.in/projects-search-result?project_state=27&project_district=517&page=3 | X96: 2026-10-11 | Y96: Verified (official listing) | Z96: reg no, project name, promoter, district, taluka, pincode, last modified, detail URL | AA96: project address, registration date, original completion date, revised completion date | AB96: Cross-checked against 5 fully downloaded official lists (deregistered, 3 abeyance lists, NCLT) and the Revoked search (4/9 pages collected - revoked status may be under-reported)
A97: R000096 | B97: P51700000681 | C97: Courtyard - Ornella | D97: COURTYARD REAL ESTATE PRIVATE LIMITED | E97: D00179 | G97: Thane | H97: 400601 | I97: Thane | J97: Mumbai MMR | K97: Thane district (incl. Thane, Navi Mumbai-Thane side, Mira-Bhayandar, Kalyan-Dombivli, Bhiwandi, Ulhasnagar, Ambernath) | L97: 19.220122 | M97: 72.9637 | Q97: Registered - no adverse list match | R97: No | S97: No | U97: 2017-07-20 | V97: https://maharerait.maharashtra.gov.in/public/project/view/3236 | W97: https://www.maharera.maharashtra.gov.in/projects-search-result?project_state=27&project_district=517&page=8 | X97: 2026-10-11 | Y97: Verified (official listing) | Z97: reg no, project name, promoter, district, taluka, pincode, last modified, detail URL | AA97: project address, registration date, original completion date, revised completion date | AB97: Cross-checked against 5 fully downloaded official lists (deregistered, 3 abeyance lists, NCLT) and the Revoked search (4/9 pages collected - revoked status may be under-reported)
A98: R000097 | B98: P51700000686 | C98: MARATHON NEXTOWN EMERALD | D98: MARATHON ENER-GEN | E98: D00562 | G98: Thane | H98: 421201 | I98: Thane | J98: Mumbai MMR | K98: Thane district (incl. Thane, Navi Mumbai-Thane side, Mira-Bhayandar, Kalyan-Dombivli, Bhiwandi, Ulhasnagar, Ambernath) | L98: 19.161664 | M98: 73.055094 | Q98: Registered - no adverse list match | R98: Yes | S98: No | U98: 2020-06-13 | V98: https://maharerait.maharashtra.gov.in/public/project/view/4543 | W98: https://www.maharera.maharashtra.gov.in/projects-search-result?project_state=27&project_district=517&page=16 | X98: 2026-10-11 | Y98: Verified (official listing) | Z98: reg no, project name, promoter, district, taluka, pincode, last modified, detail URL | AA98: project address, registration date, original completion date, revised completion date | AB98: Cross-checked against 5 fully downloaded official lists (deregistered, 3 abeyance lists, NCLT) and the Revoked search (4/9 pages collected - revoked status may be under-reported)
A99: R000098 | B99: P51700000689 | C99: Rumahbali Phase 2 | D99: Puranik Builders Limited | E99: D00761 | G99: Thane | H99: 400615 | I99: Thane | J99: Mumbai MMR | K99: Thane district (incl. Thane, Navi Mumbai-Thane side, Mira-Bhayandar, Kalyan-Dombivli, Bhiwandi, Ulhasnagar, Ambernath) | L99: 19.271548 | M99: 72.9637728 | Q99: Registered - no adverse list match | R99: No | S99: No | U99: 2017-07-20 | V99: https://maharerait.maharashtra.gov.in/public/project/view/4016 | W99: https://www.maharera.maharashtra.gov.in/projects-search-result?project_state=27&project_district=517&page=11 | X99: 2026-10-11 | Y99: Verified (official listing) | Z99: reg no, project name, promoter, district, taluka, pincode, last modified, detail URL | AA99: project address, registration date, original completion date, revised completion date | AB99: Cross-checked against 5 fully downloaded official lists (deregistered, 3 abeyance lists, NCLT) and the Revoked search (4/9 pages collected - revoked status may be under-reported)
A100: R000099 | B100: P51700000696 | C100: PALAVA URBANO G AND H | D100: Palava Dwellers Private Limited | E100: D00697 | G100: Kalyan | H100: 421202 | I100: Thane | J100: Mumbai MMR | K100: Thane district (incl. Thane, Navi Mumbai-Thane side, Mira-Bhayandar, Kalyan-Dombivli, Bhiwandi, Ulhasnagar, Ambernath) | L100: 19.1714522 | M100: 73.1190742 | Q100: Registered - no adverse list match | R100: No | S100: No | U100: 2018-09-28 | V100: https://maharerait.maharashtra.gov.in/public/project/view/4275 | W100: https://www.maharera.maharashtra.gov.in/projects-search-result?project_state=27&project_district=517&page=14 | X100: 2026-10-11 | Y100: Verified (official listing) | Z100: reg no, project name, promoter, district, taluka, pincode, last modified, detail URL | AA100: project address, registration date, original completion date, revised completion date | AB100: Cross-checked against 5 fully downloaded official lists (deregistered, 3 abeyance lists, NCLT) and the Revoked search (4/9 pages collected - revoked status may be under-reported)
A101: R000100 | B101: P51700000704 | C101: Amanda Shopping | D101: HIRANANDANI PROPERTIES PRIVATE LIMITED | E101: D00352 | G101: Thane | H101: 400610 | I101: Thane | J101: Mumbai MMR | K101: Thane district (incl. Thane, Navi Mumbai-Thane side, Mira-Bhayandar, Kalyan-Dombivli, Bhiwandi, Ulhasnagar, Ambernath) | L101: 19.22728624110684 | M101: 72.9735051871719 | Q101: Registered - no adverse list match | R101: No | S101: No | U101: 2017-07-20 | V101: https://maharerait.maharashtra.gov.in/public/project/view/5677 | W101: https://www.maharera.maharashtra.gov.in/projects-search-result?project_state=27&project_district=517&page=29 | X101: 2026-10-11 | Y101: Verified (official listing) | Z101: reg no, project name, promoter, district, taluka, pincode, last modified, detail URL | AA101: project address, registration date, original completion date, revised completion date | AB101: Cross-checked against 5 fully downloaded official lists (deregistered, 3 abeyance lists, NCLT) and the Revoked search (4/9 pages collected - revoked status may be under-reported)
A102: R000101 | B102: P51700000714 | C102: Courtyard - Onyx | D102: COURTYARD REAL ESTATE PRIVATE LIMITED | E102: D00179 | G102: Thane | H102: 400601 | I102: Thane | J102: Mumbai MMR | K102: Thane district (incl. Thane, Navi Mumbai-Thane side, Mira-Bhayandar, Kalyan-Dombivli, Bhiwandi, Ulhasnagar, Ambernath) | L102: 19.220892 | M102: 72.96492 | Q102: Registered - no adverse list match | R102: No | S102: No | U102: 2017-07-20 | V102: https://maharerait.maharashtra.gov.in/public/project/view/3275 | W102: https://www.maharera.maharashtra.gov.in/projects-search-result?project_state=27&project_district=517&page=8 | X102: 2026-10-11 | Y102: Verified (official listing) | Z102: reg no, project name, promoter, district, taluka, pincode, last modified, detail URL | AA102: project address, registration date, original completion date, revised completion date | AB102: Cross-checked against 5 fully downloaded official lists (deregistered, 3 abeyance lists, NCLT) and the Revoked search (4/9 pages collected - revoked status may be under-reported)
A103: R000102 | B103: P51700000725 | C103: SARVODAY AANAND | D103: OM SAI LAND DEVELOPERS | E103: D00682 | G103: Kalyan | H103: 421202 | I103: Thane | J103: Mumbai MMR | K103: Thane district (incl. Thane, Navi Mumbai-Thane side, Mira-Bhayandar, Kalyan-Dombivli, Bhiwandi, Ulhasnagar, Ambernath) | L103: 19.221922 | M103: 73.082294 | Q103: Registered - no adverse list match | R103: Yes | S103: No | U103: 2026-10-06 | V103: https://maharerait.maharashtra.gov.in/public/project/view/5117 | W103: https://www.maharera.maharashtra.gov.in/projects-search-result?project_state=27&project_district=517&page=23 | X103: 2026-10-11 | Y103: Verified (official listing) | Z103: reg no, project name, promoter, district, taluka, pincode, last modified, detail URL | AA103: project address, registration date, original completion date, revised completion date | AB103: Cross-checked against 5 fully downloaded official lists (deregistered, 3 abeyance lists, NCLT) and the Revoked search (4/9 pages collected - revoked status may be under-reported)
A104: R000103 | B104: P51700000732 | C104: Immensa D | D104: Agile Real Estate Pvt. Ltd. | E104: D00038 | G104: Thane | H104: 400607 | I104: Thane | J104: Mumbai MMR | K104: Thane district (incl. Thane, Navi Mumbai-Thane side, Mira-Bhayandar, Kalyan-Dombivli, Bhiwandi, Ulhasnagar, Ambernath) | L104: 19.2317808758669 | M104: 72.99011107794036 | Q104: Registered - no adverse list match | R104: No | S104: No | U104: 2024-05-20 | V104: https://maharerait.maharashtra.gov.in/public/project/view/5415 | W104: https://www.maharera.maharashtra.gov.in/projects-search-result?project_state=27&project_district=517&page=27 | X104: 2026-10-11 | Y104: Verified (official listing) | Z104: reg no, project name, promoter, district, taluka, pincode, last modified, detail URL | AA104: project address, registration date, original completion date, revised completion date | AB104: Cross-checked against 5 fully downloaded official lists (deregistered, 3 abeyance lists, NCLT) and the Revoked search (4/9 pages collected - revoked status may be under-reported)
A105: R000104 | B105: P51700000734 | C105: VASANT FIONA | D105: Sheth Developers Private Limited | E105: D00917 | G105: Thane | H105: 400601 | I105: Thane | J105: Mumbai MMR | K105: Thane district (incl. Thane, Navi Mumbai-Thane side, Mira-Bhayandar, Kalyan-Dombivli, Bhiwandi, Ulhasnagar, Ambernath) | L105: 19.2010502 | M105: 72.9785353 | Q105: Registered - no adverse list match | R105: No | S105: No | U105: 2017-07-23 | V105: https://maharerait.maharashtra.gov.in/public/project/view/2723 | W105: https://www.maharera.maharashtra.gov.in/projects-search-result?project_state=27&project_district=517&page=5 | X105: 2026-10-11 | Y105: Verified (official listing) | Z105: reg no, project name, promoter, district, taluka, pincode, last modified, detail URL | AA105: project address, registration date, original completion date, revised completion date | AB105: Cross-checked against 5 fully downloaded official lists (deregistered, 3 abeyance lists, NCLT) and the Revoked search (4/9 pages collected - revoked status may be under-reported)
A106: R000105 | B106: P51700000736 | C106: SKY VILLAS WING A1 AND WING A2 | D106: VERTEX NEWTON PROJECTS PRIVATE LIMITED | E106: D01128 | G106: Kalyan | H106: 421301 | I106: Thane | J106: Mumbai MMR | K106: Thane district (incl. Thane, Navi Mumbai-Thane side, Mira-Bhayandar, Kalyan-Dombivli, Bhiwandi, Ulhasnagar, Ambernath) | L106: 19.2527132 | M106: 73.1290596 | Q106: Registered - no adverse list match | R106: No | S106: No | U106: 2017-07-23 | V106: https://maharerait.maharashtra.gov.in/public/project/view/6172 | W106: https://www.maharera.maharashtra.gov.in/projects-search-result?project_state=27&project_district=517&page=34 | X106: 2026-10-11 | Y106: Verified (official listing) | Z106: reg no, project name, promoter, district, taluka, pincode, last modified, detail URL | AA106: project address, registration date, original completion date, revised completion date | AB106: Cross-checked against 5 fully downloaded official lists (deregistered, 3 abeyance lists, NCLT) and the Revoked search (4/9 pages collected - revoked status may be under-reported)
A107: R000106 | B107: P51700000743 | C107: PRAMUKH SADAN | D107: SAHAJANAND DEVELOPERS | E107: D00845 | G107: Ambarnath | H107: 421501 | I107: Thane | J107: Mumbai MMR | K107: Thane district (incl. Thane, Navi Mumbai-Thane side, Mira-Bhayandar, Kalyan-Dombivli, Bhiwandi, Ulhasnagar, Ambernath) | L107: 19.2007023 | M107: 73.1880618 | Q107: Registered - no adverse list match | R107: No | S107: No | U107: 2017-07-23 | V107: https://maharerait.maharashtra.gov.in/public/project/view/3564 | W107: https://www.maharera.maharashtra.gov.in/projects-search-result?project_state=27&project_district=517&page=9 | X107: 2026-10-11 | Y107: Verified (official listing) | Z107: reg no, project name, promoter, district, taluka, pincode, last modified, detail URL | AA107: project address, registration date, original completion date, revised completion date | AB107: Cross-checked against 5 fully downloaded official lists (deregistered, 3 abeyance lists, NCLT) and the Revoked search (4/9 pages collected - revoked status may be under-reported)
A108: R000107 | B108: P51700000745 | C108: PATEL RESIDENCY NX | D108: NAVNIRMAN DEVELOPERS | E108: D00633 | G108: Ambarnath | H108: 421501 | I108: Thane | J108: Mumbai MMR | K108: Thane district (incl. Thane, Navi Mumbai-Thane side, Mira-Bhayandar, Kalyan-Dombivli, Bhiwandi, Ulhasnagar, Ambernath) | L108: 19.2007023 | M108: 73.1880618 | Q108: Registered - no adverse list match | R108: No | S108: No | U108: 2017-07-23 | V108: https://maharerait.maharashtra.gov.in/public/project/view/3967 | W108: https://www.maharera.maharashtra.gov.in/projects-search-result?project_state=27&project_district=517&page=11 | X108: 2026-10-11 | Y108: Verified (official listing) | Z108: reg no, project name, promoter, district, taluka, pincode, last modified, detail URL | AA108: project address, registration date, original completion date, revised completion date | AB108: Cross-checked against 5 fully downloaded official lists (deregistered, 3 abeyance lists, NCLT) and the Revoked search (4/9 pages collected - revoked status may be under-reported)
... A197: R000196 | B197: P51700001561 | C197: MEERA PARK ROYALE | D197: SARASWATI BUILDCON | E197: D00887 | G197: Ambarnath | H197: 421501 | I197: Thane | J197: Mumbai MMR | K197: Thane district (incl. Thane, Navi Mumbai-Thane side, Mira-Bhayandar, Kalyan-Dombivli, Bhiwandi, Ulhasnagar, Ambernath) | L197: 19.192824968749388 | M197: 73.19552023554729 | Q197: Registered - no adverse list match | R197: Yes | S197: No | U197: 2021-09-09 | V197: https://maharerait.maharashtra.gov.in/public/project/view/6730 | W197: https://www.maharera.maharashtra.gov.in/projects-search-result?project_state=27&project_district=517&page=40 | X197: 2026-10-11 | Y197: Verified (official listing) | Z197: reg no, project name, promoter, district, taluka, pincode, last modified, detail URL | AA197: project address, registration date, original completion date, revised completion date | AB197: Cross-checked against 5 fully downloaded official lists (deregistered, 3 abeyance lists, NCLT) and the Revoked search (4/9 pages collected - revoked status may be under-reported)
A198: R000197 | B198: P51700001566 | C198: SAI WORLD RETREAT | D198: Paradise Leisure Homes | E198: D00704 | G198: Ulhasnagar | H198: 421002 | I198: Thane | J198: Mumbai MMR | K198: Thane district (incl. Thane, Navi Mumbai-Thane side, Mira-Bhayandar, Kalyan-Dombivli, Bhiwandi, Ulhasnagar, Ambernath) | L198: 18.765335 | M198: 73.436267 | Q198: Deregistered | R198: No | S198: Yes | T198: Deregistered: Planning authority: PMRDA | U198: 2017-07-28 | V198: https://maharerait.maharashtra.gov.in/public/project/view/4872 | W198: https://www.maharera.maharashtra.gov.in/projects-search-result?project_state=27&project_district=517&page=20 | X198: 2026-10-11 | Y198: Verified (official listing) | Z198: reg no, project name, promoter, district, taluka, pincode, last modified, detail URL | AA198: project address, registration date, original completion date, revised completion date | AB198: Cross-checked against 5 fully downloaded official lists (deregistered, 3 abeyance lists, NCLT) and the Revoked search (4/9 pages collected - revoked status may be under-reported)
A199: R000198 | B199: P51700001570 | C199: GOPAL KRISHNA | D199: SONAL DEV-CON PVT LTD | E199: D01011 | G199: Thane | H199: 400614 | I199: Thane | J199: Mumbai MMR | K199: Thane district (incl. Thane, Navi Mumbai-Thane side, Mira-Bhayandar, Kalyan-Dombivli, Bhiwandi, Ulhasnagar, Ambernath) | L199: 19.02296510646092 | M199: 73.03490847519072 | Q199: Registered - no adverse list match | R199: Yes | S199: No | U199: 2026-08-20 | V199: https://maharerait.maharashtra.gov.in/public/project/view/7058 | W199: https://www.maharera.maharashtra.gov.in/projects-search-result?project_state=27&project_district=517&page=43 | X199: 2026-10-11 | Y199: Verified (official listing) | Z199: reg no, project name, promoter, district, taluka, pincode, last modified, detail URL | AA199: project address, registration date, original completion date, revised completion date | AB199: Cross-checked against 5 fully downloaded official lists (deregistered, 3 abeyance lists, NCLT) and the Revoked search (4/9 pages collected - revoked status may be under-reported)
A200: R000199 | B200: P51700001574 | C200: MAITHILI PRIDE | D200: MAITHILI KALPVRUKSH PRIVATE LIMITED | E200: D00545 | G200: Thane | H200: 400606 | I200: Thane | J200: Mumbai MMR | K200: Thane district (incl. Thane, Navi Mumbai-Thane side, Mira-Bhayandar, Kalyan-Dombivli, Bhiwandi, Ulhasnagar, Ambernath) | L200: 19.212512 | M200: 72.960472 | Q200: Registered - no adverse list match | R200: Yes | S200: No | U200: 2021-09-09 | V200: https://maharerait.maharashtra.gov.in/public/project/view/6586 | W200: https://www.maharera.maharashtra.gov.in/projects-search-result?project_state=27&project_district=517&page=38 | X200: 2026-10-11 | Y200: Verified (official listing) | Z200: reg no, project name, promoter, district, taluka, pincode, last modified, detail URL | AA200: project address, registration date, original completion date, revised completion date | AB200: Cross-checked against 5 fully downloaded official lists (deregistered, 3 abeyance lists, NCLT) and the Revoked search (4/9 pages collected - revoked status may be under-reported)
A201: R000200 | B201: P51700001595 | C201: SHREE SHASHWAT BUILDING NO 19 | D201: Shashwat Developers | E201: D00913 | G201: Thane | H201: 401107 | I201: Thane | J201: Mumbai MMR | K201: Thane district (incl. Thane, Navi Mumbai-Thane side, Mira-Bhayandar, Kalyan-Dombivli, Bhiwandi, Ulhasnagar, Ambernath) | L201: 19.2763286 | M201: 72.8759478 | Q201: Registered - no adverse list match | R201: Yes | S201: No | U201: 2021-09-09 | V201: https://maharerait.maharashtra.gov.in/public/project/view/5792 | W201: https://www.maharera.maharashtra.gov.in/projects-search-result?project_state=27&project_district=517&page=30 | X201: 2026-10-11 | Y201: Verified (official listing) | Z201: reg no, project name, promoter, district, taluka, pincode, last modified, detail URL | AA201: project address, registration date, original completion date, revised completion date | AB201: Cross-checked against 5 fully downloaded official lists (deregistered, 3 abeyance lists, NCLT) and the Revoked search (4/9 pages collected - revoked status may be under-reported)
A202: R000201 | B202: P51700001597 | C202: SIDDHICITY | D202: Siddhitech Homes Private Limited | E202: D00990 | G202: Ambarnath | H202: 421503 | I202: Thane | J202: Mumbai MMR | K202: Thane district (incl. Thane, Navi Mumbai-Thane side, Mira-Bhayandar, Kalyan-Dombivli, Bhiwandi, Ulhasnagar, Ambernath) | L202: 19.142212 | M202: 73.246316 | Q202: Registered - no adverse list match | R202: Yes | S202: No | U202: 2018-06-25 | V202: https://maharerait.maharashtra.gov.in/public/project/view/6015 | W202: https://www.maharera.maharashtra.gov.in/projects-search-result?project_state=27&project_district=517&page=33 | X202: 2026-10-11 | Y202: Verified (official listing) | Z202: reg no, project name, promoter, district, taluka, pincode, last modified, detail URL | AA202: project address, registration date, original completion date, revised completion date | AB202: Cross-checked against 5 fully downloaded official lists (deregistered, 3 abeyance lists, NCLT) and the Revoked search (4/9 pages collected - revoked status may be under-reported)
A203: R000202 | B203: P51700001599 | C203: DIVYA JYOT COMPLEX | D203: SHREE ADITI DEVELOPERS | E203: D00934 | G203: Ambarnath | H203: 421503 | I203: Thane | J203: Mumbai MMR | K203: Thane district (incl. Thane, Navi Mumbai-Thane side, Mira-Bhayandar, Kalyan-Dombivli, Bhiwandi, Ulhasnagar, Ambernath) | L203: 19.176718 | M203: 73.240037 | Q203: Registered - no adverse list match | R203: No | S203: No | U203: 2017-07-29 | V203: https://maharerait.maharashtra.gov.in/public/project/view/5681 | W203: https://www.maharera.maharashtra.gov.in/projects-search-result?project_state=27&project_district=517&page=29 | X203: 2026-10-11 | Y203: Verified (official listing) | Z203: reg no, project name, promoter, district, taluka, pincode, last modified, detail URL | AA203: project address, registration date, original completion date, revised completion date | AB203: Cross-checked against 5 fully downloaded official lists (deregistered, 3 abeyance lists, NCLT) and the Revoked search (4/9 pages collected - revoked status may be under-reported)
A204: R000203 | B204: P51700001611 | C204: Flamingo | D204: ROMA BUILDERS PRIVATE LIMITED | E204: D00811 | G204: Thane | H204: 400607 | I204: Thane | J204: Mumbai MMR | K204: Thane district (incl. Thane, Navi Mumbai-Thane side, Mira-Bhayandar, Kalyan-Dombivli, Bhiwandi, Ulhasnagar, Ambernath) | L204: 19.258675210294903 | M204: 72.9839840589691 | Q204: Registered - no adverse list match | R204: No | S204: No | U204: 2018-01-03 | V204: https://maharerait.maharashtra.gov.in/public/project/view/6889 | W204: https://www.maharera.maharashtra.gov.in/projects-search-result?project_state=27&project_district=517&page=42 | X204: 2026-10-11 | Y204: Verified (official listing) | Z204: reg no, project name, promoter, district, taluka, pincode, last modified, detail URL | AA204: project address, registration date, original completion date, revised completion date | AB204: Cross-checked against 5 fully downloaded official lists (deregistered, 3 abeyance lists, NCLT) and the Revoked search (4/9 pages collected - revoked status may be under-reported)
A205: R000204 | B205: P51700001636 | C205: SAMRIDDHI | D205: A G SUPERSTRUCTURES PVT LTD | E205: D00001 | G205: Thane | H205: 401105 | I205: Thane | J205: Mumbai MMR | K205: Thane district (incl. Thane, Navi Mumbai-Thane side, Mira-Bhayandar, Kalyan-Dombivli, Bhiwandi, Ulhasnagar, Ambernath) | L205: 19.135317194650696 | M205: 72.96710337187506 | Q205: Registered - no adverse list match | R205: Yes | S205: No | U205: 2021-09-09 | V205: https://maharerait.maharashtra.gov.in/public/project/view/25 | W205: https://www.maharera.maharashtra.gov.in/projects-search-result?project_state=27&project_district=517&page=1 | X205: 2026-10-11 | Y205: Verified (official listing) | Z205: reg no, project name, promoter, district, taluka, pincode, last modified, detail URL | AA205: project address, registration date, original completion date, revised completion date | AB205: Cross-checked against 5 fully downloaded official lists (deregistered, 3 abeyance lists, NCLT) and the Revoked search (4/9 pages collected - revoked status may be under-reported)
A206: R000205 | B206: P51700001641 | C206: Kohinoor Castles | D206: Kohinoor Castles | E206: D00444 | G206: Ambarnath | H206: 421505 | I206: Thane | J206: Mumbai MMR | K206: Thane district (incl. Thane, Navi Mumbai-Thane side, Mira-Bhayandar, Kalyan-Dombivli, Bhiwandi, Ulhasnagar, Ambernath) | L206: 19.186329 | M206: 73.22126300000002 | Q206: Registered - no adverse list match | R206: No | S206: No | U206: 2017-07-29 | V206: https://maharerait.maharashtra.gov.in/public/project/view/6892 | W206: https://www.maharera.maharashtra.gov.in/projects-search-result?project_state=27&project_district=517&page=42 | X206: 2026-10-11 | Y206: Verified (official listing) | Z206: reg no, project name, promoter, district, taluka, pincode, last modified, detail URL | AA206: project address, registration date, original completion date, revised completion date | AB206: Cross-checked against 5 fully downloaded official lists (deregistered, 3 abeyance lists, NCLT) and the Revoked search (4/9 pages collected - revoked status may be under-reported)
A207: R000206 | B207: P51700001654 | C207: VISHWAJEET ELITE | D207: VISHWAJEET MEADOWS | E207: D01158 | G207: Ambarnath | H207: 421501 | I207: Thane | J207: Mumbai MMR | K207: Thane district (incl. Thane, Navi Mumbai-Thane side, Mira-Bhayandar, Kalyan-Dombivli, Bhiwandi, Ulhasnagar, Ambernath) | L207: 19.2007023 | M207: 73.1880618 | Q207: Registered - no adverse list match | R207: Yes | S207: No | U207: 2018-10-12 | V207: https://maharerait.maharashtra.gov.in/public/project/view/2327 | W207: https://www.maharera.maharashtra.gov.in/projects-search-result?project_state=27&project_district=517&page=4 | X207: 2026-10-11 | Y207: Verified (official listing) | Z207: reg no, project name, promoter, district, taluka, pincode, last modified, detail URL | AA207: project address, registration date, original completion date, revised completion date | AB207: Cross-checked against 5 fully downloaded official lists (deregistered, 3 abeyance lists, NCLT) and the Revoked search (4/9 pages collected - revoked status may be under-reported)
A208: R000207 | B208: P51700001682 | C208: EKDANT DEVELOPERS | D208: EKDANT DEVELOPERS | E208: D00247 | G208: Kalyan | H208: 421201 | I208: Thane | J208: Mumbai MMR | K208: Thane district (incl. Thane, Navi Mumbai-Thane side, Mira-Bhayandar, Kalyan-Dombivli, Bhiwandi, Ulhasnagar, Ambernath) | L208: 19.2116805 | M208: 73.0907 | Q208: Registered - no adverse list match | R208: No | S208: No | U208: 2017-07-29 | V208: https://maharerait.maharashtra.gov.in/public/project/view/1843 | W208: https://www.maharera.maharashtra.gov.in/projects-search-result?project_state=27&project_district=517&page=3 | X208: 2026-10-11 | Y208: Verified (official listing) | Z208: reg no, project name, promoter, district, taluka, pincode, last modified, detail URL | AA208: project address, registration date, original completion date, revised completion date | AB208: Cross-checked against 5 fully downloaded official lists (deregistered, 3 abeyance lists, NCLT) and the Revoked search (4/9 pages collected - revoked status may be under-reported)
A209: R000208 | B209: P51700001702 | C209: RAJ ESTATE | D209: D.V.BUILDERS & DEVELOPERS PVT. LTD. | E209: D00191 | G209: Thane | H209: 401107 | I209: Thane | J209: Mumbai MMR | K209: Thane district (incl. Thane, Navi Mumbai-Thane side, Mira-Bhayandar, Kalyan-Dombivli, Bhiwandi, Ulhasnagar, Ambernath) | L209: 19.271807 | M209: 72.888523 | Q209: Registered - no adverse list match | R209: No | S209: No | U209: 2017-07-29 | V209: https://maharerait.maharashtra.gov.in/public/project/view/5503 | W209: https://www.maharera.maharashtra.gov.in/projects-search-result?project_state=27&project_district=517&page=28 | X209: 2026-10-11 | Y209: Verified (official listing) | Z209: reg no, project name, promoter, district, taluka, pincode, last modified, detail URL | AA209: project address, registration date, original completion date, revised completion date | AB209: Cross-checked against 5 fully downloaded official lists (deregistered, 3 abeyance lists, NCLT) and the Revoked search (4/9 pages collected - revoked status may be under-reported)
A210: R000209 | B210: P51700001707 | C210: Manhattan Phase 1 | D210: SAI UMA CONSTRUCTION PRIVATE LIMITED | E210: D00863 | G210: Thane | H210: 400615 | I210: Thane | J210: Mumbai MMR | K210: Thane district (incl. Thane, Navi Mumbai-Thane side, Mira-Bhayandar, Kalyan-Dombivli, Bhiwandi, Ulhasnagar, Ambernath) | L210: 19.2555333 | M210: 72.97155040000007 | Q210: Registered - no adverse list match | R210: Yes | S210: No | U210: 2024-12-30 | V210: https://maharerait.maharashtra.gov.in/public/project/view/6621 | W210: https://www.maharera.maharashtra.gov.in/projects-search-result?project_state=27&project_district=517&page=39 | X210: 2026-10-11 | Y210: Verified (official listing) | Z210: reg no, project name, promoter, district, taluka, pincode, last modified, detail URL | AA210: project address, registration date, original completion date, revised completion date | AB210: Cross-checked against 5 fully downloaded official lists (deregistered, 3 abeyance lists, NCLT) and the Revoked search (4/9 pages collected - revoked status may be under-reported)
... A243: R000242 | B243: P51700002491 | C243: INDRAPRASTH WING C | D243: SONAM SPARK INFRA PRIVATE LIMITED | E243: D01012 | G243: Thane | H243: 401105 | I243: Thane | J243: Mumbai MMR | K243: Thane district (incl. Thane, Navi Mumbai-Thane side, Mira-Bhayandar, Kalyan-Dombivli, Bhiwandi, Ulhasnagar, Ambernath) | L243: 19.2183307 | M243: 72.97808970000006 | Q243: Registered - no adverse list match | R243: No | S243: No | U243: 2017-08-01 | V243: https://maharerait.maharashtra.gov.in/public/project/view/380 | W243: https://www.maharera.maharashtra.gov.in/projects-search-result?project_state=27&project_district=517&page=2 | X243: 2026-10-11 | Y243: Verified (official listing) | Z243: reg no, project name, promoter, district, taluka, pincode, last modified, detail URL | AA243: project address, registration date, original completion date, revised completion date | AB243: Cross-checked against 5 fully downloaded official lists (deregistered, 3 abeyance lists, NCLT) and the Revoked search (4/9 pages collected - revoked status may be under-reported)
A244: R000243 | B244: P51700002499 | C244: WADHWA RHODESIA | D244: WADHWA BUILDCON LLP | E244: D01168 | G244: Bhiwandi | H244: 421302 | I244: Thane | J244: Mumbai MMR | K244: Thane district (incl. Thane, Navi Mumbai-Thane side, Mira-Bhayandar, Kalyan-Dombivli, Bhiwandi, Ulhasnagar, Ambernath) | L244: 19.266028 | M244: 73.046793 | P244: 31-12-2026 | Q244: Registered - no adverse list match | R244: Yes | S244: No | T244: NCLT: Project status as on 31-01-2025: Active; Form 4 uploaded: N | U244: 2024-04-02 | V244: https://maharerait.maharashtra.gov.in/public/project/view/4536 | W244: https://www.maharera.maharashtra.gov.in/projects-search-result?project_state=27&project_district=517&page=16 | X244: 2026-10-11 | Y244: Verified (official listing) | Z244: reg no, project name, promoter, district, taluka, pincode, last modified, detail URL | AA244: project address, registration date, original completion date | AB244: Cross-checked against 5 fully downloaded official lists (deregistered, 3 abeyance lists, NCLT) and the Revoked search (4/9 pages collected - revoked status may be under-reported) | AC244: Revised/proposed completion date taken from official NCLT list
A245: R000244 | B245: P51700002512 | C245: ASHWA ANNEX | D245: ASHWAMEDH CONSTRUCTION | E245: D00101 | G245: Thane | H245: 400602 | I245: Thane | J245: Mumbai MMR | K245: Thane district (incl. Thane, Navi Mumbai-Thane side, Mira-Bhayandar, Kalyan-Dombivli, Bhiwandi, Ulhasnagar, Ambernath) | L245: 19.197416 | M245: 72.964746 | Q245: Registered - no adverse list match | R245: No | S245: No | U245: 2017-08-01 | V245: https://maharerait.maharashtra.gov.in/public/project/view/5092 | W245: https://www.maharera.maharashtra.gov.in/projects-search-result?project_state=27&project_district=517&page=22 | X245: 2026-10-11 | Y245: Verified (official listing) | Z245: reg no, project name, promoter, district, taluka, pincode, last modified, detail URL | AA245: project address, registration date, original completion date, revised completion date | AB245: Cross-checked against 5 fully downloaded official lists (deregistered, 3 abeyance lists, NCLT) and the Revoked search (4/9 pages collected - revoked status may be under-reported)
A246: R000245 | B246: P51700002522 | C246: NIRMAL | D246: Bhalchandra Wadnerkar | E246: D00130 | G246: Kalyan | H246: 421201 | I246: Thane | J246: Mumbai MMR | K246: Thane district (incl. Thane, Navi Mumbai-Thane side, Mira-Bhayandar, Kalyan-Dombivli, Bhiwandi, Ulhasnagar, Ambernath) | L246: 19.2127037 | M246: 73.0870836 | Q246: Registered - no adverse list match | R246: Yes | S246: No | U246: 2025-04-07 | V246: https://maharerait.maharashtra.gov.in/public/project/view/4173 | W246: https://www.maharera.maharashtra.gov.in/projects-search-result?project_state=27&project_district=517&page=13 | X246: 2026-10-11 | Y246: Verified (official listing) | Z246: reg no, project name, promoter, district, taluka, pincode, last modified, detail URL | AA246: project address, registration date, original completion date, revised completion date | AB246: Cross-checked against 5 fully downloaded official lists (deregistered, 3 abeyance lists, NCLT) and the Revoked search (4/9 pages collected - revoked status may be under-reported)
A247: R000246 | B247: P51700002550 | C247: Mohan Waters Edge I | D247: MOHAN LIFESPACES LLP | E247: D00591 | G247: Ambarnath | H247: 421503 | I247: Thane | J247: Mumbai MMR | K247: Thane district (incl. Thane, Navi Mumbai-Thane side, Mira-Bhayandar, Kalyan-Dombivli, Bhiwandi, Ulhasnagar, Ambernath) | L247: 19.18022 | M247: 73.247604 | Q247: Registered - no adverse list match | R247: No | S247: No | U247: 2017-08-01 | V247: https://maharerait.maharashtra.gov.in/public/project/view/6521 | W247: https://www.maharera.maharashtra.gov.in/projects-search-result?project_state=27&project_district=517&page=37 | X247: 2026-10-11 | Y247: Verified (official listing) | Z247: reg no, project name, promoter, district, taluka, pincode, last modified, detail URL | AA247: project address, registration date, original completion date, revised completion date | AB247: Cross-checked against 5 fully downloaded official lists (deregistered, 3 abeyance lists, NCLT) and the Revoked search (4/9 pages collected - revoked status may be under-reported)
A248: R000247 | B248: P51700002559 | C248: SHREE MANGALMURTI | D248: SHIVAM UNIVERSAL | E248: D00925 | G248: Kalyan | H248: 421202 | I248: Thane | J248: Mumbai MMR | K248: Thane district (incl. Thane, Navi Mumbai-Thane side, Mira-Bhayandar, Kalyan-Dombivli, Bhiwandi, Ulhasnagar, Ambernath) | L248: 19.224182 | M248: 73.101481 | Q248: Registered - no adverse list match | R248: No | S248: No | U248: 2017-08-01 | V248: https://maharerait.maharashtra.gov.in/public/project/view/5037 | W248: https://www.maharera.maharashtra.gov.in/projects-search-result?project_state=27&project_district=517&page=22 | X248: 2026-10-11 | Y248: Verified (official listing) | Z248: reg no, project name, promoter, district, taluka, pincode, last modified, detail URL | AA248: project address, registration date, original completion date, revised completion date | AB248: Cross-checked against 5 fully downloaded official lists (deregistered, 3 abeyance lists, NCLT) and the Revoked search (4/9 pages collected - revoked status may be under-reported)
A249: R000248 | B249: P51700002560 | C249: YOGI NIWAS | D249: ELITE INFRASTRUCTURE | E249: D00252 | G249: Ambarnath | H249: 421501 | I249: Thane | J249: Mumbai MMR | K249: Thane district (incl. Thane, Navi Mumbai-Thane side, Mira-Bhayandar, Kalyan-Dombivli, Bhiwandi, Ulhasnagar, Ambernath) | L249: 19.2007023 | M249: 73.1880618 | Q249: Registered - no adverse list match | R249: No | S249: No | U249: 2017-08-01 | V249: https://maharerait.maharashtra.gov.in/public/project/view/3576 | W249: https://www.maharera.maharashtra.gov.in/projects-search-result?project_state=27&project_district=517&page=9 | X249: 2026-10-11 | Y249: Verified (official listing) | Z249: reg no, project name, promoter, district, taluka, pincode, last modified, detail URL | AA249: project address, registration date, original completion date, revised completion date | AB249: Cross-checked against 5 fully downloaded official lists (deregistered, 3 abeyance lists, NCLT) and the Revoked search (4/9 pages collected - revoked status may be under-reported)
A250: R000249 | B250: P51700002572 | C250: SHANTI SEVEN | D250: SHANTISTAR BUILDERS | E250: D00910 | G250: Thane | H250: 401107 | I250: Thane | J250: Mumbai MMR | K250: Thane district (incl. Thane, Navi Mumbai-Thane side, Mira-Bhayandar, Kalyan-Dombivli, Bhiwandi, Ulhasnagar, Ambernath) | L250: 19.277124 | M250: 72.862948 | Q250: Registered - no adverse list match | R250: No | S250: No | U250: 2017-08-01 | V250: https://maharerait.maharashtra.gov.in/public/project/view/3178 | W250: https://www.maharera.maharashtra.gov.in/projects-search-result?project_state=27&project_district=517&page=7 | X250: 2026-10-11 | Y250: Verified (official listing) | Z250: reg no, project name, promoter, district, taluka, pincode, last modified, detail URL | AA250: project address, registration date, original completion date, revised completion date | AB250: Cross-checked against 5 fully downloaded official lists (deregistered, 3 abeyance lists, NCLT) and the Revoked search (4/9 pages collected - revoked status may be under-reported)
A251: R000250 | B251: P51700002579 | C251: MANGALMURTI GALAXY | D251: SHREE MANGALMURTI ENTERPRISES | E251: D00947 | G251: Kalyan | H251: 421201 | I251: Thane | J251: Mumbai MMR | K251: Thane district (incl. Thane, Navi Mumbai-Thane side, Mira-Bhayandar, Kalyan-Dombivli, Bhiwandi, Ulhasnagar, Ambernath) | L251: 19.227528839700476 | M251: 73.10951291250308 | Q251: Registered - no adverse list match | R251: Yes | S251: No | U251: 2021-09-09 | V251: https://maharerait.maharashtra.gov.in/public/project/view/4910 | W251: https://www.maharera.maharashtra.gov.in/projects-search-result?project_state=27&project_district=517&page=21 | X251: 2026-10-11 | Y251: Verified (official listing) | Z251: reg no, project name, promoter, district, taluka, pincode, last modified, detail URL | AA251: project address, registration date, original completion date, revised completion date | AB251: Cross-checked against 5 fully downloaded official lists (deregistered, 3 abeyance lists, NCLT) and the Revoked search (4/9 pages collected - revoked status may be under-reported)
A252: R000251 | B252: P51700002581 | C252: ANMOL SAPPHIRE | D252: M/s Ekdant Housing | E252: D00511 | G252: Thane | H252: 400602 | I252: Thane | J252: Mumbai MMR | K252: Thane district (incl. Thane, Navi Mumbai-Thane side, Mira-Bhayandar, Kalyan-Dombivli, Bhiwandi, Ulhasnagar, Ambernath) | L252: 19.1900019 | M252: 72.9682017 | Q252: Registered - no adverse list match | R252: No | S252: No | U252: 2017-08-02 | V252: https://maharerait.maharashtra.gov.in/public/project/view/4896 | W252: https://www.maharera.maharashtra.gov.in/projects-search-result?project_state=27&project_district=517&page=20 | X252: 2026-10-11 | Y252: Verified (official listing) | Z252: reg no, project name, promoter, district, taluka, pincode, last modified, detail URL | AA252: project address, registration date, original completion date, revised completion date | AB252: Cross-checked against 5 fully downloaded official lists (deregistered, 3 abeyance lists, NCLT) and the Revoked search (4/9 pages collected - revoked status may be under-reported)
A253: R000252 | B253: P51700002586 | C253: JOSHI DATTA NAGAR | D253: Bhalchandra Wadnerkar | E253: D00130 | G253: Kalyan | H253: 421201 | I253: Thane | J253: Mumbai MMR | K253: Thane district (incl. Thane, Navi Mumbai-Thane side, Mira-Bhayandar, Kalyan-Dombivli, Bhiwandi, Ulhasnagar, Ambernath) | L253: 19.212271361109416 | M253: 73.08688580989838 | Q253: Registered - no adverse list match | R253: Yes | S253: No | U253: 2024-12-30 | V253: https://maharerait.maharashtra.gov.in/public/project/view/4129 | W253: https://www.maharera.maharashtra.gov.in/projects-search-result?project_state=27&project_district=517&page=13 | X253: 2026-10-11 | Y253: Verified (official listing) | Z253: reg no, project name, promoter, district, taluka, pincode, last modified, detail URL | AA253: project address, registration date, original completion date, revised completion date | AB253: Cross-checked against 5 fully downloaded official lists (deregistered, 3 abeyance lists, NCLT) and the Revoked search (4/9 pages collected - revoked status may be under-reported)
A254: R000253 | B254: P51700002614 | C254: MADHUBAN F1 F2 | D254: Abhilasha Venture | E254: D00022 | G254: Kalyan | H254: 421605 | I254: Thane | J254: Mumbai MMR | K254: Thane district (incl. Thane, Navi Mumbai-Thane side, Mira-Bhayandar, Kalyan-Dombivli, Bhiwandi, Ulhasnagar, Ambernath) | L254: 19.289110375739547 | M254: 73.20227945830084 | Q254: Registered - no adverse list match | R254: Yes | S254: No | U254: 2020-06-13 | V254: https://maharerait.maharashtra.gov.in/public/project/view/5086 | W254: https://www.maharera.maharashtra.gov.in/projects-search-result?project_state=27&project_district=517&page=22 | X254: 2026-10-11 | Y254: Verified (official listing) | Z254: reg no, project name, promoter, district, taluka, pincode, last modified, detail URL | AA254: project address, registration date, original completion date, revised completion date | AB254: Cross-checked against 5 fully downloaded official lists (deregistered, 3 abeyance lists, NCLT) and the Revoked search (4/9 pages collected - revoked status may be under-reported)
A255: R000254 | B255: P51700002627 | C255: DEEPMALA CHS LTD | D255: S. D. Bhalerao Associates | E255: D00830 | G255: Thane | H255: 400606 | I255: Thane | J255: Mumbai MMR | K255: Thane district (incl. Thane, Navi Mumbai-Thane side, Mira-Bhayandar, Kalyan-Dombivli, Bhiwandi, Ulhasnagar, Ambernath) | L255: 19.212465464610748 | M255: 72.9622975043518 | Q255: Registered - no adverse list match | R255: Yes | S255: No | U255: 2026-08-14 | V255: https://maharerait.maharashtra.gov.in/public/project/view/4995 | W255: https://www.maharera.maharashtra.gov.in/projects-search-result?project_state=27&project_district=517&page=21 | X255: 2026-10-11 | Y255: Verified (official listing) | Z255: reg no, project name, promoter, district, taluka, pincode, last modified, detail URL | AA255: project address, registration date, original completion date, revised completion date | AB255: Cross-checked against 5 fully downloaded official lists (deregistered, 3 abeyance lists, NCLT) and the Revoked search (4/9 pages collected - revoked status may be under-reported)
A256: R000255 | B256: P51700002657 | C256: PRIDE PALMS QUEENS A2 PHASE 2 | D256: LARKINS REALTORS | E256: D00480 | G256: Thane | H256: 400607 | I256: Thane | J256: Mumbai MMR | K256: Thane district (incl. Thane, Navi Mumbai-Thane side, Mira-Bhayandar, Kalyan-Dombivli, Bhiwandi, Ulhasnagar, Ambernath) | L256: 19.232564959444087 | M256: 72.98556936924206 | Q256: Registered - no adverse list match | R256: No | S256: No | U256: 2019-02-02 | V256: https://maharerait.maharashtra.gov.in/public/project/view/7147 | W256: https://www.maharera.maharashtra.gov.in/projects-search-result?project_state=27&project_district=517&page=44 | X256: 2026-10-11 | Y256: Verified (official listing) | Z256: reg no, project name, promoter, district, taluka, pincode, last modified, detail URL | AA256: project address, registration date, original completion date, revised completion date | AB256: Cross-checked against 5 fully downloaded official lists (deregistered, 3 abeyance lists, NCLT) and the Revoked search (4/9 pages collected - revoked status may be under-reported)
... A460: R000459 | B460: P51700015836 | C460: Capsule Business Hub | D460: Maa Vaishnavi Builders & Developers | E460: D00536 | G460: Kalyan | H460: 421301 | I460: Thane | J460: Mumbai MMR | K460: Thane district (incl. Thane, Navi Mumbai-Thane side, Mira-Bhayandar, Kalyan-Dombivli, Bhiwandi, Ulhasnagar, Ambernath) | L460: 19.2498805 | M460: 73.14134 | Q460: Registered - no adverse list match | R460: Yes | S460: No | U460: 2025-06-02 | V460: https://maharerait.maharashtra.gov.in/public/project/view/3638 | W460: https://www.maharera.maharashtra.gov.in/projects-search-result?project_state=27&project_district=517&page=9 | X460: 2026-10-11 | Y460: Verified (official listing) | Z460: reg no, project name, promoter, district, taluka, pincode, last modified, detail URL | AA460: project address, registration date, original completion date, revised completion date | AB460: Cross-checked against 5 fully downloaded official lists (deregistered, 3 abeyance lists, NCLT) and the Revoked search (4/9 pages collected - revoked status may be under-reported)
A461: R000460 | B461: P51800000861 | C461: Kamlakarendu | D461: Ashta Siddhi Constructions Private Limited | E461: D00099 | G461: Thane | H461: 400603 | I461: Thane | J461: Mumbai MMR | K461: Thane district (incl. Thane, Navi Mumbai-Thane side, Mira-Bhayandar, Kalyan-Dombivli, Bhiwandi, Ulhasnagar, Ambernath) | L461: 19.184834434901205 | M461: 72.97795022513128 | Q461: Registered - no adverse list match | R461: Yes | S461: No | U461: 2020-06-17 | V461: https://maharerait.maharashtra.gov.in/public/project/view/5847 | W461: https://www.maharera.maharashtra.gov.in/projects-search-result?project_state=27&project_district=517&page=31 | X461: 2026-10-11 | Y461: Verified (official listing) | Z461: reg no, project name, promoter, district, taluka, pincode, last modified, detail URL | AA461: project address, registration date, original completion date, revised completion date | AB461: Cross-checked against 5 fully downloaded official lists (deregistered, 3 abeyance lists, NCLT) and the Revoked search (4/9 pages collected - revoked status may be under-reported) | AC461: Registration-number prefix belongs to a different district
A462: R000461 | B462: P51800000876 | C462: Annapurna Avenue | D462: ANNAPURNA BUILDCON INFRA PRIVATE LIMITED | E462: D00075 | G462: Thane | H462: 401105 | I462: Thane | J462: Mumbai MMR | K462: Thane district (incl. Thane, Navi Mumbai-Thane side, Mira-Bhayandar, Kalyan-Dombivli, Bhiwandi, Ulhasnagar, Ambernath) | L462: 19.301819 | M462: 72.87452 | Q462: Registered - no adverse list match | R462: Yes | S462: No | U462: 2022-01-11 | V462: https://maharerait.maharashtra.gov.in/public/project/view/6436 | W462: https://www.maharera.maharashtra.gov.in/projects-search-result?project_state=27&project_district=517&page=36 | X462: 2026-10-11 | Y462: Verified (official listing) | Z462: reg no, project name, promoter, district, taluka, pincode, last modified, detail URL | AA462: project address, registration date, original completion date, revised completion date | AB462: Cross-checked against 5 fully downloaded official lists (deregistered, 3 abeyance lists, NCLT) and the Revoked search (4/9 pages collected - revoked status may be under-reported) | AC462: Registration-number prefix belongs to a different district
A463: R000462 | B463: P51800001460 | C463: DYNAMIC CREST PHASE I - RIMO/EVEREST | D463: SNEH MAKEWELL LLP | E463: D01006 | G463: Thane | H463: 421204 | I463: Thane | J463: Mumbai MMR | K463: Thane district (incl. Thane, Navi Mumbai-Thane side, Mira-Bhayandar, Kalyan-Dombivli, Bhiwandi, Ulhasnagar, Ambernath) | L463: 19.15668 | M463: 73.065775 | Q463: Registered - no adverse list match | R463: Yes | S463: No | U463: 2021-09-09 | V463: https://maharerait.maharashtra.gov.in/public/project/view/4301 | W463: https://www.maharera.maharashtra.gov.in/projects-search-result?project_state=27&project_district=517&page=14 | X463: 2026-10-11 | Y463: Verified (official listing) | Z463: reg no, project name, promoter, district, taluka, pincode, last modified, detail URL | AA463: project address, registration date, original completion date, revised completion date | AB463: Cross-checked against 5 fully downloaded official lists (deregistered, 3 abeyance lists, NCLT) and the Revoked search (4/9 pages collected - revoked status may be under-reported) | AC463: Registration-number prefix belongs to a different district
A464: R000463 | B464: P51800001920 | C464: Heena Presidency | D464: Neha Developers | E464: D00643 | G464: Thane | H464: 401107 | I464: Thane | J464: Mumbai MMR | K464: Thane district (incl. Thane, Navi Mumbai-Thane side, Mira-Bhayandar, Kalyan-Dombivli, Bhiwandi, Ulhasnagar, Ambernath) | L464: 19.272591 | M464: 72.87839269999999 | Q464: Registered - no adverse list match | R464: Yes | S464: No | U464: 2026-08-14 | V464: https://maharerait.maharashtra.gov.in/public/project/view/6459 | W464: https://www.maharera.maharashtra.gov.in/projects-search-result?project_state=27&project_district=517&page=36 | X464: 2026-10-11 | Y464: Verified (official listing) | Z464: reg no, project name, promoter, district, taluka, pincode, last modified, detail URL | AA464: project address, registration date, original completion date, revised completion date | AB464: Cross-checked against 5 fully downloaded official lists (deregistered, 3 abeyance lists, NCLT) and the Revoked search (4/9 pages collected - revoked status may be under-reported) | AC464: Registration-number prefix belongs to a different district
A465: R000464 | B465: P51800002185 | C465: Annapurna Aquarius | D465: Annapurna Properties | E465: D00077 | G465: Thane | H465: 401101 | I465: Thane | J465: Mumbai MMR | K465: Thane district (incl. Thane, Navi Mumbai-Thane side, Mira-Bhayandar, Kalyan-Dombivli, Bhiwandi, Ulhasnagar, Ambernath) | L465: 19.291663 | M465: 72.852372 | Q465: Registered - no adverse list match | R465: No | S465: No | U465: 2021-08-16 | V465: https://maharerait.maharashtra.gov.in/public/project/view/6997 | W465: https://www.maharera.maharashtra.gov.in/projects-search-result?project_state=27&project_district=517&page=43 | X465: 2026-10-11 | Y465: Verified (official listing) | Z465: reg no, project name, promoter, district, taluka, pincode, last modified, detail URL | AA465: project address, registration date, original completion date, revised completion date | AB465: Cross-checked against 5 fully downloaded official lists (deregistered, 3 abeyance lists, NCLT) and the Revoked search (4/9 pages collected - revoked status may be under-reported) | AC465: Registration-number prefix belongs to a different district
A466: R000465 | B466: P51800003594 | C466: Bhavani Heights | D466: Kalyani Enterprises | E466: D00417 | G466: Ambarnath | H466: 421503 | I466: Thane | J466: Mumbai MMR | K466: Thane district (incl. Thane, Navi Mumbai-Thane side, Mira-Bhayandar, Kalyan-Dombivli, Bhiwandi, Ulhasnagar, Ambernath) | L466: 19.1667854 | M466: 73.2367896 | Q466: Registered - no adverse list match | R466: No | S466: No | U466: 2017-10-10 | V466: https://maharerait.maharashtra.gov.in/public/project/view/894 | W466: https://www.maharera.maharashtra.gov.in/projects-search-result?project_state=27&project_district=517&page=2 | X466: 2026-10-11 | Y466: Verified (official listing) | Z466: reg no, project name, promoter, district, taluka, pincode, last modified, detail URL | AA466: project address, registration date, original completion date, revised completion date | AB466: Cross-checked against 5 fully downloaded official lists (deregistered, 3 abeyance lists, NCLT) and the Revoked search (4/9 pages collected - revoked status may be under-reported) | AC466: Registration-number prefix belongs to a different district
A467: R000466 | B467: P51800007505 | C467: PINE WOOD | D467: RDC VENTURES | E467: D00791 | G467: Thane | H467: 400615 | I467: Thane | J467: Mumbai MMR | K467: Thane district (incl. Thane, Navi Mumbai-Thane side, Mira-Bhayandar, Kalyan-Dombivli, Bhiwandi, Ulhasnagar, Ambernath) | L467: 19.271548 | M467: 72.9637728 | Q467: Registered - no adverse list match | R467: Yes | S467: No | U467: 2018-01-15 | V467: https://maharerait.maharashtra.gov.in/public/project/view/1415 | W467: https://www.maharera.maharashtra.gov.in/projects-search-result?project_state=27&project_district=517&page=3 | X467: 2026-10-11 | Y467: Verified (official listing) | Z467: reg no, project name, promoter, district, taluka, pincode, last modified, detail URL | AA467: project address, registration date, original completion date, revised completion date | AB467: Cross-checked against 5 fully downloaded official lists (deregistered, 3 abeyance lists, NCLT) and the Revoked search (4/9 pages collected - revoked status may be under-reported) | AC467: Registration-number prefix belongs to a different district
A468: R000467 | B468: P51800011407 | C468: GAURAV WOODS II | D468: Ravi Developments | E468: D00789 | G468: Thane | H468: 401107 | I468: Thane | J468: Mumbai MMR | K468: Thane district (incl. Thane, Navi Mumbai-Thane side, Mira-Bhayandar, Kalyan-Dombivli, Bhiwandi, Ulhasnagar, Ambernath) | L468: 19.290835 | M468: 72.879053 | Q468: Abeyance - QPR non-compliance | R468: Yes | S468: Yes | T468: Abeyance - QPR non-compliance: QPR period August 2017 | U468: 2026-08-20 | V468: https://maharerait.maharashtra.gov.in/public/project/view/7302 | W468: https://www.maharera.maharashtra.gov.in/projects-search-result?project_state=27&project_district=517&page=47 | X468: 2026-10-11 | Y468: Verified (official listing) | Z468: reg no, project name, promoter, district, taluka, pincode, last modified, detail URL | AA468: project address, registration date, original completion date, revised completion date | AB468: Cross-checked against 5 fully downloaded official lists (deregistered, 3 abeyance lists, NCLT) and the Revoked search (4/9 pages collected - revoked status may be under-reported) | AC468: Registration-number prefix belongs to a different district
A469: R000468 | B469: P51900009084 | C469: OM SRUSHTI DARSHAN | D469: VINAYAK DEVELOPERS | E469: D01146 | G469: Thane | H469: 400601 | I469: Thane | J469: Mumbai MMR | K469: Thane district (incl. Thane, Navi Mumbai-Thane side, Mira-Bhayandar, Kalyan-Dombivli, Bhiwandi, Ulhasnagar, Ambernath) | L469: 19.2010502 | M469: 72.9785353 | Q469: Registered - no adverse list match | R469: No | S469: No | U469: 2017-10-09 | V469: https://maharerait.maharashtra.gov.in/public/project/view/6560 | W469: https://www.maharera.maharashtra.gov.in/projects-search-result?project_state=27&project_district=517&page=38 | X469: 2026-10-11 | Y469: Verified (official listing) | Z469: reg no, project name, promoter, district, taluka, pincode, last modified, detail URL | AA469: project address, registration date, original completion date, revised completion date | AB469: Cross-checked against 5 fully downloaded official lists (deregistered, 3 abeyance lists, NCLT) and the Revoked search (4/9 pages collected - revoked status may be under-reported) | AC469: Registration-number prefix belongs to a different district
A470: R000469 | B470: P51900010004 | C470: KIPL Morya | D470: khade Infrastructre Pvt. Ltd. | E470: D00441 | G470: Thane | H470: 400615 | I470: Thane | J470: Mumbai MMR | K470: Thane district (incl. Thane, Navi Mumbai-Thane side, Mira-Bhayandar, Kalyan-Dombivli, Bhiwandi, Ulhasnagar, Ambernath) | L470: 19.271548 | M470: 72.9637728 | Q470: Registered - no adverse list match | R470: Yes | S470: No | U470: 2021-09-09 | V470: https://maharerait.maharashtra.gov.in/public/project/view/2416 | W470: https://www.maharera.maharashtra.gov.in/projects-search-result?project_state=27&project_district=517&page=4 | X470: 2026-10-11 | Y470: Verified (official listing) | Z470: reg no, project name, promoter, district, taluka, pincode, last modified, detail URL | AA470: project address, registration date, original completion date, revised completion date | AB470: Cross-checked against 5 fully downloaded official lists (deregistered, 3 abeyance lists, NCLT) and the Revoked search (4/9 pages collected - revoked status may be under-reported) | AC470: Registration-number prefix belongs to a different district
A471: R000470 | B471: P52000001364 | C471: SILVER ICON | D471: SILVER GLADES PROJECTS PRIVATE LIMITED | E471: D00996 | G471: Thane | H471: 400701 | I471: Thane | J471: Mumbai MMR | K471: Thane district (incl. Thane, Navi Mumbai-Thane side, Mira-Bhayandar, Kalyan-Dombivli, Bhiwandi, Ulhasnagar, Ambernath) | L471: 19.135805 | M471: 72.997578 | Q471: Registered - no adverse list match | R471: No | S471: No | U471: 2018-02-21 | V471: https://maharerait.maharashtra.gov.in/public/project/view/6679 | W471: https://www.maharera.maharashtra.gov.in/projects-search-result?project_state=27&project_district=517&page=40 | X471: 2026-10-11 | Y471: Verified (official listing) | Z471: reg no, project name, promoter, district, taluka, pincode, last modified, detail URL | AA471: project address, registration date, original completion date, revised completion date | AB471: Cross-checked against 5 fully downloaded official lists (deregistered, 3 abeyance lists, NCLT) and the Revoked search (4/9 pages collected - revoked status may be under-reported) | AC471: Registration-number prefix belongs to a different district
A472: R000471 | B472: P51700000636 | C472: Swiss Boulevard | D472: Chaurang Associates | E472: D00161 | G472: Kurla | H472: 400071 | I472: Mumbai Suburban | J472: Mumbai MMR | K472: Mumbai Suburban | L472: 19.0609099 | M472: 72.89390359999993 | Q472: Registered - no adverse list match | R472: No | S472: No | U472: 2020-09-30 | V472: https://maharerait.maharashtra.gov.in/public/project/view/3701 | W472: https://www.maharera.maharashtra.gov.in/projects-search-result?project_state=27&project_district=518&page=16 | X472: 2026-10-11 | Y472: Verified (official listing) | Z472: reg no, project name, promoter, district, taluka, pincode, last modified, detail URL | AA472: project address, registration date, original completion date, revised completion date | AB472: Cross-checked against 5 fully downloaded official lists (deregistered, 3 abeyance lists, NCLT) and the Revoked search (4/9 pages collected - revoked status may be under-reported) | AC472: Registration-number prefix belongs to a different district
A473: R000472 | B473: P51800000004 | C473: KRISHNA ENCLAVE | D473: ASHA DEVELOPERS | E473: D00092 | G473: Andheri | H473: 400055 | I473: Mumbai Suburban | J473: Mumbai MMR | K473: Mumbai Suburban | L473: 19.0803885 | M473: 72.8468571 | Q473: Registered - no adverse list match | R473: No | S473: No | U473: 2017-05-19 | V473: https://maharerait.maharashtra.gov.in/public/project/view/349 | W473: https://www.maharera.maharashtra.gov.in/projects-search-result?project_state=27&project_district=518&page=1 | X473: 2026-10-11 | Y473: Verified (official listing) | Z473: reg no, project name, promoter, district, taluka, pincode, last modified, detail URL | AA473: project address, registration date, original completion date, revised completion date | AB473: Cross-checked against 5 fully downloaded official lists (deregistered, 3 abeyance lists, NCLT) and the Revoked search (4/9 pages collected - revoked status may be under-reported)
A474: R000473 | B474: P51800000010 | C474: SAANVI HEIGHTS | D474: ADINATH ENTERPRISE | E474: D00032 | G474: Borivali | H474: 400104 | I474: Mumbai Suburban | J474: Mumbai MMR | K474: Mumbai Suburban | L474: 19.1630445 | M474: 72.8392995 | Q474: Registered - no adverse list match | R474: No | S474: No | U474: 2017-05-23 | V474: https://maharerait.maharashtra.gov.in/public/project/view/859 | W474: https://www.maharera.maharashtra.gov.in/projects-search-result?project_state=27&project_district=518&page=2 | X474: 2026-10-11 | Y474: Verified (official listing) | Z474: reg no, project name, promoter, district, taluka, pincode, last modified, detail URL | AA474: project address, registration date, original completion date, revised completion date | AB474: Cross-checked against 5 fully downloaded official lists (deregistered, 3 abeyance lists, NCLT) and the Revoked search (4/9 pages collected - revoked status may be under-reported)
A475: R000474 | B475: P51800000014 | C475: Jeevan Kanchan Co-Operative Housing Society Ltd. | D475: Shri Krishna Chaitanya Enterprises | E475: D00980 | G475: Andheri | H475: 400058 | I475: Mumbai Suburban | J475: Mumbai MMR | K475: Mumbai Suburban | L475: 19.1227346 | M475: 72.8302013 | Q475: Registered - no adverse list match | R475: No | S475: No | U475: 2017-05-31 | V475: https://maharerait.maharashtra.gov.in/public/project/view/820 | W475: https://www.maharera.maharashtra.gov.in/projects-search-result?project_state=27&project_district=518&page=2 | X475: 2026-10-11 | Y475: Verified (official listing) | Z475: reg no, project name, promoter, district, taluka, pincode, last modified, detail URL | AA475: project address, registration date, original completion date, revised completion date | AB475: Cross-checked against 5 fully downloaded official lists (deregistered, 3 abeyance lists, NCLT) and the Revoked search (4/9 pages collected - revoked status may be under-reported)
A476: R000475 | B476: P51800000016 | C476: Veena Serenity | D476: VEENA REALCON PRIVATE LIMITED | E476: D01122 | G476: Kurla | H476: 400071 | I476: Mumbai Suburban | J476: Mumbai MMR | K476: Mumbai Suburban | L476: 19.0626988 | M476: 72.8925313 | Q476: Registered - no adverse list match | R476: No | S476: No | U476: 2017-06-05 | V476: https://maharerait.maharashtra.gov.in/public/project/view/1408 | W476: https://www.maharera.maharashtra.gov.in/projects-search-result?project_state=27&project_district=518&page=3 | X476: 2026-10-11 | Y476: Verified (official listing) | Z476: reg no, project name, promoter, district, taluka, pincode, last modified, detail URL | AA476: project address, registration date, original completion date, revised completion date | AB476: Cross-checked against 5 fully downloaded official lists (deregistered, 3 abeyance lists, NCLT) and the Revoked search (4/9 pages collected - revoked status may be under-reported)
A477: R000476 | B477: P51800000017 | C477: PLOT NO 3 CHARKOP SECTOR 8 | D477: MAHARASHTRA HOUSING AND AREA DEVELOPMENT AUTHORITY | E477: D00542 | G477: Borivali | H477: 400067 | I477: Mumbai Suburban | J477: Mumbai MMR | K477: Mumbai Suburban | L477: 19.2072366 | M477: 72.8348221 | Q477: Registered - no adverse list match | R477: Yes | S477: No | U477: 2020-06-17 | V477: https://maharerait.maharashtra.gov.in/public/project/view/1002 | W477: https://www.maharera.maharashtra.gov.in/projects-search-result?project_state=27&project_district=518&page=3 | X477: 2026-10-11 | Y477: Verified (official listing) | Z477: reg no, project name, promoter, district, taluka, pincode, last modified, detail URL | AA477: project address, registration date, original completion date, revised completion date | AB477: Cross-checked against 5 fully downloaded official lists (deregistered, 3 abeyance lists, NCLT) and the Revoked search (4/9 pages collected - revoked status may be under-reported)
A478: R000477 | B478: P51800000019 | C478: PLOT NO.2 | D478: MAHARASHTRA HOUSING AND AREA DEVELOPMENT AUTHORITY | E478: D00542 | G478: Borivali | H478: 400067 | I478: Mumbai Suburban | J478: Mumbai MMR | K478: Mumbai Suburban | L478: 19.2072366 | M478: 72.8348221 | Q478: Registered - no adverse list match | R478: No | S478: No | U478: 2017-12-28 | V478: https://maharerait.maharashtra.gov.in/public/project/view/1638 | W478: https://www.maharera.maharashtra.gov.in/projects-search-result?project_state=27&project_district=518&page=5 | X478: 2026-10-11 | Y478: Verified (official listing) | Z478: reg no, project name, promoter, district, taluka, pincode, last modified, detail URL | AA478: project address, registration date, original completion date, revised completion date | AB478: Cross-checked against 5 fully downloaded official lists (deregistered, 3 abeyance lists, NCLT) and the Revoked search (4/9 pages collected - revoked status may be under-reported)
A479: R000478 | B479: P51800000023 | C479: Construction of 83 LIG Ts on Guest plot CTS no 43 Pt of Unnatagar, Village Pahadi goregaon | D479: MUMBAI HOUSING AND AREA DEVELOPMENT BOARD | E479: D00608 | G479: Andheri | H479: 400062 | I479: Mumbai Suburban | J479: Mumbai MMR | K479: Mumbai Suburban | L479: 19.1593396 | M479: 72.8426858 | Q479: Registered - no adverse list match | R479: Yes | S479: No | U479: 2020-06-17 | V479: https://maharerait.maharashtra.gov.in/public/project/view/1531 | W479: https://www.maharera.maharashtra.gov.in/projects-search-result?project_state=27&project_district=518&page=4 | X479: 2026-10-11 | Y479: Verified (official listing) | Z479: reg no, project name, promoter, district, taluka, pincode, last modified, detail URL | AA479: project address, registration date, original completion date, revised completion date | AB479: Cross-checked against 5 fully downloaded official lists (deregistered, 3 abeyance lists, NCLT) and the Revoked search (4/9 pages collected - revoked status may be under-reported)
A480: R000479 | B480: P51800000024 | C480: Construction of 406 TR TS 442 EWS 258 MIG TS at Gavanpada Mulund east Mumbai | D480: MHADA | E480: D00577 | G480: Kurla | H480: 400081 | I480: Mumbai Suburban | J480: Mumbai MMR | K480: Mumbai Suburban | L480: 19.1660696 | M480: 72.96456280000007 | Q480: Registered - no adverse list match | R480: Yes | S480: No | U480: 2019-03-15 | V480: https://maharerait.maharashtra.gov.in/public/project/view/1917 | W480: https://www.maharera.maharashtra.gov.in/projects-search-result?project_state=27&project_district=518&page=6 | X480: 2026-10-11 | Y480: Verified (official listing) | Z480: reg no, project name, promoter, district, taluka, pincode, last modified, detail URL | AA480: project address, registration date, original completion date, revised completion date | AB480: Cross-checked against 5 fully downloaded official lists (deregistered, 3 abeyance lists, NCLT) and the Revoked search (4/9 pages collected - revoked status may be under-reported)
A481: R000480 | B481: P51800000026 | C481: Construction of 69 shops at sno 263 CTS no 6A/6 Ekta nagar Malwani Malad west Mumbai95 | D481: MUMBAI HOUSING AND AREA DEVELOPMENT BOARD | E481: D00608 | G481: Borivali | H481: 400095 | I481: Mumbai Suburban | J481: Mumbai MMR | K481: Mumbai Suburban | L481: 19.1888023 | M481: 72.8197043 | Q481: Registered - no adverse list match | R481: Yes | S481: No | U481: 2020-06-16 | V481: https://maharerait.maharashtra.gov.in/public/project/view/1658 | W481: https://www.maharera.maharashtra.gov.in/projects-search-result?project_state=27&project_district=518&page=5 | X481: 2026-10-11 | Y481: Verified (official listing) | Z481: reg no, project name, promoter, district, taluka, pincode, last modified, detail URL | AA481: project address, registration date, original completion date, revised completion date | AB481: Cross-checked against 5 fully downloaded official lists (deregistered, 3 abeyance lists, NCLT) and the Revoked search (4/9 pages collected - revoked status may be under-reported)
A482: R000481 | B482: P51800000030 | C482: Redevelopment of Transit Building No 32 and 33 Sidharth Nagar Goregaon West | D482: MUMBAI HOUSING AND AREA DEVELOPMENT BOARD | E482: D00608 | G482: Andheri | H482: 400062 | I482: Mumbai Suburban | J482: Mumbai MMR | K482: Mumbai Suburban | L482: 19.1593396 | M482: 72.8426858 | Q482: Registered - no adverse list match | R482: No | S482: No | U482: 2017-06-13 | V482: https://maharerait.maharashtra.gov.in/public/project/view/1590 | W482: https://www.maharera.maharashtra.gov.in/projects-search-result?project_state=27&project_district=518&page=4 | X482: 2026-10-11 | Y482: Verified (official listing) | Z482: reg no, project name, promoter, district, taluka, pincode, last modified, detail URL | AA482: project address, registration date, original completion date, revised completion date | AB482: Cross-checked against 5 fully downloaded official lists (deregistered, 3 abeyance lists, NCLT) and the Revoked search (4/9 pages collected - revoked status may be under-reported)
A483: R000482 | B483: P51800000031 | C483: Construcion of 28 LIG tenement on Plot OB 8,Siddharth nagar ,Goregaon west,Mumbai | D483: MUMBAI HOUSING AND AREA DEVELOPMENT BOARD | E483: D00608 | G483: Borivali | H483: 400062 | I483: Mumbai Suburban | J483: Mumbai MMR | K483: Mumbai Suburban | L483: 19.1593396 | M483: 72.8426858 | Q483: Registered - no adverse list match | R483: No | S483: No | U483: 2017-06-13 | V483: https://maharerait.maharashtra.gov.in/public/project/view/1541 | W483: https://www.maharera.maharashtra.gov.in/projects-search-result?project_state=27&project_district=518&page=4 | X483: 2026-10-11 | Y483: Verified (official listing) | Z483: reg no, project name, promoter, district, taluka, pincode, last modified, detail URL | AA483: project address, registration date, original completion date, revised completion date | AB483: Cross-checked against 5 fully downloaded official lists (deregistered, 3 abeyance lists, NCLT) and the Revoked search (4/9 pages collected - revoked status may be under-reported)
A484: R000483 | B484: P51800000033 | C484: Construction of 232 LIG TS on S.No. 263 p C.T.S No. 3525p Nr Bus depo Malwani Malad west Mumbai 95 | D484: MUMBAI HOUSING AND AREA DEVELOPMENT BOARD | E484: D00608 | G484: Borivali | H484: 400095 | I484: Mumbai Suburban | J484: Mumbai MMR | K484: Mumbai Suburban | L484: 19.1888023 | M484: 72.8197043 | Q484: Registered - no adverse list match | R484: No | S484: No | U484: 2017-06-15 | V484: https://maharerait.maharashtra.gov.in/public/project/view/1609 | W484: https://www.maharera.maharashtra.gov.in/projects-search-result?project_state=27&project_district=518&page=5 | X484: 2026-10-11 | Y484: Verified (official listing) | Z484: reg no, project name, promoter, district, taluka, pincode, last modified, detail URL | AA484: project address, registration date, original completion date, revised completion date | AB484: Cross-checked against 5 fully downloaded official lists (deregistered, 3 abeyance lists, NCLT) and the Revoked search (4/9 pages collected - revoked status may be under-reported)
... A526: R000525 | B526: P51800000294 | C526: LODHA ETERNIS SERENA A | D526: MACROTECH DEVELOPERS LIMITED | E526: D00539 | G526: Andheri | H526: 400093 | I526: Mumbai Suburban | J526: Mumbai MMR | K526: Mumbai Suburban | L526: 19.122128 | M526: 72.867693 | Q526: Registered - no adverse list match | R526: No | S526: No | U526: 2019-01-09 | V526: https://maharerait.maharashtra.gov.in/public/project/view/3342 | W526: https://www.maharera.maharashtra.gov.in/projects-search-result?project_state=27&project_district=518&page=13 | X526: 2026-10-11 | Y526: Verified (official listing) | Z526: reg no, project name, promoter, district, taluka, pincode, last modified, detail URL | AA526: project address, registration date, original completion date, revised completion date | AB526: Cross-checked against 5 fully downloaded official lists (deregistered, 3 abeyance lists, NCLT) and the Revoked search (4/9 pages collected - revoked status may be under-reported)
A527: R000526 | B527: P51800000340 | C527: LIVSMART KURLA | D527: D. K. REALTY (INDIA) PVT. LTD. | E527: D00185 | G527: Kurla | H527: 400070 | I527: Mumbai Suburban | J527: Mumbai MMR | K527: Mumbai Suburban | L527: 19.0822065 | M527: 72.9002988 | P527: 30-12-2021 | Q527: Registered - no adverse list match | R527: Yes | S527: No | T527: NCLT: Project status as on 31-01-2025: Lapsed; Form 4 uploaded: N | U527: 2026-08-06 | V527: https://maharerait.maharashtra.gov.in/public/project/view/3869 | W527: https://www.maharera.maharashtra.gov.in/projects-search-result?project_state=27&project_district=518&page=18 | X527: 2026-10-11 | Y527: Verified (official listing) | Z527: reg no, project name, promoter, district, taluka, pincode, last modified, detail URL | AA527: project address, registration date, original completion date | AB527: Cross-checked against 5 fully downloaded official lists (deregistered, 3 abeyance lists, NCLT) and the Revoked search (4/9 pages collected - revoked status may be under-reported) | AC527: Revised/proposed completion date taken from official NCLT list
A528: R000527 | B528: P51800000345 | C528: LODHA ETERNIS NATURA A | D528: MACROTECH DEVELOPERS LIMITED | E528: D00539 | G528: Andheri | H528: 400093 | I528: Mumbai Suburban | J528: Mumbai MMR | K528: Mumbai Suburban | L528: 19.1224 | M528: 72.868464 | Q528: Registered - no adverse list match | R528: No | S528: No | U528: 2019-01-09 | V528: https://maharerait.maharashtra.gov.in/public/project/view/3336 | W528: https://www.maharera.maharashtra.gov.in/projects-search-result?project_state=27&project_district=518&page=13 | X528: 2026-10-11 | Y528: Verified (official listing) | Z528: reg no, project name, promoter, district, taluka, pincode, last modified, detail URL | AA528: project address, registration date, original completion date, revised completion date | AB528: Cross-checked against 5 fully downloaded official lists (deregistered, 3 abeyance lists, NCLT) and the Revoked search (4/9 pages collected - revoked status may be under-reported)
A529: R000528 | B529: P51800000347 | C529: RUNWAL SERENE | D529: Runwal Construction Private Limited | E529: D00821 | G529: Kurla | H529: 400088 | I529: Mumbai Suburban | J529: Mumbai MMR | K529: Mumbai Suburban | L529: 19.050856 | M529: 72.916361 | Q529: Registered - no adverse list match | R529: Yes | S529: No | U529: 2023-10-10 | V529: https://maharerait.maharashtra.gov.in/public/project/view/3376 | W529: https://www.maharera.maharashtra.gov.in/projects-search-result?project_state=27&project_district=518&page=13 | X529: 2026-10-11 | Y529: Verified (official listing) | Z529: reg no, project name, promoter, district, taluka, pincode, last modified, detail URL | AA529: project address, registration date, original completion date, revised completion date | AB529: Cross-checked against 5 fully downloaded official lists (deregistered, 3 abeyance lists, NCLT) and the Revoked search (4/9 pages collected - revoked status may be under-reported)
A530: R000529 | B530: P51800000359 | C530: PARMAR HERITAGE | D530: JITENDRA | E530: D00394 | G530: Andheri | H530: 400057 | I530: Mumbai Suburban | J530: Mumbai MMR | K530: Mumbai Suburban | L530: 19.12410830071659 | M530: 72.83420210593627 | Q530: Registered - no adverse list match | R530: Yes | S530: No | U530: 2023-08-02 | V530: https://maharerait.maharashtra.gov.in/public/project/view/3628 | W530: https://www.maharera.maharashtra.gov.in/projects-search-result?project_state=27&project_district=518&page=15 | X530: 2026-10-11 | Y530: Verified (official listing) | Z530: reg no, project name, promoter, district, taluka, pincode, last modified, detail URL | AA530: project address, registration date, original completion date, revised completion date | AB530: Cross-checked against 5 fully downloaded official lists (deregistered, 3 abeyance lists, NCLT) and the Revoked search (4/9 pages collected - revoked status may be under-reported)
A531: R000530 | B531: P51800000368 | C531: Harshail Dhanuka Residency | D531: HARSHMAAN CONSTRUCTION | E531: D00331 | G531: Andheri | H531: 400057 | I531: Mumbai Suburban | J531: Mumbai MMR | K531: Mumbai Suburban | L531: 19.098144 | M531: 72.847971 | Q531: Registered - no adverse list match | R531: No | S531: No | U531: 2017-07-15 | V531: https://maharerait.maharashtra.gov.in/public/project/view/2853 | W531: https://www.maharera.maharashtra.gov.in/projects-search-result?project_state=27&project_district=518&page=9 | X531: 2026-10-11 | Y531: Verified (official listing) | Z531: reg no, project name, promoter, district, taluka, pincode, last modified, detail URL | AA531: project address, registration date, original completion date, revised completion date | AB531: Cross-checked against 5 fully downloaded official lists (deregistered, 3 abeyance lists, NCLT) and the Revoked search (4/9 pages collected - revoked status may be under-reported)
A532: R000531 | B532: P51800000370 | C532: MIRABILIS | D532: SKYLINK HOSPITALITY LLP | E532: D01004 | G532: Mumbai | H532: 400055 | I532: Mumbai Suburban | J532: Mumbai MMR | K532: Mumbai Suburban | L532: 19.1538231 | M532: 72.8751786 | Q532: Registered - no adverse list match | R532: Yes | S532: No | U532: 2021-09-09 | V532: https://maharerait.maharashtra.gov.in/public/project/view/2315 | W532: https://www.maharera.maharashtra.gov.in/projects-search-result?project_state=27&project_district=518&page=7 | X532: 2026-10-11 | Y532: Verified (official listing) | Z532: reg no, project name, promoter, district, taluka, pincode, last modified, detail URL | AA532: project address, registration date, original completion date, revised completion date | AB532: Cross-checked against 5 fully downloaded official lists (deregistered, 3 abeyance lists, NCLT) and the Revoked search (4/9 pages collected - revoked status may be under-reported)
A533: R000532 | B533: P51800000372 | C533: HETALI ANUCHHAYA | D533: Hetali Enterprises | E533: D00344 | G533: Andheri | H533: 400058 | I533: Mumbai Suburban | J533: Mumbai MMR | K533: Mumbai Suburban | L533: 19.1227346 | M533: 72.8302013 | Q533: Registered - no adverse list match | R533: No | S533: No | U533: 2018-08-06 | V533: https://maharerait.maharashtra.gov.in/public/project/view/2417 | W533: https://www.maharera.maharashtra.gov.in/projects-search-result?project_state=27&project_district=518&page=7 | X533: 2026-10-11 | Y533: Verified (official listing) | Z533: reg no, project name, promoter, district, taluka, pincode, last modified, detail URL | AA533: project address, registration date, original completion date, revised completion date | AB533: Cross-checked against 5 fully downloaded official lists (deregistered, 3 abeyance lists, NCLT) and the Revoked search (4/9 pages collected - revoked status may be under-reported)
A534: R000533 | B534: P51800000373 | C534: Sudarshan Lands End | D534: Jagjit estate & Devlopment Co. Pvt. Ltd | E534: D00380 | G534: Borivali | H534: 400095 | I534: Mumbai Suburban | J534: Mumbai MMR | K534: Mumbai Suburban | L534: 19.1888023 | M534: 72.8197043 | Q534: Registered - no adverse list match | R534: Yes | S534: No | U534: 2018-11-30 | V534: https://maharerait.maharashtra.gov.in/public/project/view/1309 | W534: https://www.maharera.maharashtra.gov.in/projects-search-result?project_state=27&project_district=518&page=3 | X534: 2026-10-11 | Y534: Verified (official listing) | Z534: reg no, project name, promoter, district, taluka, pincode, last modified, detail URL | AA534: project address, registration date, original completion date, revised completion date | AB534: Cross-checked against 5 fully downloaded official lists (deregistered, 3 abeyance lists, NCLT) and the Revoked search (4/9 pages collected - revoked status may be under-reported)
A535: R000534 | B535: P51800000388 | C535: KANAKIA SEVENS | D535: KANAKIA SPACES REALTY PRIVATE LIMITED | E535: D00423 | G535: Andheri | H535: 400059 | I535: Mumbai Suburban | J535: Mumbai MMR | K535: Mumbai Suburban | L535: 19.1118641 | M535: 72.8790282 | Q535: Registered - no adverse list match | R535: No | S535: No | U535: 2017-07-15 | V535: https://maharerait.maharashtra.gov.in/public/project/view/2799 | W535: https://www.maharera.maharashtra.gov.in/projects-search-result?project_state=27&project_district=518&page=9 | X535: 2026-10-11 | Y535: Verified (official listing) | Z535: reg no, project name, promoter, district, taluka, pincode, last modified, detail URL | AA535: project address, registration date, original completion date, revised completion date | AB535: Cross-checked against 5 fully downloaded official lists (deregistered, 3 abeyance lists, NCLT) and the Revoked search (4/9 pages collected - revoked status may be under-reported)
A536: R000535 | B536: P51800000403 | C536: SRISHTI SOLITAIRE | D536: SIDDHIVINAYAK ENTERPRISE | E536: D00991 | G536: Kurla | H536: 400078 | I536: Mumbai Suburban | J536: Mumbai MMR | K536: Mumbai Suburban | L536: 19.0599836 | M536: 72.889999 | Q536: Registered - no adverse list match | R536: No | S536: No | U536: 2017-07-15 | V536: https://maharerait.maharashtra.gov.in/public/project/view/1727 | W536: https://www.maharera.maharashtra.gov.in/projects-search-result?project_state=27&project_district=518&page=5 | X536: 2026-10-11 | Y536: Verified (official listing) | Z536: reg no, project name, promoter, district, taluka, pincode, last modified, detail URL | AA536: project address, registration date, original completion date, revised completion date | AB536: Cross-checked against 5 fully downloaded official lists (deregistered, 3 abeyance lists, NCLT) and the Revoked search (4/9 pages collected - revoked status may be under-reported)
A537: R000536 | B537: P51800000408 | C537: Castle Rock A and B Wing | D537: HGP Community Pvt. Ltd. | E537: D00345 | G537: Kurla | H537: 400076 | I537: Mumbai Suburban | J537: Mumbai MMR | K537: Mumbai Suburban | L537: 19.115973649153528 | M537: 72.9129703823478 | Q537: Registered - no adverse list match | R537: No | S537: No | U537: 2019-05-17 | V537: https://maharerait.maharashtra.gov.in/public/project/view/3920 | W537: https://www.maharera.maharashtra.gov.in/projects-search-result?project_state=27&project_district=518&page=19 | X537: 2026-10-11 | Y537: Verified (official listing) | Z537: reg no, project name, promoter, district, taluka, pincode, last modified, detail URL | AA537: project address, registration date, original completion date, revised completion date | AB537: Cross-checked against 5 fully downloaded official lists (deregistered, 3 abeyance lists, NCLT) and the Revoked search (4/9 pages collected - revoked status may be under-reported)
A538: R000537 | B538: P51800000409 | C538: Mahavir Aria | D538: Milestone Developers | E538: D00580 | G538: Kurla | H538: 400077 | I538: Mumbai Suburban | J538: Mumbai MMR | K538: Mumbai Suburban | L538: 19.0778737 | M538: 72.9055627 | Q538: Registered - no adverse list match | R538: No | S538: No | U538: 2017-07-15 | V538: https://maharerait.maharashtra.gov.in/public/project/view/3802 | W538: https://www.maharera.maharashtra.gov.in/projects-search-result?project_state=27&project_district=518&page=17 | X538: 2026-10-11 | Y538: Verified (official listing) | Z538: reg no, project name, promoter, district, taluka, pincode, last modified, detail URL | AA538: project address, registration date, original completion date, revised completion date | AB538: Cross-checked against 5 fully downloaded official lists (deregistered, 3 abeyance lists, NCLT) and the Revoked search (4/9 pages collected - revoked status may be under-reported)
A539: R000538 | B539: P51800000418 | C539: BEAUPRIDE | D539: SHETH REALTORS | E539: D00918 | G539: Andheri | H539: 400050 | I539: Mumbai Suburban | J539: Mumbai MMR | K539: Mumbai Suburban | L539: 19.0551695 | M539: 72.8299518 | Q539: Registered - no adverse list match | R539: No | S539: No | U539: 2017-07-15 | V539: https://maharerait.maharashtra.gov.in/public/project/view/3850 | W539: https://www.maharera.maharashtra.gov.in/projects-search-result?project_state=27&project_district=518&page=18 | X539: 2026-10-11 | Y539: Verified (official listing) | Z539: reg no, project name, promoter, district, taluka, pincode, last modified, detail URL | AA539: project address, registration date, original completion date, revised completion date | AB539: Cross-checked against 5 fully downloaded official lists (deregistered, 3 abeyance lists, NCLT) and the Revoked search (4/9 pages collected - revoked status may be under-reported)
... A558: R000557 | B558: P51800000873 | C558: SHREE RASRAJ TOWER | D558: K MEHTA AND COMPANY | E558: D00400 | G558: Borivali | H558: 400092 | I558: Mumbai Suburban | J558: Mumbai MMR | K558: Mumbai Suburban | L558: 19.237014679441792 | M558: 72.8561188227402 | Q558: Registered - no adverse list match | R558: No | S558: No | U558: 2017-07-23 | V558: https://maharerait.maharashtra.gov.in/public/project/view/3713 | W558: https://www.maharera.maharashtra.gov.in/projects-search-result?project_state=27&project_district=518&page=16 | X558: 2026-10-11 | Y558: Verified (official listing) | Z558: reg no, project name, promoter, district, taluka, pincode, last modified, detail URL | AA558: project address, registration date, original completion date, revised completion date | AB558: Cross-checked against 5 fully downloaded official lists (deregistered, 3 abeyance lists, NCLT) and the Revoked search (4/9 pages collected - revoked status may be under-reported)
A559: R000558 | B559: P51800000956 | C559: Altavista - Phase 2 | D559: SPENTA ENCLAVE PRIVATE LIMITED | E559: D01017 | G559: Kurla | H559: 400071 | I559: Mumbai Suburban | J559: Mumbai MMR | K559: Mumbai Suburban | L559: 19.051547 | M559: 72.886466 | P559: 30-06-2025 | Q559: Registered - no adverse list match | R559: Yes | S559: No | T559: NCLT: Project status as on 31-01-2025: Active; Form 4 uploaded: N | U559: 2026-08-12 | V559: https://maharerait.maharashtra.gov.in/public/project/view/2897 | W559: https://www.maharera.maharashtra.gov.in/projects-search-result?project_state=27&project_district=518&page=9 | X559: 2026-10-11 | Y559: Verified (official listing) | Z559: reg no, project name, promoter, district, taluka, pincode, last modified, detail URL | AA559: project address, registration date, original completion date | AB559: Cross-checked against 5 fully downloaded official lists (deregistered, 3 abeyance lists, NCLT) and the Revoked search (4/9 pages collected - revoked status may be under-reported) | AC559: Revised/proposed completion date taken from official NCLT list
A560: R000559 | B560: P51800001050 | C560: Altavista - Phase 1 | D560: SPENTA ENCLAVE PRIVATE LIMITED | E560: D01017 | G560: Kurla | H560: 400071 | I560: Mumbai Suburban | J560: Mumbai MMR | K560: Mumbai Suburban | L560: 19.05176 | M560: 72.886643 | P560: 31-07-2024 | Q560: Registered - no adverse list match | R560: Yes | S560: No | T560: NCLT: Project status as on 31-01-2025: Lapsed; Form 4 uploaded: N | U560: 2023-09-25 | V560: https://maharerait.maharashtra.gov.in/public/project/view/2886 | W560: https://www.maharera.maharashtra.gov.in/projects-search-result?project_state=27&project_district=518&page=9 | X560: 2026-10-11 | Y560: Verified (official listing) | Z560: reg no, project name, promoter, district, taluka, pincode, last modified, detail URL | AA560: project address, registration date, original completion date | AB560: Cross-checked against 5 fully downloaded official lists (deregistered, 3 abeyance lists, NCLT) and the Revoked search (4/9 pages collected - revoked status may be under-reported) | AC560: Revised/proposed completion date taken from official NCLT list
A561: R000560 | B561: P51800001084 | C561: IDEAL CHSL | D561: NEUMEC INFRASTRUCTURE LLP | E561: D00649 | G561: Andheri | H561: 400049 | I561: Mumbai Suburban | J561: Mumbai MMR | K561: Mumbai Suburban | L561: 19.116335 | M561: 72.83182 | Q561: Registered - no adverse list match | R561: No | S561: No | U561: 2017-07-26 | V561: https://maharerait.maharashtra.gov.in/public/project/view/3668 | W561: https://www.maharera.maharashtra.gov.in/projects-search-result?project_state=27&project_district=518&page=15 | X561: 2026-10-11 | Y561: Verified (official listing) | Z561: reg no, project name, promoter, district, taluka, pincode, last modified, detail URL | AA561: project address, registration date, original completion date, revised completion date | AB561: Cross-checked against 5 fully downloaded official lists (deregistered, 3 abeyance lists, NCLT) and the Revoked search (4/9 pages collected - revoked status may be under-reported)
A562: R000561 | B562: P51800001115 | C562: GUNDECHA TRILLIUM | D562: SEA PRINCESS REALTY | E562: D00894 | G562: Borivali | H562: 400066 | I562: Mumbai Suburban | J562: Mumbai MMR | K562: Mumbai Suburban | L562: 19.215146 | M562: 72.870332 | Q562: Registered - no adverse list match | R562: No | S562: No | U562: 2017-07-26 | V562: https://maharerait.maharashtra.gov.in/public/project/view/3305 | W562: https://www.maharera.maharashtra.gov.in/projects-search-result?project_state=27&project_district=518&page=13 | X562: 2026-10-11 | Y562: Verified (official listing) | Z562: reg no, project name, promoter, district, taluka, pincode, last modified, detail URL | AA562: project address, registration date, original completion date, revised completion date | AB562: Cross-checked against 5 fully downloaded official lists (deregistered, 3 abeyance lists, NCLT) and the Revoked search (4/9 pages collected - revoked status may be under-reported)
A563: R000562 | B563: P51800001136 | C563: Neelyog Aashiyana | D563: Neelyog Construction Pvt Ltd | E563: D00640 | G563: Borivali | H563: 400067 | I563: Mumbai Suburban | J563: Mumbai MMR | K563: Mumbai Suburban | L563: 19.208314771533153 | M563: 72.8424597565529 | Q563: Registered - no adverse list match | R563: No | S563: No | U563: 2017-07-26 | V563: https://maharerait.maharashtra.gov.in/public/project/view/319 | W563: https://www.maharera.maharashtra.gov.in/projects-search-result?project_state=27&project_district=518&page=1 | X563: 2026-10-11 | Y563: Verified (official listing) | Z563: reg no, project name, promoter, district, taluka, pincode, last modified, detail URL | AA563: project address, registration date, original completion date, revised completion date | AB563: Cross-checked against 5 fully downloaded official lists (deregistered, 3 abeyance lists, NCLT) and the Revoked search (4/9 pages collected - revoked status may be under-reported)
...

Sheet Pune Projects
A1: Record ID | B1: MahaRERA Registration No. | C1: Project Name | D1: Promoter / Developer Name (as displayed) | E1: Developer ID | F1: Project Address | G1: Locality / Taluka (as displayed) | H1: Pincode | I1: District | J1: Region Group | K1: Sub-region | L1: Latitude | M1: Longitude | N1: Registration Date | O1: Original Completion Date | P1: Revised / Proposed Completion Date | Q1: Current Status (derived from official lists) | R1: Extension Certificate Shown | S1: Revocation / Lapse / Deregistration / Abeyance Indicated | T1: Status Flags Detail | U1: MahaRERA Last Modified | V1: Official Project Detail URL | W1: Source Listing URL | X1: Retrieved Date | Y1: Record Verification | Z1: Verified Fields | AA1: Missing / Unverified Fields | AB1: Status Verification | AC1: Notes
A2: R001311 | B2: P52100000008 | C2: Sai Saroj | D2: M/S Vighnaharta Developers | E2: D00531 | G2: Haveli | H2: 412101 | I2: Pune | J2: Pune | K2: Pune district | L2: 18.657929 | M2: 73.755236 | Q2: Registered - no adverse list match | R2: Yes | S2: No | U2: 2020-02-24 | V2: https://maharerait.maharashtra.gov.in/public/project/view/295 | W2: https://www.maharera.maharashtra.gov.in/projects-search-result?project_state=27&project_district=521&page=2 | X2: 2026-10-11 | Y2: Verified (official listing) | Z2: reg no, project name, promoter, district, taluka, pincode, last modified, detail URL | AA2: project address, registration date, original completion date, revised completion date | AB2: Cross-checked against 5 fully downloaded official lists (deregistered, 3 abeyance lists, NCLT) and the Revoked search (4/9 pages collected - revoked status may be under-reported)
A3: R001312 | B3: P52100000011 | C3: Yashwin Jeevan | D3: Vilas Javdekar & Sanjeevani Developers LLP | E3: D01143 | G3: Mulshi | H3: 411021 | I3: Pune | J3: Pune | K3: Pune district | L3: 18.562396 | M3: 73.757154 | Q3: Registered - no adverse list match | R3: No | S3: No | U3: 2017-05-26 | V3: https://maharerait.maharashtra.gov.in/public/project/view/131 | W3: https://www.maharera.maharashtra.gov.in/projects-search-result?project_state=27&project_district=521&page=1 | X3: 2026-10-11 | Y3: Verified (official listing) | Z3: reg no, project name, promoter, district, taluka, pincode, last modified, detail URL | AA3: project address, registration date, original completion date, revised completion date | AB3: Cross-checked against 5 fully downloaded official lists (deregistered, 3 abeyance lists, NCLT) and the Revoked search (4/9 pages collected - revoked status may be under-reported)
A4: R001313 | B4: P52100000012 | C4: Yashwin Anand | D4: Vilas Javdekar & Sanjeevani Developers LLP | E4: D01143 | G4: Mulshi | H4: 411021 | I4: Pune | J4: Pune | K4: Pune district | L4: 18.561534344887775 | M4: 73.75709679629517 | Q4: Registered - no adverse list match | R4: No | S4: No | U4: 2017-05-27 | V4: https://maharerait.maharashtra.gov.in/public/project/view/558 | W4: https://www.maharera.maharashtra.gov.in/projects-search-result?project_state=27&project_district=521&page=4 | X4: 2026-10-11 | Y4: Verified (official listing) | Z4: reg no, project name, promoter, district, taluka, pincode, last modified, detail URL | AA4: project address, registration date, original completion date, revised completion date | AB4: Cross-checked against 5 fully downloaded official lists (deregistered, 3 abeyance lists, NCLT) and the Revoked search (4/9 pages collected - revoked status may be under-reported)
A5: R001314 | B5: P52100000013 | C5: NEELAYA | D5: NAIKNAVARE BUILDCON PVT LTD | E5: D00616 | G5: Mawal | H5: 410506 | I5: Pune | J5: Pune | K5: Pune district | L5: 18.721281 | M5: 73.667479 | Q5: Registered - no adverse list match | R5: Yes | S5: No | U5: 2021-09-09 | V5: https://maharerait.maharashtra.gov.in/public/project/view/537 | W5: https://www.maharera.maharashtra.gov.in/projects-search-result?project_state=27&project_district=521&page=3 | X5: 2026-10-11 | Y5: Verified (official listing) | Z5: reg no, project name, promoter, district, taluka, pincode, last modified, detail URL | AA5: project address, registration date, original completion date, revised completion date | AB5: Cross-checked against 5 fully downloaded official lists (deregistered, 3 abeyance lists, NCLT) and the Revoked search (4/9 pages collected - revoked status may be under-reported)
A6: R001315 | B6: P52100000015 | C6: Sai Kunj | D6: Vighnaharta Developers & Promoters | E6: D01131 | G6: Haveli | H6: 412101 | I6: Pune | J6: Pune | K6: Pune district | L6: 18.6742528 | M6: 73.7301331 | Q6: Registered - no adverse list match | R6: No | S6: No | U6: 2017-05-31 | V6: https://maharerait.maharashtra.gov.in/public/project/view/432 | W6: https://www.maharera.maharashtra.gov.in/projects-search-result?project_state=27&project_district=521&page=3 | X6: 2026-10-11 | Y6: Verified (official listing) | Z6: reg no, project name, promoter, district, taluka, pincode, last modified, detail URL | AA6: project address, registration date, original completion date, revised completion date | AB6: Cross-checked against 5 fully downloaded official lists (deregistered, 3 abeyance lists, NCLT) and the Revoked search (4/9 pages collected - revoked status may be under-reported)
A7: R001316 | B7: P52100000029 | C7: Forest Trails Athashri - B2 | D7: PARANJAPE SCHEMES (CONSTRUCTION) LIMITED | E7: D00708 | G7: Mulshi | H7: 412115 | I7: Pune | J7: Pune | K7: Pune district | L7: 18.510944332937257 | M7: 73.73399236482089 | Q7: Registered - no adverse list match | R7: Yes | S7: No | U7: 2023-11-21 | V7: https://maharerait.maharashtra.gov.in/public/project/view/1053 | W7: https://www.maharera.maharashtra.gov.in/projects-search-result?project_state=27&project_district=521&page=7 | X7: 2026-10-11 | Y7: Verified (official listing) | Z7: reg no, project name, promoter, district, taluka, pincode, last modified, detail URL | AA7: project address, registration date, original completion date, revised completion date | AB7: Cross-checked against 5 fully downloaded official lists (deregistered, 3 abeyance lists, NCLT) and the Revoked search (4/9 pages collected - revoked status may be under-reported)
A8: R001317 | B8: P52100000035 | C8: SWAPNASAMRAT | D8: PARANJAPE SCHEMES (CONSTRUCTION) LTD | E8: D00709 | G8: Pune City | H8: 411004 | I8: Pune | J8: Pune | K8: Pune district | L8: 18.510033409517582 | M8: 73.83609847605749 | Q8: Registered - no adverse list match | R8: Yes | S8: No | U8: 2020-06-13 | V8: https://maharerait.maharashtra.gov.in/public/project/view/909 | W8: https://www.maharera.maharashtra.gov.in/projects-search-result?project_state=27&project_district=521&page=6 | X8: 2026-10-11 | Y8: Verified (official listing) | Z8: reg no, project name, promoter, district, taluka, pincode, last modified, detail URL | AA8: project address, registration date, original completion date, revised completion date | AB8: Cross-checked against 5 fully downloaded official lists (deregistered, 3 abeyance lists, NCLT) and the Revoked search (4/9 pages collected - revoked status may be under-reported)
A9: R001318 | B9: P52100000036 | C9: Silver Satyam | D9: Silver Satyam | E9: D00997 | G9: Haveli | H9: 412114 | I9: Pune | J9: Pune | K9: Pune district | L9: 18.6831112 | M9: 73.7977928 | Q9: Registered - no adverse list match | R9: No | S9: No | U9: 2017-06-16 | V9: https://maharerait.maharashtra.gov.in/public/project/view/1243 | W9: https://www.maharera.maharashtra.gov.in/projects-search-result?project_state=27&project_district=521&page=8 | X9: 2026-10-11 | Y9: Verified (official listing) | Z9: reg no, project name, promoter, district, taluka, pincode, last modified, detail URL | AA9: project address, registration date, original completion date, revised completion date | AB9: Cross-checked against 5 fully downloaded official lists (deregistered, 3 abeyance lists, NCLT) and the Revoked search (4/9 pages collected - revoked status may be under-reported)
A10: R001319 | B10: P52100000037 | C10: YASHWIN HINJAWADI | D10: Vilas Javdekar Eco Shelters Private Limited | E10: D01144 | G10: Mulshi | H10: 411057 | I10: Pune | J10: Pune | K10: Pune district | L10: 18.5973002 | M10: 73.69252359999996 | Q10: Registered - no adverse list match | R10: No | S10: No | U10: 2017-06-16 | V10: https://maharerait.maharashtra.gov.in/public/project/view/1060 | W10: https://www.maharera.maharashtra.gov.in/projects-search-result?project_state=27&project_district=521&page=7 | X10: 2026-10-11 | Y10: Verified (official listing) | Z10: reg no, project name, promoter, district, taluka, pincode, last modified, detail URL | AA10: project address, registration date, original completion date, revised completion date | AB10: Cross-checked against 5 fully downloaded official lists (deregistered, 3 abeyance lists, NCLT) and the Revoked search (4/9 pages collected - revoked status may be under-reported)
A11: R001320 | B11: P52100000045 | C11: SILVER OAK | D11: Anand Properties | E11: D00064 | G11: Haveli | H11: 412101 | I11: Pune | J11: Pune | K11: Pune district | L11: 18.6742528 | M11: 73.7301331 | Q11: Registered - no adverse list match | R11: No | S11: No | U11: 2017-06-16 | V11: https://maharerait.maharashtra.gov.in/public/project/view/723 | W11: https://www.maharera.maharashtra.gov.in/projects-search-result?project_state=27&project_district=521&page=5 | X11: 2026-10-11 | Y11: Verified (official listing) | Z11: reg no, project name, promoter, district, taluka, pincode, last modified, detail URL | AA11: project address, registration date, original completion date, revised completion date | AB11: Cross-checked against 5 fully downloaded official lists (deregistered, 3 abeyance lists, NCLT) and the Revoked search (4/9 pages collected - revoked status may be under-reported)
A12: R001321 | B12: P52100000051 | C12: Athashri Xion | D12: PSC Pacific | E12: D00756 | G12: Mulshi | H12: 411057 | I12: Pune | J12: Pune | K12: Pune district | L12: 18.593395 | M12: 73.745541 | Q12: Registered - no adverse list match | R12: No | S12: No | U12: 2017-06-19 | V12: https://maharerait.maharashtra.gov.in/public/project/view/183 | W12: https://www.maharera.maharashtra.gov.in/projects-search-result?project_state=27&project_district=521&page=2 | X12: 2026-10-11 | Y12: Verified (official listing) | Z12: reg no, project name, promoter, district, taluka, pincode, last modified, detail URL | AA12: project address, registration date, original completion date, revised completion date | AB12: Cross-checked against 5 fully downloaded official lists (deregistered, 3 abeyance lists, NCLT) and the Revoked search (4/9 pages collected - revoked status may be under-reported)
A13: R001322 | B13: P52100000054 | C13: Blue Ridge Project C Land T18 and T19 | D13: Paranjape Schemes (Construction) Ltd. | E13: D00709 | G13: Mulshi | H13: 411057 | I13: Pune | J13: Pune | K13: Pune district | L13: 18.575384414128326 | M13: 73.74246299024355 | Q13: Registered - no adverse list match | R13: No | S13: No | U13: 2020-04-21 | V13: https://maharerait.maharashtra.gov.in/public/project/view/1421 | W13: https://www.maharera.maharashtra.gov.in/projects-search-result?project_state=27&project_district=521&page=9 | X13: 2026-10-11 | Y13: Verified (official listing) | Z13: reg no, project name, promoter, district, taluka, pincode, last modified, detail URL | AA13: project address, registration date, original completion date, revised completion date | AB13: Cross-checked against 5 fully downloaded official lists (deregistered, 3 abeyance lists, NCLT) and the Revoked search (4/9 pages collected - revoked status may be under-reported)
... A57: R001366 | B57: P52100000236 | C57: FLORIDA RIVER BANK | D57: ONE EARTH | E57: D00690 | G57: Haveli | H57: 411036 | I57: Pune | J57: Pune | K57: Pune district | L57: 18.52928 | M57: 73.945706 | Q57: Registered - no adverse list match | R57: No | S57: No | U57: 2017-07-10 | V57: https://maharerait.maharashtra.gov.in/public/project/view/878 | W57: https://www.maharera.maharashtra.gov.in/projects-search-result?project_state=27&project_district=521&page=6 | X57: 2026-10-11 | Y57: Verified (official listing) | Z57: reg no, project name, promoter, district, taluka, pincode, last modified, detail URL | AA57: project address, registration date, original completion date, revised completion date | AB57: Cross-checked against 5 fully downloaded official lists (deregistered, 3 abeyance lists, NCLT) and the Revoked search (4/9 pages collected - revoked status may be under-reported)
A58: R001367 | B58: P52100000237 | C58: Dreams Lynnea A B wings | D58: Dreams Construction ( Pune) Pvt. Ltd. | E58: D00231 | G58: Haveli | H58: 412207 | I58: Pune | J58: Pune | K58: Pune district | L58: 18.5817469 | M58: 73.9817056 | P58: 30-09-2020 | Q58: Registered - no adverse list match | R58: Yes | S58: No | T58: NCLT: Project status as on 31-01-2025: Lapsed; Form 4 uploaded: N | U58: 2020-06-13 | V58: https://maharerait.maharashtra.gov.in/public/project/view/1375 | W58: https://www.maharera.maharashtra.gov.in/projects-search-result?project_state=27&project_district=521&page=9 | X58: 2026-10-11 | Y58: Verified (official listing) | Z58: reg no, project name, promoter, district, taluka, pincode, last modified, detail URL | AA58: project address, registration date, original completion date | AB58: Cross-checked against 5 fully downloaded official lists (deregistered, 3 abeyance lists, NCLT) and the Revoked search (4/9 pages collected - revoked status may be under-reported) | AC58: Revised/proposed completion date taken from official NCLT list
A59: R001368 | B59: P52100000241 | C59: Azure - A,C,D,E and F | D59: PARANJAPE SCHEMES (CONSTRUCTION) LTD | E59: D00709 | G59: Mulshi | H59: 411033 | I59: Pune | J59: Pune | K59: Pune district | L59: 18.612694430598342 | M59: 73.7514564232788 | Q59: Registered - no adverse list match | R59: No | S59: No | U59: 2017-07-10 | V59: https://maharerait.maharashtra.gov.in/public/project/view/1882 | W59: https://www.maharera.maharashtra.gov.in/projects-search-result?project_state=27&project_district=521&page=15 | X59: 2026-10-11 | Y59: Verified (official listing) | Z59: reg no, project name, promoter, district, taluka, pincode, last modified, detail URL | AA59: project address, registration date, original completion date, revised completion date | AB59: Cross-checked against 5 fully downloaded official lists (deregistered, 3 abeyance lists, NCLT) and the Revoked search (4/9 pages collected - revoked status may be under-reported)
A60: R001369 | B60: P52100000246 | C60: Woodsville Phase 3 Cluster B | D60: Pharande Promoters and Builders | E60: D00723 | G60: Haveli | H60: 412105 | I60: Pune | J60: Pune | K60: Pune district | L60: 18.672214806989885 | M60: 73.83776291883854 | Q60: Registered - no adverse list match | R60: No | S60: No | U60: 2017-07-10 | V60: https://maharerait.maharashtra.gov.in/public/project/view/2686 | W60: https://www.maharera.maharashtra.gov.in/projects-search-result?project_state=27&project_district=521&page=25 | X60: 2026-10-11 | Y60: Verified (official listing) | Z60: reg no, project name, promoter, district, taluka, pincode, last modified, detail URL | AA60: project address, registration date, original completion date, revised completion date | AB60: Cross-checked against 5 fully downloaded official lists (deregistered, 3 abeyance lists, NCLT) and the Revoked search (4/9 pages collected - revoked status may be under-reported)
A61: R001370 | B61: P52100000248 | C61: Dreams BelleVue D wing | D61: Dreams Raka Associates | E61: D00235 | G61: Mulshi | H61: 411021 | I61: Pune | J61: Pune | K61: Pune district | L61: 18.5052428 | M61: 73.7661129 | Q61: Registered - no adverse list match | R61: Yes | S61: No | U61: 2020-06-14 | V61: https://maharerait.maharashtra.gov.in/public/project/view/1749 | W61: https://www.maharera.maharashtra.gov.in/projects-search-result?project_state=27&project_district=521&page=14 | X61: 2026-10-11 | Y61: Verified (official listing) | Z61: reg no, project name, promoter, district, taluka, pincode, last modified, detail URL | AA61: project address, registration date, original completion date, revised completion date | AB61: Cross-checked against 5 fully downloaded official lists (deregistered, 3 abeyance lists, NCLT) and the Revoked search (4/9 pages collected - revoked status may be under-reported)
A62: R001371 | B62: P52100000249 | C62: Antheia C2 | D62: Mahindra Lifespace Developers limited | E62: D00543 | G62: Haveli | H62: 411018 | I62: Pune | J62: Pune | K62: Pune district | L62: 18.631371760139285 | M62: 73.80949572949976 | Q62: Registered - no adverse list match | R62: No | S62: No | U62: 2017-07-10 | V62: https://maharerait.maharashtra.gov.in/public/project/view/2747 | W62: https://www.maharera.maharashtra.gov.in/projects-search-result?project_state=27&project_district=521&page=26 | X62: 2026-10-11 | Y62: Verified (official listing) | Z62: reg no, project name, promoter, district, taluka, pincode, last modified, detail URL | AA62: project address, registration date, original completion date, revised completion date | AB62: Cross-checked against 5 fully downloaded official lists (deregistered, 3 abeyance lists, NCLT) and the Revoked search (4/9 pages collected - revoked status may be under-reported)
A63: R001372 | B63: P52100000252 | C63: SELENA B | D63: Kumar Construction and Properties Pvt Ltd | E63: D00463 | G63: Haveli | H63: 411021 | I63: Pune | J63: Pune | K63: Pune district | L63: 18.549277 | M63: 73.793088 | Q63: Registered - no adverse list match | R63: No | S63: No | U63: 2017-07-10 | V63: https://maharerait.maharashtra.gov.in/public/project/view/327 | W63: https://www.maharera.maharashtra.gov.in/projects-search-result?project_state=27&project_district=521&page=2 | X63: 2026-10-11 | Y63: Verified (official listing) | Z63: reg no, project name, promoter, district, taluka, pincode, last modified, detail URL | AA63: project address, registration date, original completion date, revised completion date | AB63: Cross-checked against 5 fully downloaded official lists (deregistered, 3 abeyance lists, NCLT) and the Revoked search (4/9 pages collected - revoked status may be under-reported)
A64: R001373 | B64: P52100000255 | C64: GANGA LEGEND A3 AND B3.. | D64: GOEL GANGA INDIA PVT LTD | E64: D00301 | G64: Pune City | H64: 411021 | I64: Pune | J64: Pune | K64: Pune district | L64: 18.5217065 | M64: 73.7747683 | Q64: Registered - no adverse list match | R64: No | S64: No | U64: 2018-03-01 | V64: https://maharerait.maharashtra.gov.in/public/project/view/2105 | W64: https://www.maharera.maharashtra.gov.in/projects-search-result?project_state=27&project_district=521&page=17 | X64: 2026-10-11 | Y64: Verified (official listing) | Z64: reg no, project name, promoter, district, taluka, pincode, last modified, detail URL | AA64: project address, registration date, original completion date, revised completion date | AB64: Cross-checked against 5 fully downloaded official lists (deregistered, 3 abeyance lists, NCLT) and the Revoked search (4/9 pages collected - revoked status may be under-reported)
A65: R001374 | B65: P52100000259 | C65: GANGA GLITZ F. BLDG | D65: GOEL GANGA INDIA PVT LTD | E65: D00301 | G65: Pune City | H65: 411001 | I65: Pune | J65: Pune | K65: Pune district | L65: 18.4608762 | M65: 73.91505669999992 | Q65: Registered - no adverse list match | R65: No | S65: No | U65: 2018-03-01 | V65: https://maharerait.maharashtra.gov.in/public/project/view/2061 | W65: https://www.maharera.maharashtra.gov.in/projects-search-result?project_state=27&project_district=521&page=16 | X65: 2026-10-11 | Y65: Verified (official listing) | Z65: reg no, project name, promoter, district, taluka, pincode, last modified, detail URL | AA65: project address, registration date, original completion date, revised completion date | AB65: Cross-checked against 5 fully downloaded official lists (deregistered, 3 abeyance lists, NCLT) and the Revoked search (4/9 pages collected - revoked status may be under-reported)
A66: R001375 | B66: P52100000275 | C66: PRISTINE PACIFIC PART-2 | D66: Melange Developers | E66: D00571 | G66: Haveli | H66: 411046 | I66: Pune | J66: Pune | K66: Pune district | L66: 18.451729 | M66: 73.844614 | Q66: Registered - no adverse list match | R66: No | S66: No | U66: 2017-07-12 | V66: https://maharerait.maharashtra.gov.in/public/project/view/1088 | W66: https://www.maharera.maharashtra.gov.in/projects-search-result?project_state=27&project_district=521&page=7 | X66: 2026-10-11 | Y66: Verified (official listing) | Z66: reg no, project name, promoter, district, taluka, pincode, last modified, detail URL | AA66: project address, registration date, original completion date, revised completion date | AB66: Cross-checked against 5 fully downloaded official lists (deregistered, 3 abeyance lists, NCLT) and the Revoked search (4/9 pages collected - revoked status may be under-reported)
A67: R001376 | B67: P52100000276 | C67: STKANWARRAMPALACIOPHASE1 | D67: VINOD PREMCHAND CHANDWANI | E67: D01150 | G67: Mulshi | H67: 411062 | I67: Pune | J67: Pune | K67: Pune district | L67: 18.5035327 | M67: 73.7615386 | Q67: Registered - no adverse list match | R67: No | S67: No | U67: 2017-07-12 | V67: https://maharerait.maharashtra.gov.in/public/project/view/2157 | W67: https://www.maharera.maharashtra.gov.in/projects-search-result?project_state=27&project_district=521&page=18 | X67: 2026-10-11 | Y67: Verified (official listing) | Z67: reg no, project name, promoter, district, taluka, pincode, last modified, detail URL | AA67: project address, registration date, original completion date, revised completion date | AB67: Cross-checked against 5 fully downloaded official lists (deregistered, 3 abeyance lists, NCLT) and the Revoked search (4/9 pages collected - revoked status may be under-reported)
A68: R001377 | B68: P52100000281 | C68: Antheia B4 | D68: Mahindra Lifespace Developers limited | E68: D00543 | G68: Haveli | H68: 411018 | I68: Pune | J68: Pune | K68: Pune district | L68: 18.6354307 | M68: 73.8124984 | Q68: Registered - no adverse list match | R68: No | S68: No | U68: 2017-07-12 | V68: https://maharerait.maharashtra.gov.in/public/project/view/2663 | W68: https://www.maharera.maharashtra.gov.in/projects-search-result?project_state=27&project_district=521&page=24 | X68: 2026-10-11 | Y68: Verified (official listing) | Z68: reg no, project name, promoter, district, taluka, pincode, last modified, detail URL | AA68: project address, registration date, original completion date, revised completion date | AB68: Cross-checked against 5 fully downloaded official lists (deregistered, 3 abeyance lists, NCLT) and the Revoked search (4/9 pages collected - revoked status may be under-reported)
A69: R001378 | B69: P52100000283 | C69: Lodha Belmondo St. Andrews B,C,D Villa 1 to 28 | D69: Macrotech Developers Limited | E69: D00539 | G69: Mawal | H69: 412101 | I69: Pune | J69: Pune | K69: Pune district | L69: 18.663458 | M69: 73.70872899999995 | Q69: Registered - no adverse list match | R69: No | S69: No | U69: 2018-09-28 | V69: https://maharerait.maharashtra.gov.in/public/project/view/2418 | W69: https://www.maharera.maharashtra.gov.in/projects-search-result?project_state=27&project_district=521&page=21 | X69: 2026-10-11 | Y69: Verified (official listing) | Z69: reg no, project name, promoter, district, taluka, pincode, last modified, detail URL | AA69: project address, registration date, original completion date, revised completion date | AB69: Cross-checked against 5 fully downloaded official lists (deregistered, 3 abeyance lists, NCLT) and the Revoked search (4/9 pages collected - revoked status may be under-reported)
A70: R001379 | B70: P52100000288 | C70: Pancham Phase II at Nanded City | D70: Nanded City Development & Construction Co. Ltd. | E70: D00623 | G70: Haveli | H70: 411068 | I70: Pune | J70: Pune | K70: Pune district | L70: 18.459451298432718 | M70: 73.7881230208709 | Q70: Registered - no adverse list match | R70: No | S70: No | U70: 2017-07-12 | V70: https://maharerait.maharashtra.gov.in/public/project/view/1705 | W70: https://www.maharera.maharashtra.gov.in/projects-search-result?project_state=27&project_district=521&page=13 | X70: 2026-10-11 | Y70: Verified (official listing) | Z70: reg no, project name, promoter, district, taluka, pincode, last modified, detail URL | AA70: project address, registration date, original completion date, revised completion date | AB70: Cross-checked against 5 fully downloaded official lists (deregistered, 3 abeyance lists, NCLT) and the Revoked search (4/9 pages collected - revoked status may be under-reported)
... A261: R001570 | B261: P52100021548 | C261: SPLENDOUR COUNTY WAGHOLI | D261: PS DEVELOPERS | E261: D00755 | G261: Haveli | H261: 412207 | I261: Pune | J261: Pune | K261: Pune district | L261: 18.585458 | M261: 73.9761235 | Q261: Registered - no adverse list match | R261: Yes | S261: No | U261: 2026-08-12 | V261: https://maharerait.maharashtra.gov.in/public/project/view/1726 | W261: https://www.maharera.maharashtra.gov.in/projects-search-result?project_state=27&project_district=521&page=13 | X261: 2026-10-11 | Y261: Verified (official listing) | Z261: reg no, project name, promoter, district, taluka, pincode, last modified, detail URL | AA261: project address, registration date, original completion date, revised completion date | AB261: Cross-checked against 5 fully downloaded official lists (deregistered, 3 abeyance lists, NCLT) and the Revoked search (4/9 pages collected - revoked status may be under-reported)

Sheet Mumbai MMR Projects
A1: Record ID | B1: MahaRERA Registration No. | C1: Project Name | D1: Promoter / Developer Name (as displayed) | E1: Developer ID | F1: Project Address | G1: Locality / Taluka (as displayed) | H1: Pincode | I1: District | J1: Region Group | K1: Sub-region | L1: Latitude | M1: Longitude | N1: Registration Date | O1: Original Completion Date | P1: Revised / Proposed Completion Date | Q1: Current Status (derived from official lists) | R1: Extension Certificate Shown | S1: Revocation / Lapse / Deregistration / Abeyance Indicated | T1: Status Flags Detail | U1: MahaRERA Last Modified | V1: Official Project Detail URL | W1: Source Listing URL | X1: Retrieved Date | Y1: Record Verification | Z1: Verified Fields | AA1: Missing / Unverified Fields | AB1: Status Verification | AC1: Notes
A2: R000001 | B2: P51700000001 | C2: MAYFAIR VISHWARAJA | D2: MAYFAIR HOUSING PRIVATE LIMITED | E2: D00568 | G2: Kalyan | H2: 421605 | I2: Thane | J2: Mumbai MMR | K2: Thane district (incl. Thane, Navi Mumbai-Thane side, Mira-Bhayandar, Kalyan-Dombivli, Bhiwandi, Ulhasnagar, Ambernath) | L2: 19.300941738924593 | M2: 73.21858197033089 | Q2: Registered - no adverse list match | R2: No | S2: No | U2: 2017-05-09 | V2: https://maharerait.maharashtra.gov.in/public/project/view/4 | W2: https://www.maharera.maharashtra.gov.in/projects-search-result?project_state=27&project_district=517&page=1 | X2: 2026-10-11 | Y2: Verified (official listing) | Z2: reg no, project name, promoter, district, taluka, pincode, last modified, detail URL | AA2: project address, registration date, original completion date, revised completion date | AB2: Cross-checked against 5 fully downloaded official lists (deregistered, 3 abeyance lists, NCLT) and the Revoked search (4/9 pages collected - revoked status may be under-reported)
A3: R000002 | B3: P51700000002 | C3: UNNATHI WOODS PHASE VII A | D3: UNNATHI ESTATES | E3: D01097 | G3: Thane | H3: 400615 | I3: Thane | J3: Mumbai MMR | K3: Thane district (incl. Thane, Navi Mumbai-Thane side, Mira-Bhayandar, Kalyan-Dombivli, Bhiwandi, Ulhasnagar, Ambernath) | L3: 19.268511 | M3: 72.97367 | Q3: Registered - no adverse list match | R3: No | S3: No | U3: 2018-04-12 | V3: https://maharerait.maharashtra.gov.in/public/project/view/3 | W3: https://www.maharera.maharashtra.gov.in/projects-search-result?project_state=27&project_district=517&page=1 | X3: 2026-10-11 | Y3: Verified (official listing) | Z3: reg no, project name, promoter, district, taluka, pincode, last modified, detail URL | AA3: project address, registration date, original completion date, revised completion date | AB3: Cross-checked against 5 fully downloaded official lists (deregistered, 3 abeyance lists, NCLT) and the Revoked search (4/9 pages collected - revoked status may be under-reported)
A4: R000003 | B4: P51700000006 | C4: THE PALMS | D4: METRO DEVELOPMENT | E4: D00576 | G4: Thane | H4: 400706 | I4: Thane | J4: Mumbai MMR | K4: Thane district (incl. Thane, Navi Mumbai-Thane side, Mira-Bhayandar, Kalyan-Dombivli, Bhiwandi, Ulhasnagar, Ambernath) | L4: 19.00971 | M4: 73.01719 | Q4: Registered - no adverse list match | R4: No | S4: No | U4: 2017-05-23 | V4: https://maharerait.maharashtra.gov.in/public/project/view/256 | W4: https://www.maharera.maharashtra.gov.in/projects-search-result?project_state=27&project_district=517&page=2 | X4: 2026-10-11 | Y4: Verified (official listing) | Z4: reg no, project name, promoter, district, taluka, pincode, last modified, detail URL | AA4: project address, registration date, original completion date, revised completion date | AB4: Cross-checked against 5 fully downloaded official lists (deregistered, 3 abeyance lists, NCLT) and the Revoked search (4/9 pages collected - revoked status may be under-reported)
A5: R000004 | B5: P51700000009 | C5: N G Silver Spring | D5: RNA Builders (NG) | E5: D00806 | G5: Thane | H5: 401107 | I5: Thane | J5: Mumbai MMR | K5: Thane district (incl. Thane, Navi Mumbai-Thane side, Mira-Bhayandar, Kalyan-Dombivli, Bhiwandi, Ulhasnagar, Ambernath) | L5: 19.2855196 | M5: 72.8692967 | Q5: Registered - no adverse list match | R5: No | S5: No | U5: 2017-05-23 | V5: https://maharerait.maharashtra.gov.in/public/project/view/825 | W5: https://www.maharera.maharashtra.gov.in/projects-search-result?project_state=27&project_district=517&page=2 | X5: 2026-10-11 | Y5: Verified (official listing) | Z5: reg no, project name, promoter, district, taluka, pincode, last modified, detail URL | AA5: project address, registration date, original completion date, revised completion date | AB5: Cross-checked against 5 fully downloaded official lists (deregistered, 3 abeyance lists, NCLT) and the Revoked search (4/9 pages collected - revoked status may be under-reported)
A6: R000005 | B6: P51700000038 | C6: THE WHITE VILLAS | D6: St. Angelo's VNCT Ventures Pvt. Ltd. | E6: D01024 | G6: Shahapur | H6: 420601 | I6: Thane | J6: Mumbai MMR | K6: Thane district (incl. Thane, Navi Mumbai-Thane side, Mira-Bhayandar, Kalyan-Dombivli, Bhiwandi, Ulhasnagar, Ambernath) | L6: 19.4559236 | M6: 73.3296037 | Q6: Registered - no adverse list match | R6: Yes | S6: No | U6: 2026-09-26 | V6: https://maharerait.maharashtra.gov.in/public/project/view/2491 | W6: https://www.maharera.maharashtra.gov.in/projects-search-result?project_state=27&project_district=517&page=4 | X6: 2026-10-11 | Y6: Verified (official listing) | Z6: reg no, project name, promoter, district, taluka, pincode, last modified, detail URL | AA6: project address, registration date, original completion date, revised completion date | AB6: Cross-checked against 5 fully downloaded official lists (deregistered, 3 abeyance lists, NCLT) and the Revoked search (4/9 pages collected - revoked status may be under-reported)
A7: R000006 | B7: P51700000053 | C7: GOLDSTAR DECENT HOMES | D7: GOLDSTAR SANKALP CONSTRUCTION | E7: D00305 | G7: Thane | H7: 401107 | I7: Thane | J7: Mumbai MMR | K7: Thane district (incl. Thane, Navi Mumbai-Thane side, Mira-Bhayandar, Kalyan-Dombivli, Bhiwandi, Ulhasnagar, Ambernath) | L7: 19.281762 | M7: 72.881768 | Q7: Registered - no adverse list match | R7: Yes | S7: No | U7: 2019-01-09 | V7: https://maharerait.maharashtra.gov.in/public/project/view/166 | W7: https://www.maharera.maharashtra.gov.in/projects-search-result?project_state=27&project_district=517&page=1 | X7: 2026-10-11 | Y7: Verified (official listing) | Z7: reg no, project name, promoter, district, taluka, pincode, last modified, detail URL | AA7: project address, registration date, original completion date, revised completion date | AB7: Cross-checked against 5 fully downloaded official lists (deregistered, 3 abeyance lists, NCLT) and the Revoked search (4/9 pages collected - revoked status may be under-reported)
A8: R000007 | B8: P51700000064 | C8: TULSI AAHAN | D8: RAJ GROUP | E8: D00777 | G8: Ambarnath | H8: 421503 | I8: Thane | J8: Mumbai MMR | K8: Thane district (incl. Thane, Navi Mumbai-Thane side, Mira-Bhayandar, Kalyan-Dombivli, Bhiwandi, Ulhasnagar, Ambernath) | L8: 19.1667854 | M8: 73.2367896 | Q8: Registered - no adverse list match | R8: No | S8: No | U8: 2017-06-22 | V8: https://maharerait.maharashtra.gov.in/public/project/view/1283 | W8: https://www.maharera.maharashtra.gov.in/projects-search-result?project_state=27&project_district=517&page=2 | X8: 2026-10-11 | Y8: Verified (official listing) | Z8: reg no, project name, promoter, district, taluka, pincode, last modified, detail URL | AA8: project address, registration date, original completion date, revised completion date | AB8: Cross-checked against 5 fully downloaded official lists (deregistered, 3 abeyance lists, NCLT) and the Revoked search (4/9 pages collected - revoked status may be under-reported)
A9: R000008 | B9: P51700000068 | C9: NG GRAND PLAZA PHASE I | D9: OM NAMAH SHIVAY DEVELOPERS PRIVATE LIMITED | E9: D00679 | G9: Thane | H9: 400701 | I9: Thane | J9: Mumbai MMR | K9: Thane district (incl. Thane, Navi Mumbai-Thane side, Mira-Bhayandar, Kalyan-Dombivli, Bhiwandi, Ulhasnagar, Ambernath) | L9: 19.118673 | M9: 72.992341 | Q9: Registered - no adverse list match | R9: No | S9: No | U9: 2017-06-22 | V9: https://maharerait.maharashtra.gov.in/public/project/view/2943 | W9: https://www.maharera.maharashtra.gov.in/projects-search-result?project_state=27&project_district=517&page=5 | X9: 2026-10-11 | Y9: Verified (official listing) | Z9: reg no, project name, promoter, district, taluka, pincode, last modified, detail URL | AA9: project address, registration date, original completion date, revised completion date | AB9: Cross-checked against 5 fully downloaded official lists (deregistered, 3 abeyance lists, NCLT) and the Revoked search (4/9 pages collected - revoked status may be under-reported)
A10: R000009 | B10: P51700000074 | C10: Juhi Serenity | D10: Vijaykumar Baldev Bajaj | E10: D01139 | G10: Thane | H10: 400701 | I10: Thane | J10: Mumbai MMR | K10: Thane district (incl. Thane, Navi Mumbai-Thane side, Mira-Bhayandar, Kalyan-Dombivli, Bhiwandi, Ulhasnagar, Ambernath) | L10: 19.118294 | M10: 72.996908 | Q10: Registered - no adverse list match | R10: No | S10: No | U10: 2017-06-28 | V10: https://maharerait.maharashtra.gov.in/public/project/view/3212 | W10: https://www.maharera.maharashtra.gov.in/projects-search-result?project_state=27&project_district=517&page=8 | X10: 2026-10-11 | Y10: Verified (official listing) | Z10: reg no, project name, promoter, district, taluka, pincode, last modified, detail URL | AA10: project address, registration date, original completion date, revised completion date | AB10: Cross-checked against 5 fully downloaded official lists (deregistered, 3 abeyance lists, NCLT) and the Revoked search (4/9 pages collected - revoked status may be under-reported)
A11: R000010 | B11: P51700000089 | C11: Eagleton | D11: ROMA BUILDERS PRIVATE LIMITED | E11: D00811 | G11: Thane | H11: 400607 | I11: Thane | J11: Mumbai MMR | K11: Thane district (incl. Thane, Navi Mumbai-Thane side, Mira-Bhayandar, Kalyan-Dombivli, Bhiwandi, Ulhasnagar, Ambernath) | L11: 19.24360352 | M11: 72.97722982 | Q11: Registered - no adverse list match | R11: No | S11: No | U11: 2017-06-29 | V11: https://maharerait.maharashtra.gov.in/public/project/view/3090 | W11: https://www.maharera.maharashtra.gov.in/projects-search-result?project_state=27&project_district=517&page=7 | X11: 2026-10-11 | Y11: Verified (official listing) | Z11: reg no, project name, promoter, district, taluka, pincode, last modified, detail URL | AA11: project address, registration date, original completion date, revised completion date | AB11: Cross-checked against 5 fully downloaded official lists (deregistered, 3 abeyance lists, NCLT) and the Revoked search (4/9 pages collected - revoked status may be under-reported)
A12: R000011 | B12: P51700000091 | C12: Hampton | D12: ROMA BUILDERS PRIVATE LIMITED | E12: D00811 | G12: Thane | H12: 400607 | I12: Thane | J12: Mumbai MMR | K12: Thane district (incl. Thane, Navi Mumbai-Thane side, Mira-Bhayandar, Kalyan-Dombivli, Bhiwandi, Ulhasnagar, Ambernath) | L12: 19.24360352 | M12: 72.97722982 | Q12: Registered - no adverse list match | R12: No | S12: No | U12: 2017-06-30 | V12: https://maharerait.maharashtra.gov.in/public/project/view/3293 | W12: https://www.maharera.maharashtra.gov.in/projects-search-result?project_state=27&project_district=517&page=8 | X12: 2026-10-11 | Y12: Verified (official listing) | Z12: reg no, project name, promoter, district, taluka, pincode, last modified, detail URL | AA12: project address, registration date, original completion date, revised completion date | AB12: Cross-checked against 5 fully downloaded official lists (deregistered, 3 abeyance lists, NCLT) and the Revoked search (4/9 pages collected - revoked status may be under-reported)
